Workbook

Sheet Base Consolidada
A1: Marca | B1: Responsável BDR | C1: Responsável Closer | D1: Status | E1: Status Completo | F1: Classificação | G1: Data do último FUP | H1: FCA - Qual próximo passo? | I1: 1. Iniciado | J1: 2. Primeiro Contato com a marca | K1: 3. Apresentação | L1: 4. Diagnóstico | M1: 5. Demo/Showroom | N1: 6. Negociação | O1: 7. Piloto | P1: 8. Contrato enviado | Q1: 9. Contrato assinado | R1: 10. Perdido | S1: 11. Stand by | T1: 12. Orgânico | U1: 13. Reativado | V1: Motivo da perda/stand by | W1: Mensalidade | X1: Tempo de contrato | Y1: Setup | Z1: Implantação | AA1: Qtd lojas físicas | AB1: Marca TOP KA | AC1: Marca no BP | AD1: PDV atual | AE1: Qtd de lojas | AF1: Mês de início | AG1: Qtd de meses | AH1: Qtd Lojas físicas qualificadas | AI1: Faturamento qualificado | AJ1: PDV/integradora atual | AK1: Tipo de serviço qualificado | AL1: Delivery abriu porta? | AM1: Base Elegível | AN1: Base Novos Produtos | AO1: Dias último FUP | AP1: Estado | AQ1: Coordenador Delivery | AR1: Executivo Delivery | AS1: Head Delivery | AT1: Gerente Delivery | AU1: Antigo Resp | AV1: Base Comer Fora | AW1: Prioridade Comer Fora | AX1: Ataque Comer Fora | AY1: PDV atual (2) | AZ1: Culinária | BA1: Ticket Médio | BB1: Perfil operacional | BC1: Localização Geográfica | BD1: Faturamento da rede | BE1: Lead Scoring | BF1: Percentual de Aderencia | BG1: Comparativo (Integradora atual x 3S) | BH1: Software Atual | BI1: Share Atual (%)
A2: =IFERROR(__xludf.DUMMYFUNCTION("IMPORTRANGE(""https://docs.google.com/spreadsheets/d/1fHelesWk1_KVNNgiTqliLjSdm_xdxzuv79w5l7MdQUk"",""CRM!B5:BA1707"")"),"A PIZZA DA MOOCA") -> A PIZZA DA MOOCA | B2: =IFERROR(__xludf.DUMMYFUNCTION("""COMPUTED_VALUE"""),"Lídia Esteves") -> Lídia Esteves | C2: =IFERROR(__xludf.DUMMYFUNCTION("""COMPUTED_VALUE"""),"Gabriela Roma") -> Gabriela Roma | D2: =IFERROR(__xludf.DUMMYFUNCTION("""COMPUTED_VALUE"""),"4. Diagnóstico") -> 4. Diagnóstico | E2: =IFERROR(__xludf.DUMMYFUNCTION("""COMPUTED_VALUE"""),"Pré-vendas - Em validação técnica") -> Pré-vendas - Em validação técnica | F2: =IFERROR(__xludf.DUMMYFUNCTION("""COMPUTED_VALUE"""),"P") -> P | G2: =IFERROR(__xludf.DUMMYFUNCTION("""COMPUTED_VALUE"""),46155.0) -> 46155 | H2: =IFERROR(__xludf.DUMMYFUNCTION("""COMPUTED_VALUE"""),"Agenda 12/05 presencial com a Rafa, parceiro tem interesse em colocar totem em 1 das lojas, sao 4 lojas no totem, só que 3 socios diferentes, o cliente que falamos ontem Derek é sócio da pizza onesta e pizza da mocca shop, usa aloha e quer mudar de pdv pr"&"a ter totem gratuito por ser do ifood, vamos enviar proposta mas nao sabemos se irá avanças por querer serviço gratuito do ifood, Samuca encontrará o socio de todas as lojas em chicago e vai conversar com ele") -> Agenda 12/05 presencial com a Rafa, parceiro tem interesse em colocar totem em 1 das lojas, sao 4 lojas no totem, só que 3 socios diferentes, o cliente que falamos ontem Derek é sócio da pizza onesta e pizza da mocca shop, usa aloha e quer mudar de pdv pra ter totem gratuito por ser do ifood, vamos enviar proposta mas nao sabemos se irá avanças por querer serviço gratuito do ifood, Samuca encontrará o socio de todas as lojas em chicago e vai conversar com ele | I2: =IFERROR(__xludf.DUMMYFUNCTION("""COMPUTED_VALUE"""),46118.67255412037) -> 46118.673 | J2: =IFERROR(__xludf.DUMMYFUNCTION("""COMPUTED_VALUE"""),46155.48445200232) -> 46155.484 | K2: =IFERROR(__xludf.DUMMYFUNCTION("""COMPUTED_VALUE"""),46155.484533877316) -> 46155.485 | L2: =IFERROR(__xludf.DUMMYFUNCTION("""COMPUTED_VALUE"""),46155.48459680556) -> 46155.485 | AA2: =IFERROR(__xludf.DUMMYFUNCTION("""COMPUTED_VALUE"""),4.0) -> 4 | AB2: =IFERROR(__xludf.DUMMYFUNCTION("""COMPUTED_VALUE"""),"CE") -> CE | AC2: =IFERROR(__xludf.DUMMYFUNCTION("""COMPUTED_VALUE"""),"Sim") -> Sim | AD2: =IFERROR(__xludf.DUMMYFUNCTION("""COMPUTED_VALUE"""),"Ifood") -> Ifood | AH2: =IFERROR(__xludf.DUMMYFUNCTION("""COMPUTED_VALUE"""),4.0) -> 4 | AI2: =IFERROR(__xludf.DUMMYFUNCTION("""COMPUTED_VALUE"""),0.0) -> 0 | AJ2: =IFERROR(__xludf.DUMMYFUNCTION("""COMPUTED_VALUE"""),"linx e aloha") -> linx e aloha | AK2: =IFERROR(__xludf.DUMMYFUNCTION("""COMPUTED_VALUE"""),"table sevice, quick service") -> table sevice, quick service | AL2: =IFERROR(__xludf.DUMMYFUNCTION("""COMPUTED_VALUE"""),"SIM") -> SIM | AM2: =IFERROR(__xludf.DUMMYFUNCTION("""COMPUTED_VALUE"""),"FY27") -> FY27 | AO2: =IFERROR(__xludf.DUMMYFUNCTION("""COMPUTED_VALUE"""),60.0) -> 60 | AP2: =IFERROR(__xludf.DUMMYFUNCTION("""COMPUTED_VALUE"""),"SP") -> SP | AQ2: =IFERROR(__xludf.DUMMYFUNCTION("""COMPUTED_VALUE"""),"GABRIEL CAMACHO") -> GABRIEL CAMACHO | AR2: =IFERROR(__xludf.DUMMYFUNCTION("""COMPUTED_VALUE"""),"KAIQUE RIBEIRO") -> KAIQUE RIBEIRO | AS2: =IFERROR(__xludf.DUMMYFUNCTION("""COMPUTED_VALUE"""),"NATHALIE MERTENS") -> NATHALIE MERTENS | AT2: =IFERROR(__xludf.DUMMYFUNCTION("""COMPUTED_VALUE"""),"MATHEUS LESSA") -> MATHEUS LESSA | AU2: =IFERROR(__xludf.DUMMYFUNCTION("""COMPUTED_VALUE"""),0.0) -> 0 | AV2: =IFERROR(__xludf.DUMMYFUNCTION("""COMPUTED_VALUE"""),0.0) -> 0 | AW2: =IFERROR(__xludf.DUMMYFUNCTION("""COMPUTED_VALUE"""),0.0) -> 0 | AX2: =IFERROR(__xludf.DUMMYFUNCTION("""COMPUTED_VALUE"""),0.0) -> 0 | AZ2: =IFERROR(__xludf.DUMMYFUNCTION("""COMPUTED_VALUE"""),"Brasileira") -> Brasileira | BA2: =IFERROR(__xludf.DUMMYFUNCTION("ARRAYFORMULA(IFERROR(VLOOKUP(A2:A1000,IMPORTRANGE(""https://docs.google.com/spreadsheets/d/15k1NdSDPraw4VxeDarc9u5amYqhWqDW8MjQ0Lzs-lQc"",""LOTE_1_ENRIQUECIDO.csv!A:I""),3,0),""""))"),95.0) -> 95 | BB2: =IFERROR(__xludf.DUMMYFUNCTION("ARRAYFORMULA(IFERROR(VLOOKUP(A2:A1000,IMPORTRANGE(""https://docs.google.com/spreadsheets/d/15k1NdSDPraw4VxeDarc9u5amYqhWqDW8MjQ0Lzs-lQc"",""LOTE_1_ENRIQUECIDO.csv!A:I""),4,0),""""))"),"Fast Casual - Pizza Napoletana") -> Fast Casual - Pizza Napoletana | BC2: =IFERROR(__xludf.DUMMYFUNCTION("ARRAYFORMULA(IFERROR(VLOOKUP(A2:A1000,IMPORTRANGE(""https://docs.google.com/spreadsheets/d/15k1NdSDPraw4VxeDarc9u5amYqhWqDW8MjQ0Lzs-lQc"",""LOTE_1_ENRIQUECIDO.csv!A:I""),5,0),""""))"),"São Paulo/SP (3 unidades)") -> São Paulo/SP (3 unidades) | BD2: =IFERROR(__xludf.DUMMYFUNCTION("ARRAYFORMULA(IFERROR(VLOOKUP(A2:A1000,IMPORTRANGE(""https://docs.google.com/spreadsheets/d/15k1NdSDPraw4VxeDarc9u5amYqhWqDW8MjQ0Lzs-lQc"",""LOTE_1_ENRIQUECIDO.csv!A:I""),6,0),""""))"),"") | BE2: =IFERROR(__xludf.DUMMYFUNCTION("ARRAYFORMULA(IFERROR(VLOOKUP(A2:A1000,IMPORTRANGE(""https://docs.google.com/spreadsheets/d/15k1NdSDPraw4VxeDarc9u5amYqhWqDW8MjQ0Lzs-lQc"",""LOTE_1_ENRIQUECIDO.csv!A:I""),7,0),""""))"),65.0) -> 65 | BF2: =IFERROR(__xludf.DUMMYFUNCTION("ARRAYFORMULA(IFERROR(VLOOKUP(A2:A1000,IMPORTRANGE(""https://docs.google.com/spreadsheets/d/15k1NdSDPraw4VxeDarc9u5amYqhWqDW8MjQ0Lzs-lQc"",""LOTE_1_ENRIQUECIDO.csv!A:I""),8,0),""""))"),0.75) -> 0.75 | BG2: =IFERROR(__xludf.DUMMYFUNCTION("ARRAYFORMULA(IFERROR(VLOOKUP(A2:A1000,IMPORTRANGE(""https://docs.google.com/spreadsheets/d/15k1NdSDPraw4VxeDarc9u5amYqhWqDW8MjQ0Lzs-lQc"",""LOTE_1_ENRIQUECIDO.csv!A:I""),9,0),""""))"),"Aderência forte ao 3S: PDV atual não identificado. 3S oferece PDV robusto, KDS integrado e mobilidade (3SGO) para gestão em tempo real - ideal para operações multi-canal.") -> Aderência forte ao 3S: PDV atual não identificado. 3S oferece PDV robusto, KDS integrado e mobilidade (3SGO) para gestão em tempo real - ideal para operações multi-canal. | BH2: {=IFERROR(VLOOKUP(A2:A1000,'_Fonte_A2'!K:X,13,0),"")} -> Stone Co. | BI2: {=IFERROR(VLOOKUP(A2:A1000,'_Fonte_A2'!K:X,14,0),"")} -> 0.44444444
A3: =IFERROR(__xludf.DUMMYFUNCTION("""COMPUTED_VALUE"""),"ACAI BEAT") -> ACAI BEAT | B3: =IFERROR(__xludf.DUMMYFUNCTION("""COMPUTED_VALUE"""),"Lídia Esteves") -> Lídia Esteves | C3: =IFERROR(__xludf.DUMMYFUNCTION("""COMPUTED_VALUE"""),"Gabriela Roma") -> Gabriela Roma | D3: =IFERROR(__xludf.DUMMYFUNCTION("""COMPUTED_VALUE"""),"0. Não Iniciado") -> 0. Não Iniciado | F3: =IFERROR(__xludf.DUMMYFUNCTION("""COMPUTED_VALUE"""),"M") -> M | AA3: =IFERROR(__xludf.DUMMYFUNCTION("""COMPUTED_VALUE"""),30.0) -> 30 | AB3: =IFERROR(__xludf.DUMMYFUNCTION("""COMPUTED_VALUE"""),"-") -> - | AC3: =IFERROR(__xludf.DUMMYFUNCTION("""COMPUTED_VALUE"""),"Sim") -> Sim | AD3: =IFERROR(__xludf.DUMMYFUNCTION("""COMPUTED_VALUE"""),0.0) -> 0 | AM3: =IFERROR(__xludf.DUMMYFUNCTION("""COMPUTED_VALUE"""),"FY27") -> FY27 | AO3: =IFERROR(__xludf.DUMMYFUNCTION("""COMPUTED_VALUE"""),45553.0) -> 45553 | AP3: =IFERROR(__xludf.DUMMYFUNCTION("""COMPUTED_VALUE"""),"RJ") -> RJ | AQ3: =IFERROR(__xludf.DUMMYFUNCTION("""COMPUTED_VALUE"""),"EMILLY BIASI") -> EMILLY BIASI | AR3: =IFERROR(__xludf.DUMMYFUNCTION("""COMPUTED_VALUE"""),0.0) -> 0 | AS3: =IFERROR(__xludf.DUMMYFUNCTION("""COMPUTED_VALUE"""),"ALAN HADDAD") -> ALAN HADDAD | AT3: =IFERROR(__xludf.DUMMYFUNCTION("""COMPUTED_VALUE"""),"ISABELA DINIZ") -> ISABELA DINIZ | AU3: =IFERROR(__xludf.DUMMYFUNCTION("""COMPUTED_VALUE"""),0.0) -> 0 | AV3: =IFERROR(__xludf.DUMMYFUNCTION("""COMPUTED_VALUE"""),0.0) -> 0 | AW3: =IFERROR(__xludf.DUMMYFUNCTION("""COMPUTED_VALUE"""),0.0) -> 0 | AX3: =IFERROR(__xludf.DUMMYFUNCTION("""COMPUTED_VALUE"""),0.0) -> 0 | AY3: =IFERROR(__xludf.DUMMYFUNCTION("""COMPUTED_VALUE"""),"Cardápio Web") -> Cardápio Web | AZ3: =IFERROR(__xludf.DUMMYFUNCTION("""COMPUTED_VALUE"""),"Saudável") -> Saudável | BA3: =IFERROR(__xludf.DUMMYFUNCTION("""COMPUTED_VALUE"""),30.0) -> 30 | BB3: =IFERROR(__xludf.DUMMYFUNCTION("""COMPUTED_VALUE"""),"QSR - Açaí Bowl") -> QSR - Açaí Bowl | BC3: =IFERROR(__xludf.DUMMYFUNCTION("""COMPUTED_VALUE"""),"MT, SP (interior), MG, RJ") -> MT, SP (interior), MG, RJ | BE3: =IFERROR(__xludf.DUMMYFUNCTION("""COMPUTED_VALUE"""),75.0) -> 75 | BF3: =IFERROR(__xludf.DUMMYFUNCTION("""COMPUTED_VALUE"""),0.9) -> 0.9 | BG3: =IFERROR(__xludf.DUMMYFUNCTION("""COMPUTED_VALUE"""),"Alta aderência ao 3S: PDV atual não identificado. 3S oferece Kiosk nativo, Hub Delivery integrado e gestão centralizada multi-loja - diferenciais competitivos para expansão e redução de filas.") -> Alta aderência ao 3S: PDV atual não identificado. 3S oferece Kiosk nativo, Hub Delivery integrado e gestão centralizada multi-loja - diferenciais competitivos para expansão e redução de filas. | BH3: Cardápio Web | BI3: 0.66666667
A4: =IFERROR(__xludf.DUMMYFUNCTION("""COMPUTED_VALUE"""),"ACAI DA CIDADE") -> ACAI DA CIDADE | B4: =IFERROR(__xludf.DUMMYFUNCTION("""COMPUTED_VALUE"""),"João Biagiotti") -> João Biagiotti | C4: =IFERROR(__xludf.DUMMYFUNCTION("""COMPUTED_VALUE"""),"Diego Santos") -> Diego Santos | D4: =IFERROR(__xludf.DUMMYFUNCTION("""COMPUTED_VALUE"""),"0. Não Iniciado") -> 0. Não Iniciado | F4: =IFERROR(__xludf.DUMMYFUNCTION("""COMPUTED_VALUE"""),"P") -> P | AA4: =IFERROR(__xludf.DUMMYFUNCTION("""COMPUTED_VALUE"""),14.0) -> 14 | AB4: =IFERROR(__xludf.DUMMYFUNCTION("""COMPUTED_VALUE"""),"CE") -> CE | AC4: =IFERROR(__xludf.DUMMYFUNCTION("""COMPUTED_VALUE"""),"Sim") -> Sim | AD4: =IFERROR(__xludf.DUMMYFUNCTION("""COMPUTED_VALUE"""),0.0) -> 0 | AM4: =IFERROR(__xludf.DUMMYFUNCTION("""COMPUTED_VALUE"""),"FY27") -> FY27 | AO4: =IFERROR(__xludf.DUMMYFUNCTION("""COMPUTED_VALUE"""),45553.0) -> 45553 | AP4: =IFERROR(__xludf.DUMMYFUNCTION("""COMPUTED_VALUE"""),"SP") -> SP | AQ4: =IFERROR(__xludf.DUMMYFUNCTION("""COMPUTED_VALUE"""),"CARLOS ALBRECHT") -> CARLOS ALBRECHT | AR4: =IFERROR(__xludf.DUMMYFUNCTION("""COMPUTED_VALUE"""),0.0) -> 0 | AS4: =IFERROR(__xludf.DUMMYFUNCTION("""COMPUTED_VALUE"""),"FABIO DONATO") -> FABIO DONATO | AT4: =IFERROR(__xludf.DUMMYFUNCTION("""COMPUTED_VALUE"""),"GILSON JUNIOR") -> GILSON JUNIOR | AU4: =IFERROR(__xludf.DUMMYFUNCTION("""COMPUTED_VALUE"""),0.0) -> 0 | AV4: =IFERROR(__xludf.DUMMYFUNCTION("""COMPUTED_VALUE"""),0.0) -> 0 | AW4: =IFERROR(__xludf.DUMMYFUNCTION("""COMPUTED_VALUE"""),0.0) -> 0 | AX4: =IFERROR(__xludf.DUMMYFUNCTION("""COMPUTED_VALUE"""),0.0) -> 0 | AZ4: =IFERROR(__xludf.DUMMYFUNCTION("""COMPUTED_VALUE"""),"Açaí") -> Açaí | BA4: =IFERROR(__xludf.DUMMYFUNCTION("""COMPUTED_VALUE"""),25.0) -> 25 | BB4: =IFERROR(__xludf.DUMMYFUNCTION("""COMPUTED_VALUE"""),"QSR - Açaí") -> QSR - Açaí | BC4: =IFERROR(__xludf.DUMMYFUNCTION("""COMPUTED_VALUE"""),"Interior SP (Jundiaí, Campinas, Piracicaba)") -> Interior SP (Jundiaí, Campinas, Piracicaba) | BE4: =IFERROR(__xludf.DUMMYFUNCTION("""COMPUTED_VALUE"""),70.0) -> 70 | BF4: =IFERROR(__xludf.DUMMYFUNCTION("""COMPUTED_VALUE"""),0.9) -> 0.9 | BG4: =IFERROR(__xludf.DUMMYFUNCTION("""COMPUTED_VALUE"""),"Alta aderência ao 3S: PDV atual não identificado. 3S oferece Kiosk nativo, Hub Delivery integrado e gestão centralizada multi-loja - diferenciais competitivos para expansão e redução de filas.") -> Alta aderência ao 3S: PDV atual não identificado. 3S oferece Kiosk nativo, Hub Delivery integrado e gestão centralizada multi-loja - diferenciais competitivos para expansão e redução de filas. | BH4: Get Soft Software House Tecnologia Da Informacao Ltda | BI4: 0.85714286
A5: =IFERROR(__xludf.DUMMYFUNCTION("""COMPUTED_VALUE"""),"ACAI DA HORA - CONTA MARCA") -> ACAI DA HORA - CONTA MARCA | B5: =IFERROR(__xludf.DUMMYFUNCTION("""COMPUTED_VALUE"""),"João Biagiotti") -> João Biagiotti | C5: =IFERROR(__xludf.DUMMYFUNCTION("""COMPUTED_VALUE"""),"Diego Santos") -> Diego Santos | D5: =IFERROR(__xludf.DUMMYFUNCTION("""COMPUTED_VALUE"""),"9. Contrato assinado") -> 9. Contrato assinado | F5: =IFERROR(__xludf.DUMMYFUNCTION("""COMPUTED_VALUE"""),"P") -> P | O5: =IFERROR(__xludf.DUMMYFUNCTION("""COMPUTED_VALUE"""),46128.44601299769) -> 46128.446 | W5: =IFERROR(__xludf.DUMMYFUNCTION("""COMPUTED_VALUE"""),500.0) -> 500 | X5: =IFERROR(__xludf.DUMMYFUNCTION("""COMPUTED_VALUE"""),24.0) -> 24 | Y5: =IFERROR(__xludf.DUMMYFUNCTION("""COMPUTED_VALUE"""),1200.0) -> 1200 | Z5: =IFERROR(__xludf.DUMMYFUNCTION("""COMPUTED_VALUE"""),3000.0) -> 3000 | AA5: =IFERROR(__xludf.DUMMYFUNCTION("""COMPUTED_VALUE"""),14.0) -> 14 | AB5: =IFERROR(__xludf.DUMMYFUNCTION("""COMPUTED_VALUE"""),"CE") -> CE | AC5: =IFERROR(__xludf.DUMMYFUNCTION("""COMPUTED_VALUE"""),"Sim") -> Sim | AD5: =IFERROR(__xludf.DUMMYFUNCTION("""COMPUTED_VALUE"""),"Ifood") -> Ifood | AE5: =IFERROR(__xludf.DUMMYFUNCTION("""COMPUTED_VALUE"""),2.0) -> 2 | AF5: =IFERROR(__xludf.DUMMYFUNCTION("""COMPUTED_VALUE"""),46113.0) -> 46113 | AG5: =IFERROR(__xludf.DUMMYFUNCTION("""COMPUTED_VALUE"""),"2 meses") -> 2 meses | AM5: =IFERROR(__xludf.DUMMYFUNCTION("""COMPUTED_VALUE"""),"FY27") -> FY27 | AO5: =IFERROR(__xludf.DUMMYFUNCTION("""COMPUTED_VALUE"""),45553.0) -> 45553 | AP5: =IFERROR(__xludf.DUMMYFUNCTION("""COMPUTED_VALUE"""),"MG") -> MG | AQ5: =IFERROR(__xludf.DUMMYFUNCTION("""COMPUTED_VALUE"""),"TAMIRES DIAS") -> TAMIRES DIAS | AR5: =IFERROR(__xludf.DUMMYFUNCTION("""COMPUTED_VALUE"""),"MARIANA ACRUX") -> MARIANA ACRUX | AS5: =IFERROR(__xludf.DUMMYFUNCTION("""COMPUTED_VALUE"""),"#REF!") -> #REF! | AT5: =IFERROR(__xludf.DUMMYFUNCTION("""COMPUTED_VALUE"""),"#REF!") -> #REF! | AU5: =IFERROR(__xludf.DUMMYFUNCTION("""COMPUTED_VALUE"""),"#REF!") -> #REF! | AV5: =IFERROR(__xludf.DUMMYFUNCTION("""COMPUTED_VALUE"""),"#REF!") -> #REF! | AW5: =IFERROR(__xludf.DUMMYFUNCTION("""COMPUTED_VALUE"""),"#REF!") -> #REF! | AX5: =IFERROR(__xludf.DUMMYFUNCTION("""COMPUTED_VALUE"""),"#REF!") -> #REF! | AZ5: =IFERROR(__xludf.DUMMYFUNCTION("""COMPUTED_VALUE"""),"Açaí") -> Açaí | BA5: =IFERROR(__xludf.DUMMYFUNCTION("""COMPUTED_VALUE"""),"") | BB5: =IFERROR(__xludf.DUMMYFUNCTION("""COMPUTED_VALUE"""),"") | BC5: =IFERROR(__xludf.DUMMYFUNCTION("""COMPUTED_VALUE"""),"") | BD5: =IFERROR(__xludf.DUMMYFUNCTION("""COMPUTED_VALUE"""),"") | BE5: =IFERROR(__xludf.DUMMYFUNCTION("""COMPUTED_VALUE"""),"") | BF5: =IFERROR(__xludf.DUMMYFUNCTION("""COMPUTED_VALUE"""),"") | BG5: =IFERROR(__xludf.DUMMYFUNCTION("""COMPUTED_VALUE"""),"")
A6: =IFERROR(__xludf.DUMMYFUNCTION("""COMPUTED_VALUE"""),"ACAI DO FORTE - CONTA PAI") -> ACAI DO FORTE - CONTA PAI | B6: =IFERROR(__xludf.DUMMYFUNCTION("""COMPUTED_VALUE"""),"Lídia Esteves") -> Lídia Esteves | C6: =IFERROR(__xludf.DUMMYFUNCTION("""COMPUTED_VALUE"""),"Gabriela Roma") -> Gabriela Roma | D6: =IFERROR(__xludf.DUMMYFUNCTION("""COMPUTED_VALUE"""),"0. Não Iniciado") -> 0. Não Iniciado | F6: =IFERROR(__xludf.DUMMYFUNCTION("""COMPUTED_VALUE"""),"P") -> P | AA6: =IFERROR(__xludf.DUMMYFUNCTION("""COMPUTED_VALUE"""),14.0) -> 14 | AB6: =IFERROR(__xludf.DUMMYFUNCTION("""COMPUTED_VALUE"""),"CE") -> CE | AC6: =IFERROR(__xludf.DUMMYFUNCTION("""COMPUTED_VALUE"""),"Sim") -> Sim | AD6: =IFERROR(__xludf.DUMMYFUNCTION("""COMPUTED_VALUE"""),"Ifood") -> Ifood | AM6: =IFERROR(__xludf.DUMMYFUNCTION("""COMPUTED_VALUE"""),"FY27") -> FY27 | AO6: =IFERROR(__xludf.DUMMYFUNCTION("""COMPUTED_VALUE"""),45553.0) -> 45553 | AP6: =IFERROR(__xludf.DUMMYFUNCTION("""COMPUTED_VALUE"""),"RJ") -> RJ | AQ6: =IFERROR(__xludf.DUMMYFUNCTION("""COMPUTED_VALUE"""),"JUAN CHAROTTA") -> JUAN CHAROTTA | AR6: =IFERROR(__xludf.DUMMYFUNCTION("""COMPUTED_VALUE"""),"MARCELLA GUIMARAES") -> MARCELLA GUIMARAES | AS6: =IFERROR(__xludf.DUMMYFUNCTION("""COMPUTED_VALUE"""),"NATHALIE MERTENS") -> NATHALIE MERTENS | AT6: =IFERROR(__xludf.DUMMYFUNCTION("""COMPUTED_VALUE"""),"NATALIA COUTINHO") -> NATALIA COUTINHO | AU6: =IFERROR(__xludf.DUMMYFUNCTION("""COMPUTED_VALUE"""),0.0) -> 0 | AV6: =IFERROR(__xludf.DUMMYFUNCTION("""COMPUTED_VALUE"""),0.0) -> 0 | AW6: =IFERROR(__xludf.DUMMYFUNCTION("""COMPUTED_VALUE"""),0.0) -> 0 | AX6: =IFERROR(__xludf.DUMMYFUNCTION("""COMPUTED_VALUE"""),0.0) -> 0 | AZ6: =IFERROR(__xludf.DUMMYFUNCTION("""COMPUTED_VALUE"""),"Açaí") -> Açaí | BA6: =IFERROR(__xludf.DUMMYFUNCTION("""COMPUTED_VALUE"""),"") | BB6: =IFERROR(__xludf.DUMMYFUNCTION("""COMPUTED_VALUE"""),"") | BC6: =IFERROR(__xludf.DUMMYFUNCTION("""COMPUTED_VALUE"""),"") | BD6: =IFERROR(__xludf.DUMMYFUNCTION("""COMPUTED_VALUE"""),"") | BE6: =IFERROR(__xludf.DUMMYFUNCTION("""COMPUTED_VALUE"""),"") | BF6: =IFERROR(__xludf.DUMMYFUNCTION("""COMPUTED_VALUE"""),"") | BG6: =IFERROR(__xludf.DUMMYFUNCTION("""COMPUTED_VALUE"""),"")
A7: =IFERROR(__xludf.DUMMYFUNCTION("""COMPUTED_VALUE"""),"ACAI LAFRESCO") -> ACAI LAFRESCO | B7: =IFERROR(__xludf.DUMMYFUNCTION("""COMPUTED_VALUE"""),"João Biagiotti") -> João Biagiotti | C7: =IFERROR(__xludf.DUMMYFUNCTION("""COMPUTED_VALUE"""),"Diego Santos") -> Diego Santos | D7: =IFERROR(__xludf.DUMMYFUNCTION("""COMPUTED_VALUE"""),"0. Não Iniciado") -> 0. Não Iniciado | F7: =IFERROR(__xludf.DUMMYFUNCTION("""COMPUTED_VALUE"""),"P") -> P | AA7: =IFERROR(__xludf.DUMMYFUNCTION("""COMPUTED_VALUE"""),5.0) -> 5 | AB7: =IFERROR(__xludf.DUMMYFUNCTION("""COMPUTED_VALUE"""),"CE") -> CE | AC7: =IFERROR(__xludf.DUMMYFUNCTION("""COMPUTED_VALUE"""),"Sim") -> Sim | AD7: =IFERROR(__xludf.DUMMYFUNCTION("""COMPUTED_VALUE"""),"Ifood") -> Ifood | AM7: =IFERROR(__xludf.DUMMYFUNCTION("""COMPUTED_VALUE"""),"FY27") -> FY27 | AO7: =IFERROR(__xludf.DUMMYFUNCTION("""COMPUTED_VALUE"""),45553.0) -> 45553 | AP7: =IFERROR(__xludf.DUMMYFUNCTION("""COMPUTED_VALUE"""),"SP") -> SP | AQ7: =IFERROR(__xludf.DUMMYFUNCTION("""COMPUTED_VALUE"""),"CARLOS ALBRECHT") -> CARLOS ALBRECHT | AR7: =IFERROR(__xludf.DUMMYFUNCTION("""COMPUTED_VALUE"""),"GUILHERME VIEIRA") -> GUILHERME VIEIRA | AS7: =IFERROR(__xludf.DUMMYFUNCTION("""COMPUTED_VALUE"""),"ALAN HADDAD") -> ALAN HADDAD | AT7: =IFERROR(__xludf.DUMMYFUNCTION("""COMPUTED_VALUE"""),"ISABELA DINIZ") -> ISABELA DINIZ | AU7: =IFERROR(__xludf.DUMMYFUNCTION("""COMPUTED_VALUE"""),0.0) -> 0 | AV7: =IFERROR(__xludf.DUMMYFUNCTION("""COMPUTED_VALUE"""),0.0) -> 0 | AW7: =IFERROR(__xludf.DUMMYFUNCTION("""COMPUTED_VALUE"""),0.0) -> 0 | AX7: =IFERROR(__xludf.DUMMYFUNCTION("""COMPUTED_VALUE"""),0.0) -> 0 | AZ7: =IFERROR(__xludf.DUMMYFUNCTION("""COMPUTED_VALUE"""),"Saudável") -> Saudável | BA7: =IFERROR(__xludf.DUMMYFUNCTION("""COMPUTED_VALUE"""),"") | BB7: =IFERROR(__xludf.DUMMYFUNCTION("""COMPUTED_VALUE"""),"") | BC7: =IFERROR(__xludf.DUMMYFUNCTION("""COMPUTED_VALUE"""),"") | BD7: =IFERROR(__xludf.DUMMYFUNCTION("""COMPUTED_VALUE"""),"") | BE7: =IFERROR(__xludf.DUMMYFUNCTION("""COMPUTED_VALUE"""),"") | BF7: =IFERROR(__xludf.DUMMYFUNCTION("""COMPUTED_VALUE"""),"") | BG7: =IFERROR(__xludf.DUMMYFUNCTION("""COMPUTED_VALUE"""),"")
A8: =IFERROR(__xludf.DUMMYFUNCTION("""COMPUTED_VALUE"""),"ADEGA DO BOI TERESINA") -> ADEGA DO BOI TERESINA | B8: =IFERROR(__xludf.DUMMYFUNCTION("""COMPUTED_VALUE"""),"João Biagiotti") -> João Biagiotti | C8: =IFERROR(__xludf.DUMMYFUNCTION("""COMPUTED_VALUE"""),"Diego Santos") -> Diego Santos | D8: =IFERROR(__xludf.DUMMYFUNCTION("""COMPUTED_VALUE"""),"0. Não Iniciado") -> 0. Não Iniciado | F8: =IFERROR(__xludf.DUMMYFUNCTION("""COMPUTED_VALUE"""),"P") -> P | AA8: =IFERROR(__xludf.DUMMYFUNCTION("""COMPUTED_VALUE"""),5.0) -> 5 | AB8: =IFERROR(__xludf.DUMMYFUNCTION("""COMPUTED_VALUE"""),"CE") -> CE | AC8: =IFERROR(__xludf.DUMMYFUNCTION("""COMPUTED_VALUE"""),"Sim") -> Sim | AD8: =IFERROR(__xludf.DUMMYFUNCTION("""COMPUTED_VALUE"""),"Ifood") -> Ifood | AM8: =IFERROR(__xludf.DUMMYFUNCTION("""COMPUTED_VALUE"""),"FY27") -> FY27 | AO8: =IFERROR(__xludf.DUMMYFUNCTION("""COMPUTED_VALUE"""),45553.0) -> 45553 | AP8: =IFERROR(__xludf.DUMMYFUNCTION("""COMPUTED_VALUE"""),"PI") -> PI | AQ8: =IFERROR(__xludf.DUMMYFUNCTION("""COMPUTED_VALUE"""),"GEORGE STEIN") -> GEORGE STEIN | AR8: =IFERROR(__xludf.DUMMYFUNCTION("""COMPUTED_VALUE"""),"RAULLI SOARES") -> RAULLI SOARES | AS8: =IFERROR(__xludf.DUMMYFUNCTION("""COMPUTED_VALUE"""),"THIAGO ROMAGNOLE") -> THIAGO ROMAGNOLE | AT8: =IFERROR(__xludf.DUMMYFUNCTION("""COMPUTED_VALUE"""),"EDUARDO VAZ") -> EDUARDO VAZ | AU8: =IFERROR(__xludf.DUMMYFUNCTION("""COMPUTED_VALUE"""),0.0) -> 0 | AV8: =IFERROR(__xludf.DUMMYFUNCTION("""COMPUTED_VALUE"""),0.0) -> 0 | AW8: =IFERROR(__xludf.DUMMYFUNCTION("""COMPUTED_VALUE"""),0.0) -> 0 | AX8: =IFERROR(__xludf.DUMMYFUNCTION("""COMPUTED_VALUE"""),0.0) -> 0 | AZ8: =IFERROR(__xludf.DUMMYFUNCTION("""COMPUTED_VALUE"""),"Doces & Bolos") -> Doces & Bolos | BA8: =IFERROR(__xludf.DUMMYFUNCTION("""COMPUTED_VALUE"""),120.0) -> 120 | BB8: =IFERROR(__xludf.DUMMYFUNCTION("""COMPUTED_VALUE"""),"Table Service - Churrascaria") -> Table Service - Churrascaria | BC8: =IFERROR(__xludf.DUMMYFUNCTION("""COMPUTED_VALUE"""),"Teresina/PI") -> Teresina/PI | BE8: =IFERROR(__xludf.DUMMYFUNCTION("""COMPUTED_VALUE"""),55.0) -> 55 | BF8: =IFERROR(__xludf.DUMMYFUNCTION("""COMPUTED_VALUE"""),0.65) -> 0.65 | BG8: =IFERROR(__xludf.DUMMYFUNCTION("""COMPUTED_VALUE"""),"Aderência forte ao 3S: PDV atual não identificado. 3S oferece PDV robusto, KDS integrado e mobilidade (3SGO) para gestão em tempo real - ideal para operações multi-canal.") -> Aderência forte ao 3S: PDV atual não identificado. 3S oferece PDV robusto, KDS integrado e mobilidade (3SGO) para gestão em tempo real - ideal para operações multi-canal.
A9: =IFERROR(__xludf.DUMMYFUNCTION("""COMPUTED_VALUE"""),"AKIRO SUSHI") -> AKIRO SUSHI | B9: =IFERROR(__xludf.DUMMYFUNCTION("""COMPUTED_VALUE"""),"Lídia Esteves") -> Lídia Esteves | C9: =IFERROR(__xludf.DUMMYFUNCTION("""COMPUTED_VALUE"""),"Gabriela Roma") -> Gabriela Roma | D9: =IFERROR(__xludf.DUMMYFUNCTION("""COMPUTED_VALUE"""),"5. Demo/Showroom") -> 5. Demo/Showroom | E9: =IFERROR(__xludf.DUMMYFUNCTION("""COMPUTED_VALUE"""),"Pré-vendas - Demonstração / Showroom") -> Pré-vendas - Demonstração / Showroom | F9: =IFERROR(__xludf.DUMMYFUNCTION("""COMPUTED_VALUE"""),"P") -> P | G9: =IFERROR(__xludf.DUMMYFUNCTION("""COMPUTED_VALUE"""),46154.0) -> 46154 | H9: =IFERROR(__xludf.DUMMYFUNCTION("""COMPUTED_VALUE"""),"demo agendada para 14/5") -> demo agendada para 14/5 | I9: =IFERROR(__xludf.DUMMYFUNCTION("""COMPUTED_VALUE"""),46122.67191171296) -> 46122.672 | J9: =IFERROR(__xludf.DUMMYFUNCTION("""COMPUTED_VALUE"""),46139.72232130787) -> 46139.722 | K9: =IFERROR(__xludf.DUMMYFUNCTION("""COMPUTED_VALUE"""),46140.40413303241) -> 46140.404 | L9: =IFERROR(__xludf.DUMMYFUNCTION("""COMPUTED_VALUE"""),46153.67861347222) -> 46153.679 | M9: =IFERROR(__xludf.DUMMYFUNCTION("""COMPUTED_VALUE"""),46153.681405243056) -> 46153.681 | AA9: =IFERROR(__xludf.DUMMYFUNCTION("""COMPUTED_VALUE"""),5.0) -> 5 | AB9: =IFERROR(__xludf.DUMMYFUNCTION("""COMPUTED_VALUE"""),"CE") -> CE | AC9: =IFERROR(__xludf.DUMMYFUNCTION("""COMPUTED_VALUE"""),"Sim") -> Sim | AD9: =IFERROR(__xludf.DUMMYFUNCTION("""COMPUTED_VALUE"""),"Ifood") -> Ifood | AH9: =IFERROR(__xludf.DUMMYFUNCTION("""COMPUTED_VALUE"""),4.0) -> 4 | AI9: =IFERROR(__xludf.DUMMYFUNCTION("""COMPUTED_VALUE"""),300000.0) -> 300000 | AJ9: =IFERROR(__xludf.DUMMYFUNCTION("""COMPUTED_VALUE"""),"sistema local") -> sistema local | AK9: =IFERROR(__xludf.DUMMYFUNCTION("""COMPUTED_VALUE"""),"salão e delivery") -> salão e delivery | AL9: =IFERROR(__xludf.DUMMYFUNCTION("""COMPUTED_VALUE"""),"SIM") -> SIM | AM9: =IFERROR(__xludf.DUMMYFUNCTION("""COMPUTED_VALUE"""),"FY27") -> FY27 | AO9: =IFERROR(__xludf.DUMMYFUNCTION("""COMPUTED_VALUE"""),61.0) -> 61 | AP9: =IFERROR(__xludf.DUMMYFUNCTION("""COMPUTED_VALUE"""),"RJ") -> RJ | AQ9: =IFERROR(__xludf.DUMMYFUNCTION("""COMPUTED_VALUE"""),"JUAN CHAROTTA") -> JUAN CHAROTTA | AR9: =IFERROR(__xludf.DUMMYFUNCTION("""COMPUTED_VALUE"""),"BRUNA MEDEIROS") -> BRUNA MEDEIROS | AS9: =IFERROR(__xludf.DUMMYFUNCTION("""COMPUTED_VALUE"""),"NATHALIE MERTENS") -> NATHALIE MERTENS | AT9: =IFERROR(__xludf.DUMMYFUNCTION("""COMPUTED_VALUE"""),"NATALIA COUTINHO") -> NATALIA COUTINHO | AU9: =IFERROR(__xludf.DUMMYFUNCTION("""COMPUTED_VALUE"""),0.0) -> 0 | AV9: =IFERROR(__xludf.DUMMYFUNCTION("""COMPUTED_VALUE"""),0.0) -> 0 | AW9: =IFERROR(__xludf.DUMMYFUNCTION("""COMPUTED_VALUE"""),0.0) -> 0 | AX9: =IFERROR(__xludf.DUMMYFUNCTION("""COMPUTED_VALUE"""),0.0) -> 0 | AZ9: =IFERROR(__xludf.DUMMYFUNCTION("""COMPUTED_VALUE"""),"Japonesa") -> Japonesa | BA9: =IFERROR(__xludf.DUMMYFUNCTION("""COMPUTED_VALUE"""),95.0) -> 95 | BB9: =IFERROR(__xludf.DUMMYFUNCTION("""COMPUTED_VALUE"""),"Table Service/Delivery - Rodízio Japonês") -> Table Service/Delivery - Rodízio Japonês | BC9: =IFERROR(__xludf.DUMMYFUNCTION("""COMPUTED_VALUE"""),"Grande Rio/RJ") -> Grande Rio/RJ | BE9: =IFERROR(__xludf.DUMMYFUNCTION("""COMPUTED_VALUE"""),60.0) -> 60 | BF9: =IFERROR(__xludf.DUMMYFUNCTION("""COMPUTED_VALUE"""),0.65) -> 0.65 | BG9: =IFERROR(__xludf.DUMMYFUNCTION("""COMPUTED_VALUE"""),"Aderência forte ao 3S: PDV atual não identificado. 3S oferece PDV robusto, KDS integrado e mobilidade (3SGO) para gestão em tempo real - ideal para operações multi-canal.") -> Aderência forte ao 3S: PDV atual não identificado. 3S oferece PDV robusto, KDS integrado e mobilidade (3SGO) para gestão em tempo real - ideal para operações multi-canal.
A10: =IFERROR(__xludf.DUMMYFUNCTION("""COMPUTED_VALUE"""),"BIG PIZZA") -> BIG PIZZA | B10: =IFERROR(__xludf.DUMMYFUNCTION("""COMPUTED_VALUE"""),"João Biagiotti") -> João Biagiotti | C10: =IFERROR(__xludf.DUMMYFUNCTION("""COMPUTED_VALUE"""),"Diego Santos") -> Diego Santos | D10: =IFERROR(__xludf.DUMMYFUNCTION("""COMPUTED_VALUE"""),"0. Não Iniciado") -> 0. Não Iniciado | F10: =IFERROR(__xludf.DUMMYFUNCTION("""COMPUTED_VALUE"""),"P") -> P | AA10: =IFERROR(__xludf.DUMMYFUNCTION("""COMPUTED_VALUE"""),11.0) -> 11 | AB10: =IFERROR(__xludf.DUMMYFUNCTION("""COMPUTED_VALUE"""),"Não Encarteirado") -> Não Encarteirado | AC10: =IFERROR(__xludf.DUMMYFUNCTION("""COMPUTED_VALUE"""),"Sim") -> Sim | AD10: =IFERROR(__xludf.DUMMYFUNCTION("""COMPUTED_VALUE"""),0.0) -> 0 | AM10: =IFERROR(__xludf.DUMMYFUNCTION("""COMPUTED_VALUE"""),"FY27") -> FY27 | AO10: =IFERROR(__xludf.DUMMYFUNCTION("""COMPUTED_VALUE"""),45553.0) -> 45553 | AP10: =IFERROR(__xludf.DUMMYFUNCTION("""COMPUTED_VALUE"""),"SP") -> SP | AQ10: =IFERROR(__xludf.DUMMYFUNCTION("""COMPUTED_VALUE"""),"LAURA APOLINARIO") -> LAURA APOLINARIO | AR10: =IFERROR(__xludf.DUMMYFUNCTION("""COMPUTED_VALUE"""),0.0) -> 0 | AS10: =IFERROR(__xludf.DUMMYFUNCTION("""COMPUTED_VALUE"""),0.0) -> 0 | AT10: =IFERROR(__xludf.DUMMYFUNCTION("""COMPUTED_VALUE"""),0.0) -> 0 | AU10: =IFERROR(__xludf.DUMMYFUNCTION("""COMPUTED_VALUE"""),0.0) -> 0 | AV10: =IFERROR(__xludf.DUMMYFUNCTION("""COMPUTED_VALUE"""),0.0) -> 0 | AW10: =IFERROR(__xludf.DUMMYFUNCTION("""COMPUTED_VALUE"""),0.0) -> 0 | AX10: =IFERROR(__xludf.DUMMYFUNCTION("""COMPUTED_VALUE"""),0.0) -> 0 | AY10: =IFERROR(__xludf.DUMMYFUNCTION("""COMPUTED_VALUE"""),"Anota Ai Solucoes Digitais S/a") -> Anota Ai Solucoes Digitais S/a | AZ10: =IFERROR(__xludf.DUMMYFUNCTION("""COMPUTED_VALUE"""),"Pizza") -> Pizza | BA10: =IFERROR(__xludf.DUMMYFUNCTION("""COMPUTED_VALUE"""),55.0) -> 55 | BB10: =IFERROR(__xludf.DUMMYFUNCTION("""COMPUTED_VALUE"""),"QSR - Pizza Delivery") -> QSR - Pizza Delivery | BC10: =IFERROR(__xludf.DUMMYFUNCTION("""COMPUTED_VALUE"""),"Regional") -> Regional | BE10: =IFERROR(__xludf.DUMMYFUNCTION("""COMPUTED_VALUE"""),70.0) -> 70 | BF10: =IFERROR(__xludf.DUMMYFUNCTION("""COMPUTED_VALUE"""),0.85) -> 0.85 | BG10: =IFERROR(__xludf.DUMMYFUNCTION("""COMPUTED_VALUE"""),"Alta aderência ao 3S: PDV atual não identificado. 3S oferece Kiosk nativo, Hub Delivery integrado e gestão centralizada multi-loja - diferenciais competitivos para expansão e redução de filas.") -> Alta aderência ao 3S: PDV atual não identificado. 3S oferece Kiosk nativo, Hub Delivery integrado e gestão centralizada multi-loja - diferenciais competitivos para expansão e redução de filas. | BH10: null | BI10: 0.4
A11: =IFERROR(__xludf.DUMMYFUNCTION("""COMPUTED_VALUE"""),"AMBROZINI") -> AMBROZINI | B11: =IFERROR(__xludf.DUMMYFUNCTION("""COMPUTED_VALUE"""),"João Biagiotti") -> João Biagiotti | C11: =IFERROR(__xludf.DUMMYFUNCTION("""COMPUTED_VALUE"""),"Diego Santos") -> Diego Santos | D11: =IFERROR(__xludf.DUMMYFUNCTION("""COMPUTED_VALUE"""),"1. Iniciado") -> 1. Iniciado | E11: =IFERROR(__xludf.DUMMYFUNCTION("""COMPUTED_VALUE"""),"Delivery - Aguardando retorno executivo") -> Delivery - Aguardando retorno executivo | F11: =IFERROR(__xludf.DUMMYFUNCTION("""COMPUTED_VALUE"""),"P") -> P | G11: =IFERROR(__xludf.DUMMYFUNCTION("""COMPUTED_VALUE"""),46119.0) -> 46119 | H11: =IFERROR(__xludf.DUMMYFUNCTION("""COMPUTED_VALUE"""),"Foi enviado mensagem para a coordenação para verificar a possibilidade de uma agenda e direcionamento ") -> Foi enviado mensagem para a coordenação para verificar a possibilidade de uma agenda e direcionamento | I11: =IFERROR(__xludf.DUMMYFUNCTION("""COMPUTED_VALUE"""),46120.46079829861) -> 46120.461 | AA11: =IFERROR(__xludf.DUMMYFUNCTION("""COMPUTED_VALUE"""),5.0) -> 5 | AB11: =IFERROR(__xludf.DUMMYFUNCTION("""COMPUTED_VALUE"""),"CE") -> CE | AC11: =IFERROR(__xludf.DUMMYFUNCTION("""COMPUTED_VALUE"""),"Sim") -> Sim | AD11: =IFERROR(__xludf.DUMMYFUNCTION("""COMPUTED_VALUE"""),"Ifood") -> Ifood | AM11: =IFERROR(__xludf.DUMMYFUNCTION("""COMPUTED_VALUE"""),"FY27") -> FY27 | AO11: =IFERROR(__xludf.DUMMYFUNCTION("""COMPUTED_VALUE"""),96.0) -> 96 | AP11: =IFERROR(__xludf.DUMMYFUNCTION("""COMPUTED_VALUE"""),"MG") -> MG | AQ11: =IFERROR(__xludf.DUMMYFUNCTION("""COMPUTED_VALUE"""),"EDUARDA HALABI") -> EDUARDA HALABI | AR11: =IFERROR(__xludf.DUMMYFUNCTION("""COMPUTED_VALUE"""),"DIEGO PINTO") -> DIEGO PINTO | AS11: =IFERROR(__xludf.DUMMYFUNCTION("""COMPUTED_VALUE"""),"FABIO DONATO") -> FABIO DONATO | AT11: =IFERROR(__xludf.DUMMYFUNCTION("""COMPUTED_VALUE"""),"GILSON JUNIOR") -> GILSON JUNIOR | AU11: =IFERROR(__xludf.DUMMYFUNCTION("""COMPUTED_VALUE"""),0.0) -> 0 | AV11: =IFERROR(__xludf.DUMMYFUNCTION("""COMPUTED_VALUE"""),0.0) -> 0 | AW11: =IFERROR(__xludf.DUMMYFUNCTION("""COMPUTED_VALUE"""),0.0) -> 0 | AX11: =IFERROR(__xludf.DUMMYFUNCTION("""COMPUTED_VALUE"""),0.0) -> 0 | AY11: =IFERROR(__xludf.DUMMYFUNCTION("""COMPUTED_VALUE"""),"Saipos Serviços De Software") -> Saipos Serviços De Software | AZ11: =IFERROR(__xludf.DUMMYFUNCTION("""COMPUTED_VALUE"""),"Brasileira") -> Brasileira | BA11: =IFERROR(__xludf.DUMMYFUNCTION("""COMPUTED_VALUE"""),65.0) -> 65 | BB11: =IFERROR(__xludf.DUMMYFUNCTION("""COMPUTED_VALUE"""),"Table Service - Self-Service Gourmet") -> Table Service - Self-Service Gourmet | BC11: =IFERROR(__xludf.DUMMYFUNCTION("""COMPUTED_VALUE"""),"Belo Horizonte/MG") -> Belo Horizonte/MG | BE11: =IFERROR(__xludf.DUMMYFUNCTION("""COMPUTED_VALUE"""),55.0) -> 55 | BF11: =IFERROR(__xludf.DUMMYFUNCTION("""COMPUTED_VALUE"""),0.65) -> 0.65 | BG11: =IFERROR(__xludf.DUMMYFUNCTION("""COMPUTED_VALUE"""),"Aderência forte ao 3S: PDV atual não identificado. 3S oferece PDV robusto, KDS integrado e mobilidade (3SGO) para gestão em tempo real - ideal para operações multi-canal.") -> Aderência forte ao 3S: PDV atual não identificado. 3S oferece PDV robusto, KDS integrado e mobilidade (3SGO) para gestão em tempo real - ideal para operações multi-canal. | BH11: null | BI11: 1
A12: =IFERROR(__xludf.DUMMYFUNCTION("""COMPUTED_VALUE"""),"AMERICAN ORIGINAL - CONTA MARCA") -> AMERICAN ORIGINAL - CONTA MARCA | B12: =IFERROR(__xludf.DUMMYFUNCTION("""COMPUTED_VALUE"""),"Lídia Esteves") -> Lídia Esteves | C12: =IFERROR(__xludf.DUMMYFUNCTION("""COMPUTED_VALUE"""),"Gabriela Roma") -> Gabriela Roma | D12: =IFERROR(__xludf.DUMMYFUNCTION("""COMPUTED_VALUE"""),"1. Iniciado") -> 1. Iniciado | F12: =IFERROR(__xludf.DUMMYFUNCTION("""COMPUTED_VALUE"""),"P") -> P | I12: =IFERROR(__xludf.DUMMYFUNCTION("""COMPUTED_VALUE"""),46140.610919548606) -> 46140.611 | AA12: =IFERROR(__xludf.DUMMYFUNCTION("""COMPUTED_VALUE"""),13.0) -> 13 | AB12: =IFERROR(__xludf.DUMMYFUNCTION("""COMPUTED_VALUE"""),"-") -> - | AC12: =IFERROR(__xludf.DUMMYFUNCTION("""COMPUTED_VALUE"""),"Sim") -> Sim | AD12: =IFERROR(__xludf.DUMMYFUNCTION("""COMPUTED_VALUE"""),"Ifood") -> Ifood | AM12: =IFERROR(__xludf.DUMMYFUNCTION("""COMPUTED_VALUE"""),"FY27") -> FY27 | AO12: =IFERROR(__xludf.DUMMYFUNCTION("""COMPUTED_VALUE"""),45553.0) -> 45553 | AP12: =IFERROR(__xludf.DUMMYFUNCTION("""COMPUTED_VALUE"""),"SC") -> SC | AQ12: =IFERROR(__xludf.DUMMYFUNCTION("""COMPUTED_VALUE"""),"MARCIO CHAGAS") -> MARCIO CHAGAS | AR12: =IFERROR(__xludf.DUMMYFUNCTION("""COMPUTED_VALUE"""),"ALEXSANDER ROCHA") -> ALEXSANDER ROCHA | AS12: =IFERROR(__xludf.DUMMYFUNCTION("""COMPUTED_VALUE"""),"FABIO DONATO") -> FABIO DONATO | AT12: =IFERROR(__xludf.DUMMYFUNCTION("""COMPUTED_VALUE"""),"CAMILA HOLANDA") -> CAMILA HOLANDA | AU12: =IFERROR(__xludf.DUMMYFUNCTION("""COMPUTED_VALUE"""),0.0) -> 0 | AV12: =IFERROR(__xludf.DUMMYFUNCTION("""COMPUTED_VALUE"""),0.0) -> 0 | AW12: =IFERROR(__xludf.DUMMYFUNCTION("""COMPUTED_VALUE"""),0.0) -> 0 | AX12: =IFERROR(__xludf.DUMMYFUNCTION("""COMPUTED_VALUE"""),0.0) -> 0 | AY12: =IFERROR(__xludf.DUMMYFUNCTION("""COMPUTED_VALUE"""),"Saipos Serviços De Software") -> Saipos Serviços De Software | AZ12: =IFERROR(__xludf.DUMMYFUNCTION("""COMPUTED_VALUE"""),"Lanches") -> Lanches | BA12: =IFERROR(__xludf.DUMMYFUNCTION("""COMPUTED_VALUE"""),55.0) -> 55 | BB12: =IFERROR(__xludf.DUMMYFUNCTION("""COMPUTED_VALUE"""),"Fast Casual - Hamburgueria") -> Fast Casual - Hamburgueria | BC12: =IFERROR(__xludf.DUMMYFUNCTION("""COMPUTED_VALUE"""),"Regional") -> Regional | BE12: =IFERROR(__xludf.DUMMYFUNCTION("""COMPUTED_VALUE"""),70.0) -> 70 | BF12: =IFERROR(__xludf.DUMMYFUNCTION("""COMPUTED_VALUE"""),0.8) -> 0.8 | BG12: =IFERROR(__xludf.DUMMYFUNCTION("""COMPUTED_VALUE"""),"Alta aderência ao 3S: PDV atual não identificado. 3S oferece Kiosk nativo, Hub Delivery integrado e gestão centralizada multi-loja - diferenciais competitivos para expansão e redução de filas.") -> Alta aderência ao 3S: PDV atual não identificado. 3S oferece Kiosk nativo, Hub Delivery integrado e gestão centralizada multi-loja - diferenciais competitivos para expansão e redução de filas. | BH12: null | BI12: 1
A13: =IFERROR(__xludf.DUMMYFUNCTION("""COMPUTED_VALUE"""),"ANGUS - CARNES E HAMBURGUERIA") -> ANGUS - CARNES E HAMBURGUERIA | B13: =IFERROR(__xludf.DUMMYFUNCTION("""COMPUTED_VALUE"""),"Lídia Esteves") -> Lídia Esteves | C13: =IFERROR(__xludf.DUMMYFUNCTION("""COMPUTED_VALUE"""),"Gabriela Roma") -> Gabriela Roma | D13: =IFERROR(__xludf.DUMMYFUNCTION("""COMPUTED_VALUE"""),"1. Iniciado") -> 1. Iniciado | E13: =IFERROR(__xludf.DUMMYFUNCTION("""COMPUTED_VALUE"""),"Delivery - Aguardando retorno executivo") -> Delivery - Aguardando retorno executivo | F13: =IFERROR(__xludf.DUMMYFUNCTION("""COMPUTED_VALUE"""),"P") -> P | G13: =IFERROR(__xludf.DUMMYFUNCTION("""COMPUTED_VALUE"""),46156.0) -> 46156 | H13: =IFERROR(__xludf.DUMMYFUNCTION("""COMPUTED_VALUE"""),"pedido de agenda com delivery") -> pedido de agenda com delivery | I13: =IFERROR(__xludf.DUMMYFUNCTION("""COMPUTED_VALUE"""),46156.69866701389) -> 46156.699 | AA13: =IFERROR(__xludf.DUMMYFUNCTION("""COMPUTED_VALUE"""),5.0) -> 5 | AB13: =IFERROR(__xludf.DUMMYFUNCTION("""COMPUTED_VALUE"""),"CE") -> CE | AC13: =IFERROR(__xludf.DUMMYFUNCTION("""COMPUTED_VALUE"""),"Sim") -> Sim | AD13: =IFERROR(__xludf.DUMMYFUNCTION("""COMPUTED_VALUE"""),"Mp Multipedidos") -> Mp Multipedidos | AM13: =IFERROR(__xludf.DUMMYFUNCTION("""COMPUTED_VALUE"""),"FY27") -> FY27 | AO13: =IFERROR(__xludf.DUMMYFUNCTION("""COMPUTED_VALUE"""),59.0) -> 59 | AP13: =IFERROR(__xludf.DUMMYFUNCTION("""COMPUTED_VALUE"""),"SC") -> SC | AQ13: =IFERROR(__xludf.DUMMYFUNCTION("""COMPUTED_VALUE"""),"MARCIO CHAGAS") -> MARCIO CHAGAS | AR13: =IFERROR(__xludf.DUMMYFUNCTION("""COMPUTED_VALUE"""),"CAMILA CASAGRANDE") -> CAMILA CASAGRANDE | AS13: =IFERROR(__xludf.DUMMYFUNCTION("""COMPUTED_VALUE"""),"FABIO DONATO") -> FABIO DONATO | AT13: =IFERROR(__xludf.DUMMYFUNCTION("""COMPUTED_VALUE"""),"CAMILA HOLANDA") -> CAMILA HOLANDA | AU13: =IFERROR(__xludf.DUMMYFUNCTION("""COMPUTED_VALUE"""),0.0) -> 0 | AV13: =IFERROR(__xludf.DUMMYFUNCTION("""COMPUTED_VALUE"""),0.0) -> 0 | AW13: =IFERROR(__xludf.DUMMYFUNCTION("""COMPUTED_VALUE"""),0.0) -> 0 | AX13: =IFERROR(__xludf.DUMMYFUNCTION("""COMPUTED_VALUE"""),0.0) -> 0 | AZ13: =IFERROR(__xludf.DUMMYFUNCTION("""COMPUTED_VALUE"""),"Marmita") -> Marmita | BA13: =IFERROR(__xludf.DUMMYFUNCTION("""COMPUTED_VALUE"""),70.0) -> 70 | BB13: =IFERROR(__xludf.DUMMYFUNCTION("""COMPUTED_VALUE"""),"Fast Casual - Burgers Premium") -> Fast Casual - Burgers Premium | BC13: =IFERROR(__xludf.DUMMYFUNCTION("""COMPUTED_VALUE"""),"Regional") -> Regional | BE13: =IFERROR(__xludf.DUMMYFUNCTION("""COMPUTED_VALUE"""),70.0) -> 70 | BF13: =IFERROR(__xludf.DUMMYFUNCTION("""COMPUTED_VALUE"""),0.75) -> 0.75 | BG13: =IFERROR(__xludf.DUMMYFUNCTION("""COMPUTED_VALUE"""),"Aderência forte ao 3S: PDV atual não identificado. 3S oferece PDV robusto, KDS integrado e mobilidade (3SGO) para gestão em tempo real - ideal para operações multi-canal.") -> Aderência forte ao 3S: PDV atual não identificado. 3S oferece PDV robusto, KDS integrado e mobilidade (3SGO) para gestão em tempo real - ideal para operações multi-canal. | BH13: Mp Multipedidos | BI13: 0.57894737
A14: =IFERROR(__xludf.DUMMYFUNCTION("""COMPUTED_VALUE"""),"ARNALDOS LANCHES - NIVEL MARCA") -> ARNALDOS LANCHES - NIVEL MARCA | B14: =IFERROR(__xludf.DUMMYFUNCTION("""COMPUTED_VALUE"""),"Lídia Esteves") -> Lídia Esteves | C14: =IFERROR(__xludf.DUMMYFUNCTION("""COMPUTED_VALUE"""),"Gabriela Roma") -> Gabriela Roma | D14: =IFERROR(__xludf.DUMMYFUNCTION("""COMPUTED_VALUE"""),"1. Iniciado") -> 1. Iniciado | E14: =IFERROR(__xludf.DUMMYFUNCTION("""COMPUTED_VALUE"""),"Delivery - Aguardando retorno executivo") -> Delivery - Aguardando retorno executivo | F14: =IFERROR(__xludf.DUMMYFUNCTION("""COMPUTED_VALUE"""),"P") -> P | G14: =IFERROR(__xludf.DUMMYFUNCTION("""COMPUTED_VALUE"""),46156.0) -> 46156 | H14: =IFERROR(__xludf.DUMMYFUNCTION("""COMPUTED_VALUE"""),"pedido de abertura de portas pelo exec de delivery") -> pedido de abertura de portas pelo exec de delivery | I14: =IFERROR(__xludf.DUMMYFUNCTION("""COMPUTED_VALUE"""),46156.70339043981) -> 46156.703 | AA14: =IFERROR(__xludf.DUMMYFUNCTION("""COMPUTED_VALUE"""),5.0) -> 5 | AB14: =IFERROR(__xludf.DUMMYFUNCTION("""COMPUTED_VALUE"""),"CE") -> CE | AC14: =IFERROR(__xludf.DUMMYFUNCTION("""COMPUTED_VALUE"""),"Sim") -> Sim | AD14: =IFERROR(__xludf.DUMMYFUNCTION("""COMPUTED_VALUE"""),"Sagres Automação Comercial") -> Sagres Automação Comercial | AM14: =IFERROR(__xludf.DUMMYFUNCTION("""COMPUTED_VALUE"""),"FY27") -> FY27 | AO14: =IFERROR(__xludf.DUMMYFUNCTION("""COMPUTED_VALUE"""),59.0) -> 59 | AP14: =IFERROR(__xludf.DUMMYFUNCTION("""COMPUTED_VALUE"""),"PR") -> PR | AQ14: =IFERROR(__xludf.DUMMYFUNCTION("""COMPUTED_VALUE"""),"LUIZ FILHO") -> LUIZ FILHO | AR14: =IFERROR(__xludf.DUMMYFUNCTION("""COMPUTED_VALUE"""),"HELOISA SANTOS") -> HELOISA SANTOS | AS14: =IFERROR(__xludf.DUMMYFUNCTION("""COMPUTED_VALUE"""),"FABIO DONATO") -> FABIO DONATO | AT14: =IFERROR(__xludf.DUMMYFUNCTION("""COMPUTED_VALUE"""),"MURILO NAGASHIMA") -> MURILO NAGASHIMA | AU14: =IFERROR(__xludf.DUMMYFUNCTION("""COMPUTED_VALUE"""),0.0) -> 0 | AV14: =IFERROR(__xludf.DUMMYFUNCTION("""COMPUTED_VALUE"""),0.0) -> 0 | AW14: =IFERROR(__xludf.DUMMYFUNCTION("""COMPUTED_VALUE"""),0.0) -> 0 | AX14: =IFERROR(__xludf.DUMMYFUNCTION("""COMPUTED_VALUE"""),0.0) -> 0 | AZ14: =IFERROR(__xludf.DUMMYFUNCTION("""COMPUTED_VALUE"""),"Lanches") -> Lanches | BA14: =IFERROR(__xludf.DUMMYFUNCTION("""COMPUTED_VALUE"""),"") | BB14: =IFERROR(__xludf.DUMMYFUNCTION("""COMPUTED_VALUE"""),"") | BC14: =IFERROR(__xludf.DUMMYFUNCTION("""COMPUTED_VALUE"""),"") | BD14: =IFERROR(__xludf.DUMMYFUNCTION("""COMPUTED_VALUE"""),"") | BE14: =IFERROR(__xludf.DUMMYFUNCTION("""COMPUTED_VALUE"""),"") | BF14: =IFERROR(__xludf.DUMMYFUNCTION("""COMPUTED_VALUE"""),"") | BG14: =IFERROR(__xludf.DUMMYFUNCTION("""COMPUTED_VALUE"""),"") | BH14: Sagres Automação Comercial | BI14: 1
A15: =IFERROR(__xludf.DUMMYFUNCTION("""COMPUTED_VALUE"""),"ARO TEMAKERIA DELIVERY") -> ARO TEMAKERIA DELIVERY | B15: =IFERROR(__xludf.DUMMYFUNCTION("""COMPUTED_VALUE"""),"João Biagiotti") -> João Biagiotti | C15: =IFERROR(__xludf.DUMMYFUNCTION("""COMPUTED_VALUE"""),"Diego Santos") -> Diego Santos | D15: =IFERROR(__xludf.DUMMYFUNCTION("""COMPUTED_VALUE"""),"0. Não Iniciado") -> 0. Não Iniciado | F15: =IFERROR(__xludf.DUMMYFUNCTION("""COMPUTED_VALUE"""),"P") -> P | AA15: =IFERROR(__xludf.DUMMYFUNCTION("""COMPUTED_VALUE"""),7.0) -> 7 | AB15: =IFERROR(__xludf.DUMMYFUNCTION("""COMPUTED_VALUE"""),"CE") -> CE | AC15: =IFERROR(__xludf.DUMMYFUNCTION("""COMPUTED_VALUE"""),"Sim") -> Sim | AD15: =IFERROR(__xludf.DUMMYFUNCTION("""COMPUTED_VALUE"""),"Ifood") -> Ifood | AM15: =IFERROR(__xludf.DUMMYFUNCTION("""COMPUTED_VALUE"""),"FY27") -> FY27 | AO15: =IFERROR(__xludf.DUMMYFUNCTION("""COMPUTED_VALUE"""),45553.0) -> 45553 | AP15: =IFERROR(__xludf.DUMMYFUNCTION("""COMPUTED_VALUE"""),"SP") -> SP | AQ15: =IFERROR(__xludf.DUMMYFUNCTION("""COMPUTED_VALUE"""),"ANDRE PARAIZO") -> ANDRE PARAIZO | AR15: =IFERROR(__xludf.DUMMYFUNCTION("""COMPUTED_VALUE"""),"DIOGO NEPOMUCENO") -> DIOGO NEPOMUCENO | AS15: =IFERROR(__xludf.DUMMYFUNCTION("""COMPUTED_VALUE"""),"ALAN HADDAD") -> ALAN HADDAD | AT15: =IFERROR(__xludf.DUMMYFUNCTION("""COMPUTED_VALUE"""),"GABRIEL PERES") -> GABRIEL PERES | AU15: =IFERROR(__xludf.DUMMYFUNCTION("""COMPUTED_VALUE"""),0.0) -> 0 | AV15: =IFERROR(__xludf.DUMMYFUNCTION("""COMPUTED_VALUE"""),0.0) -> 0 | AW15: =IFERROR(__xludf.DUMMYFUNCTION("""COMPUTED_VALUE"""),0.0) -> 0 | AX15: =IFERROR(__xludf.DUMMYFUNCTION("""COMPUTED_VALUE"""),0.0) -> 0 | AY15: =IFERROR(__xludf.DUMMYFUNCTION("""COMPUTED_VALUE"""),"Anota Ai Solucoes Digitais S/a") -> Anota Ai Solucoes Digitais S/a | AZ15: =IFERROR(__xludf.DUMMYFUNCTION("""COMPUTED_VALUE"""),"Japonesa") -> Japonesa | BA15: =IFERROR(__xludf.DUMMYFUNCTION("""COMPUTED_VALUE"""),60.0) -> 60 | BB15: =IFERROR(__xludf.DUMMYFUNCTION("""COMPUTED_VALUE"""),"Delivery First - Temakeria") -> Delivery First - Temakeria | BC15: =IFERROR(__xludf.DUMMYFUNCTION("""COMPUTED_VALUE"""),"Regional") -> Regional | BE15: =IFERROR(__xludf.DUMMYFUNCTION("""COMPUTED_VALUE"""),45.0) -> 45 | BF15: =IFERROR(__xludf.DUMMYFUNCTION("""COMPUTED_VALUE"""),0.5) -> 0.5 | BG15: =IFERROR(__xludf.DUMMYFUNCTION("""COMPUTED_VALUE"""),"Aderência moderada ao 3S: PDV atual não identificado. 3S pode agregar valor com padronização multi-loja e integração delivery, mas necessário Discovery para validar fit completo.") -> Aderência moderada ao 3S: PDV atual não identificado. 3S pode agregar valor com padronização multi-loja e integração delivery, mas necessário Discovery para validar fit completo. | BH15: Anota Ai Solucoes Digitais S/a | BI15: 0.66666667
A16: =IFERROR(__xludf.DUMMYFUNCTION("""COMPUTED_VALUE"""),"BABY BEEF EXPRESS") -> BABY BEEF EXPRESS | B16: =IFERROR(__xludf.DUMMYFUNCTION("""COMPUTED_VALUE"""),"João Biagiotti") -> João Biagiotti | C16: =IFERROR(__xludf.DUMMYFUNCTION("""COMPUTED_VALUE"""),"Diego Santos") -> Diego Santos | D16: =IFERROR(__xludf.DUMMYFUNCTION("""COMPUTED_VALUE"""),"2. Primeiro Contato com a marca") -> 2. Primeiro Contato com a marca | E16: =IFERROR(__xludf.DUMMYFUNCTION("""COMPUTED_VALUE"""),"Delivery - Conciliação agenda com parceiro") -> Delivery - Conciliação agenda com parceiro | F16: =IFERROR(__xludf.DUMMYFUNCTION("""COMPUTED_VALUE"""),"P") -> P | G16: =IFERROR(__xludf.DUMMYFUNCTION("""COMPUTED_VALUE"""),46134.0) -> 46134 | H16: =IFERROR(__xludf.DUMMYFUNCTION("""COMPUTED_VALUE"""),"Valeria (coord) informou que o gerrente esta de férias, assim que voltar iremos agendar uma reunião com os mesmos") -> Valeria (coord) informou que o gerrente esta de férias, assim que voltar iremos agendar uma reunião com os mesmos | I16: =IFERROR(__xludf.DUMMYFUNCTION("""COMPUTED_VALUE"""),46134.455329895834) -> 46134.455 | J16: =IFERROR(__xludf.DUMMYFUNCTION("""COMPUTED_VALUE"""),46134.45850049768) -> 46134.459 | AA16: =IFERROR(__xludf.DUMMYFUNCTION("""COMPUTED_VALUE"""),13.0) -> 13 | AB16: =IFERROR(__xludf.DUMMYFUNCTION("""COMPUTED_VALUE"""),"CE") -> CE | AC16: =IFERROR(__xludf.DUMMYFUNCTION("""COMPUTED_VALUE"""),"Sim") -> Sim | AD16: =IFERROR(__xludf.DUMMYFUNCTION("""COMPUTED_VALUE"""),"Ifood") -> Ifood | AM16: =IFERROR(__xludf.DUMMYFUNCTION("""COMPUTED_VALUE"""),"FY27") -> FY27 | AO16: =IFERROR(__xludf.DUMMYFUNCTION("""COMPUTED_VALUE"""),81.0) -> 81 | AP16: =IFERROR(__xludf.DUMMYFUNCTION("""COMPUTED_VALUE"""),"BA") -> BA | AQ16: =IFERROR(__xludf.DUMMYFUNCTION("""COMPUTED_VALUE"""),"VIDOLIN EDUARDO") -> VIDOLIN EDUARDO | AR16: =IFERROR(__xludf.DUMMYFUNCTION("""COMPUTED_VALUE"""),"VALERIA VASCONCELOS") -> VALERIA VASCONCELOS | AS16: =IFERROR(__xludf.DUMMYFUNCTION("""COMPUTED_VALUE"""),"THIAGO ROMAGNOLE") -> THIAGO ROMAGNOLE | AT16: =IFERROR(__xludf.DUMMYFUNCTION("""COMPUTED_VALUE"""),"EDUARDO VAZ") -> EDUARDO VAZ | AU16: =IFERROR(__xludf.DUMMYFUNCTION("""COMPUTED_VALUE"""),0.0) -> 0 | AV16: =IFERROR(__xludf.DUMMYFUNCTION("""COMPUTED_VALUE"""),0.0) -> 0 | AW16: =IFERROR(__xludf.DUMMYFUNCTION("""COMPUTED_VALUE"""),0.0) -> 0 | AX16: =IFERROR(__xludf.DUMMYFUNCTION("""COMPUTED_VALUE"""),0.0) -> 0 | AZ16: =IFERROR(__xludf.DUMMYFUNCTION("""COMPUTED_VALUE"""),"Lanches") -> Lanches | BA16: =IFERROR(__xludf.DUMMYFUNCTION("""COMPUTED_VALUE"""),60.0) -> 60 | BB16: =IFERROR(__xludf.DUMMYFUNCTION("""COMPUTED_VALUE"""),"Fast Casual - Grelhados") -> Fast Casual - Grelhados | BC16: =IFERROR(__xludf.DUMMYFUNCTION("""COMPUTED_VALUE"""),"Salvador/BA (shoppings)") -> Salvador/BA (shoppings) | BE16: =IFERROR(__xludf.DUMMYFUNCTION("""COMPUTED_VALUE"""),65.0) -> 65 | BF16: =IFERROR(__xludf.DUMMYFUNCTION("""COMPUTED_VALUE"""),0.75) -> 0.75 | BG16: =IFERROR(__xludf.DUMMYFUNCTION("""COMPUTED_VALUE"""),"Aderência forte ao 3S: PDV atual não identificado. 3S oferece PDV robusto, KDS integrado e mobilidade (3SGO) para gestão em tempo real - ideal para operações multi-canal.") -> Aderência forte ao 3S: PDV atual não identificado. 3S oferece PDV robusto, KDS integrado e mobilidade (3SGO) para gestão em tempo real - ideal para operações multi-canal. | BH16: null | BI16: 0.57142857
A17: =IFERROR(__xludf.DUMMYFUNCTION("""COMPUTED_VALUE"""),"BANZAI ES") -> BANZAI ES | B17: =IFERROR(__xludf.DUMMYFUNCTION("""COMPUTED_VALUE"""),"Lídia Esteves") -> Lídia Esteves | C17: =IFERROR(__xludf.DUMMYFUNCTION("""COMPUTED_VALUE"""),"Gabriela Roma") -> Gabriela Roma | D17: =IFERROR(__xludf.DUMMYFUNCTION("""COMPUTED_VALUE"""),"0. Não Iniciado") -> 0. Não Iniciado | F17: =IFERROR(__xludf.DUMMYFUNCTION("""COMPUTED_VALUE"""),"P") -> P | AA17: =IFERROR(__xludf.DUMMYFUNCTION("""COMPUTED_VALUE"""),7.0) -> 7 | AB17: =IFERROR(__xludf.DUMMYFUNCTION("""COMPUTED_VALUE"""),"CE") -> CE | AC17: =IFERROR(__xludf.DUMMYFUNCTION("""COMPUTED_VALUE"""),"Sim") -> Sim | AD17: =IFERROR(__xludf.DUMMYFUNCTION("""COMPUTED_VALUE"""),"Ifood") -> Ifood | AM17: =IFERROR(__xludf.DUMMYFUNCTION("""COMPUTED_VALUE"""),"FY27") -> FY27 | AO17: =IFERROR(__xludf.DUMMYFUNCTION("""COMPUTED_VALUE"""),45553.0) -> 45553 | AP17: =IFERROR(__xludf.DUMMYFUNCTION("""COMPUTED_VALUE"""),"ES") -> ES | AQ17: =IFERROR(__xludf.DUMMYFUNCTION("""COMPUTED_VALUE"""),"LORENA PACHECO") -> LORENA PACHECO | AR17: =IFERROR(__xludf.DUMMYFUNCTION("""COMPUTED_VALUE"""),"THAYNA MARINS") -> THAYNA MARINS | AS17: =IFERROR(__xludf.DUMMYFUNCTION("""COMPUTED_VALUE"""),"FABIO DONATO") -> FABIO DONATO | AT17: =IFERROR(__xludf.DUMMYFUNCTION("""COMPUTED_VALUE"""),"GILSON JUNIOR") -> GILSON JUNIOR | AU17: =IFERROR(__xludf.DUMMYFUNCTION("""COMPUTED_VALUE"""),0.0) -> 0 | AV17: =IFERROR(__xludf.DUMMYFUNCTION("""COMPUTED_VALUE"""),0.0) -> 0 | AW17: =IFERROR(__xludf.DUMMYFUNCTION("""COMPUTED_VALUE"""),0.0) -> 0 | AX17: =IFERROR(__xludf.DUMMYFUNCTION("""COMPUTED_VALUE"""),0.0) -> 0 | AY17: =IFERROR(__xludf.DUMMYFUNCTION("""COMPUTED_VALUE"""),"Tigoo Serviços Ltda.") -> Tigoo Serviços Ltda. | AZ17: =IFERROR(__xludf.DUMMYFUNCTION("""COMPUTED_VALUE"""),"Japonesa") -> Japonesa | BA17: =IFERROR(__xludf.DUMMYFUNCTION("""COMPUTED_VALUE"""),65.0) -> 65 | BB17: =IFERROR(__xludf.DUMMYFUNCTION("""COMPUTED_VALUE"""),"Fast Casual - Comida Japonesa") -> Fast Casual - Comida Japonesa | BC17: =IFERROR(__xludf.DUMMYFUNCTION("""COMPUTED_VALUE"""),"Espírito Santo") -> Espírito Santo | BE17: =IFERROR(__xludf.DUMMYFUNCTION("""COMPUTED_VALUE"""),70.0) -> 70 | BF17: =IFERROR(__xludf.DUMMYFUNCTION("""COMPUTED_VALUE"""),0.75) -> 0.75 | BG17: =IFERROR(__xludf.DUMMYFUNCTION("""COMPUTED_VALUE"""),"Aderência forte ao 3S: PDV atual não identificado. 3S oferece PDV robusto, KDS integrado e mobilidade (3SGO) para gestão em tempo real - ideal para operações multi-canal.") -> Aderência forte ao 3S: PDV atual não identificado. 3S oferece PDV robusto, KDS integrado e mobilidade (3SGO) para gestão em tempo real - ideal para operações multi-canal. | BH17: Tigoo Serviços Ltda. | BI17: 0.5
A18: =IFERROR(__xludf.DUMMYFUNCTION("""COMPUTED_VALUE"""),"BAR DO ELIAS") -> BAR DO ELIAS | B18: =IFERROR(__xludf.DUMMYFUNCTION("""COMPUTED_VALUE"""),"Lídia Esteves") -> Lídia Esteves | C18: =IFERROR(__xludf.DUMMYFUNCTION("""COMPUTED_VALUE"""),"Gabriela Roma") -> Gabriela Roma | D18: =IFERROR(__xludf.DUMMYFUNCTION("""COMPUTED_VALUE"""),"1. Iniciado") -> 1. Iniciado | E18: =IFERROR(__xludf.DUMMYFUNCTION("""COMPUTED_VALUE"""),"Delivery - Aguardando retorno / Conciliação agenda") -> Delivery - Aguardando retorno / Conciliação agenda | F18: =IFERROR(__xludf.DUMMYFUNCTION("""COMPUTED_VALUE"""),"P") -> P | I18: =IFERROR(__xludf.DUMMYFUNCTION("""COMPUTED_VALUE"""),46122.672642314814) -> 46122.673 | AA18: =IFERROR(__xludf.DUMMYFUNCTION("""COMPUTED_VALUE"""),8.0) -> 8 | AB18: =IFERROR(__xludf.DUMMYFUNCTION("""COMPUTED_VALUE"""),"CE") -> CE | AC18: =IFERROR(__xludf.DUMMYFUNCTION("""COMPUTED_VALUE"""),"Sim") -> Sim | AD18: =IFERROR(__xludf.DUMMYFUNCTION("""COMPUTED_VALUE"""),"Ifood") -> Ifood | AM18: =IFERROR(__xludf.DUMMYFUNCTION("""COMPUTED_VALUE"""),"FY27") -> FY27 | AO18: =IFERROR(__xludf.DUMMYFUNCTION("""COMPUTED_VALUE"""),45553.0) -> 45553 | AP18: =IFERROR(__xludf.DUMMYFUNCTION("""COMPUTED_VALUE"""),"RJ") -> RJ | AQ18: =IFERROR(__xludf.DUMMYFUNCTION("""COMPUTED_VALUE"""),"ANA SALLES") -> ANA SALLES | AR18: =IFERROR(__xludf.DUMMYFUNCTION("""COMPUTED_VALUE"""),"MARCELLA BRAGA") -> MARCELLA BRAGA | AS18: =IFERROR(__xludf.DUMMYFUNCTION("""COMPUTED_VALUE"""),"NATHALIE MERTENS") -> NATHALIE MERTENS | AT18: =IFERROR(__xludf.DUMMYFUNCTION("""COMPUTED_VALUE"""),"NATALIA COUTINHO") -> NATALIA COUTINHO | AU18: =IFERROR(__xludf.DUMMYFUNCTION("""COMPUTED_VALUE"""),0.0) -> 0 | AV18: =IFERROR(__xludf.DUMMYFUNCTION("""COMPUTED_VALUE"""),0.0) -> 0 | AW18: =IFERROR(__xludf.DUMMYFUNCTION("""COMPUTED_VALUE"""),0.0) -> 0 | AX18: =IFERROR(__xludf.DUMMYFUNCTION("""COMPUTED_VALUE"""),0.0) -> 0 | AZ18: =IFERROR(__xludf.DUMMYFUNCTION("""COMPUTED_VALUE"""),"Árabe") -> Árabe | BA18: =IFERROR(__xludf.DUMMYFUNCTION("""COMPUTED_VALUE"""),75.0) -> 75 | BB18: =IFERROR(__xludf.DUMMYFUNCTION("""COMPUTED_VALUE"""),"Table Service - Boteco") -> Table Service - Boteco | BC18: =IFERROR(__xludf.DUMMYFUNCTION("""COMPUTED_VALUE"""),"Regional") -> Regional | BE18: =IFERROR(__xludf.DUMMYFUNCTION("""COMPUTED_VALUE"""),55.0) -> 55 | BF18: =IFERROR(__xludf.DUMMYFUNCTION("""COMPUTED_VALUE"""),0.65) -> 0.65 | BG18: =IFERROR(__xludf.DUMMYFUNCTION("""COMPUTED_VALUE"""),"Aderência forte ao 3S: PDV atual não identificado. 3S oferece PDV robusto, KDS integrado e mobilidade (3SGO) para gestão em tempo real - ideal para operações multi-canal.") -> Aderência forte ao 3S: PDV atual não identificado. 3S oferece PDV robusto, KDS integrado e mobilidade (3SGO) para gestão em tempo real - ideal para operações multi-canal.
A19: =IFERROR(__xludf.DUMMYFUNCTION("""COMPUTED_VALUE"""),"BB DOG") -> BB DOG | B19: =IFERROR(__xludf.DUMMYFUNCTION("""COMPUTED_VALUE"""),"Lídia Esteves") -> Lídia Esteves | C19: =IFERROR(__xludf.DUMMYFUNCTION("""COMPUTED_VALUE"""),"Gabriela Roma") -> Gabriela Roma | D19: =IFERROR(__xludf.DUMMYFUNCTION("""COMPUTED_VALUE"""),"0. Não Iniciado") -> 0. Não Iniciado | F19: =IFERROR(__xludf.DUMMYFUNCTION("""COMPUTED_VALUE"""),"P") -> P | AA19: =IFERROR(__xludf.DUMMYFUNCTION("""COMPUTED_VALUE"""),6.0) -> 6 | AB19: =IFERROR(__xludf.DUMMYFUNCTION("""COMPUTED_VALUE"""),"CE") -> CE | AC19: =IFERROR(__xludf.DUMMYFUNCTION("""COMPUTED_VALUE"""),"Sim") -> Sim | AD19: =IFERROR(__xludf.DUMMYFUNCTION("""COMPUTED_VALUE"""),"Ifood") -> Ifood | AM19: =IFERROR(__xludf.DUMMYFUNCTION("""COMPUTED_VALUE"""),"FY27") -> FY27 | AO19: =IFERROR(__xludf.DUMMYFUNCTION("""COMPUTED_VALUE"""),45553.0) -> 45553 | AP19: =IFERROR(__xludf.DUMMYFUNCTION("""COMPUTED_VALUE"""),"SP") -> SP | AQ19: =IFERROR(__xludf.DUMMYFUNCTION("""COMPUTED_VALUE"""),"EMILLY BIASI") -> EMILLY BIASI | AR19: =IFERROR(__xludf.DUMMYFUNCTION("""COMPUTED_VALUE"""),"MONICA VICTORIO") -> MONICA VICTORIO | AS19: =IFERROR(__xludf.DUMMYFUNCTION("""COMPUTED_VALUE"""),"ALAN HADDAD") -> ALAN HADDAD | AT19: =IFERROR(__xludf.DUMMYFUNCTION("""COMPUTED_VALUE"""),"ISABELA DINIZ") -> ISABELA DINIZ | AU19: =IFERROR(__xludf.DUMMYFUNCTION("""COMPUTED_VALUE"""),0.0) -> 0 | AV19: =IFERROR(__xludf.DUMMYFUNCTION("""COMPUTED_VALUE"""),0.0) -> 0 | AW19: =IFERROR(__xludf.DUMMYFUNCTION("""COMPUTED_VALUE"""),0.0) -> 0 | AX19: =IFERROR(__xludf.DUMMYFUNCTION("""COMPUTED_VALUE"""),0.0) -> 0 | AZ19: =IFERROR(__xludf.DUMMYFUNCTION("""COMPUTED_VALUE"""),"Lanches") -> Lanches | BA19: =IFERROR(__xludf.DUMMYFUNCTION("""COMPUTED_VALUE"""),25.0) -> 25 | BB19: =IFERROR(__xludf.DUMMYFUNCTION("""COMPUTED_VALUE"""),"QSR - Hot Dog") -> QSR - Hot Dog | BC19: =IFERROR(__xludf.DUMMYFUNCTION("""COMPUTED_VALUE"""),"Regional") -> Regional | BE19: =IFERROR(__xludf.DUMMYFUNCTION("""COMPUTED_VALUE"""),70.0) -> 70 | BF19: =IFERROR(__xludf.DUMMYFUNCTION("""COMPUTED_VALUE"""),0.85) -> 0.85 | BG19: =IFERROR(__xludf.DUMMYFUNCTION("""COMPUTED_VALUE"""),"Alta aderência ao 3S: PDV atual não identificado. 3S oferece Kiosk nativo, Hub Delivery integrado e gestão centralizada multi-loja - diferenciais competitivos para expansão e redução de filas.") -> Alta aderência ao 3S: PDV atual não identificado. 3S oferece Kiosk nativo, Hub Delivery integrado e gestão centralizada multi-loja - diferenciais competitivos para expansão e redução de filas. | BH19: Saipos Serviços De Software | BI19: 1
A20: =IFERROR(__xludf.DUMMYFUNCTION("""COMPUTED_VALUE"""),"BELLA PIZZA") -> BELLA PIZZA | B20: =IFERROR(__xludf.DUMMYFUNCTION("""COMPUTED_VALUE"""),"João Biagiotti") -> João Biagiotti | C20: =IFERROR(__xludf.DUMMYFUNCTION("""COMPUTED_VALUE"""),"Diego Santos") -> Diego Santos | D20: =IFERROR(__xludf.DUMMYFUNCTION("""COMPUTED_VALUE"""),"0. Não Iniciado") -> 0. Não Iniciado | F20: =IFERROR(__xludf.DUMMYFUNCTION("""COMPUTED_VALUE"""),"P") -> P | AA20: =IFERROR(__xludf.DUMMYFUNCTION("""COMPUTED_VALUE"""),11.0) -> 11 | AB20: =IFERROR(__xludf.DUMMYFUNCTION("""COMPUTED_VALUE"""),"CE") -> CE | AC20: =IFERROR(__xludf.DUMMYFUNCTION("""COMPUTED_VALUE"""),"Sim") -> Sim | AD20: =IFERROR(__xludf.DUMMYFUNCTION("""COMPUTED_VALUE"""),"Ifood") -> Ifood | AM20: =IFERROR(__xludf.DUMMYFUNCTION("""COMPUTED_VALUE"""),"FY27") -> FY27 | AO20: =IFERROR(__xludf.DUMMYFUNCTION("""COMPUTED_VALUE"""),45553.0) -> 45553 | AP20: =IFERROR(__xludf.DUMMYFUNCTION("""COMPUTED_VALUE"""),"PB") -> PB | AQ20: =IFERROR(__xludf.DUMMYFUNCTION("""COMPUTED_VALUE"""),"ANA ARAUJO") -> ANA ARAUJO | AR20: =IFERROR(__xludf.DUMMYFUNCTION("""COMPUTED_VALUE"""),"TAINAR ALBUQUERQUE") -> TAINAR ALBUQUERQUE | AS20: =IFERROR(__xludf.DUMMYFUNCTION("""COMPUTED_VALUE"""),"THIAGO ROMAGNOLE") -> THIAGO ROMAGNOLE | AT20: =IFERROR(__xludf.DUMMYFUNCTION("""COMPUTED_VALUE"""),"ANDERSON LAUREANO") -> ANDERSON LAUREANO | AU20: =IFERROR(__xludf.DUMMYFUNCTION("""COMPUTED_VALUE"""),0.0) -> 0 | AV20: =IFERROR(__xludf.DUMMYFUNCTION("""COMPUTED_VALUE"""),0.0) -> 0 | AW20: =IFERROR(__xludf.DUMMYFUNCTION("""COMPUTED_VALUE"""),0.0) -> 0 | AX20: =IFERROR(__xludf.DUMMYFUNCTION("""COMPUTED_VALUE"""),0.0) -> 0 | AY20: =IFERROR(__xludf.DUMMYFUNCTION("""COMPUTED_VALUE"""),"Saipos Serviços De Software") -> Saipos Serviços De Software | AZ20: =IFERROR(__xludf.DUMMYFUNCTION("""COMPUTED_VALUE"""),"Pizza") -> Pizza | BA20: =IFERROR(__xludf.DUMMYFUNCTION("""COMPUTED_VALUE"""),70.0) -> 70 | BB20: =IFERROR(__xludf.DUMMYFUNCTION("""COMPUTED_VALUE"""),"Fast Casual - Pizzaria") -> Fast Casual - Pizzaria | BC20: =IFERROR(__xludf.DUMMYFUNCTION("""COMPUTED_VALUE"""),"Regional") -> Regional | BE20: =IFERROR(__xludf.DUMMYFUNCTION("""COMPUTED_VALUE"""),65.0) -> 65 | BF20: =IFERROR(__xludf.DUMMYFUNCTION("""COMPUTED_VALUE"""),0.75) -> 0.75 | BG20: =IFERROR(__xludf.DUMMYFUNCTION("""COMPUTED_VALUE"""),"Aderência forte ao 3S: PDV atual não identificado. 3S oferece PDV robusto, KDS integrado e mobilidade (3SGO) para gestão em tempo real - ideal para operações multi-canal.") -> Aderência forte ao 3S: PDV atual não identificado. 3S oferece PDV robusto, KDS integrado e mobilidade (3SGO) para gestão em tempo real - ideal para operações multi-canal. | BH20: Saipos Serviços De Software | BI20: 0.25
A21: =IFERROR(__xludf.DUMMYFUNCTION("""COMPUTED_VALUE"""),"BELLA SUSHI") -> BELLA SUSHI | B21: =IFERROR(__xludf.DUMMYFUNCTION("""COMPUTED_VALUE"""),"João Biagiotti") -> João Biagiotti | C21: =IFERROR(__xludf.DUMMYFUNCTION("""COMPUTED_VALUE"""),"Diego Santos") -> Diego Santos | D21: =IFERROR(__xludf.DUMMYFUNCTION("""COMPUTED_VALUE"""),"0. Não Iniciado") -> 0. Não Iniciado | F21: =IFERROR(__xludf.DUMMYFUNCTION("""COMPUTED_VALUE"""),"P") -> P | AA21: =IFERROR(__xludf.DUMMYFUNCTION("""COMPUTED_VALUE"""),8.0) -> 8 | AB21: =IFERROR(__xludf.DUMMYFUNCTION("""COMPUTED_VALUE"""),"CE") -> CE | AC21: =IFERROR(__xludf.DUMMYFUNCTION("""COMPUTED_VALUE"""),"Sim") -> Sim | AD21: =IFERROR(__xludf.DUMMYFUNCTION("""COMPUTED_VALUE"""),"Ifood") -> Ifood | AM21: =IFERROR(__xludf.DUMMYFUNCTION("""COMPUTED_VALUE"""),"FY27") -> FY27 | AO21: =IFERROR(__xludf.DUMMYFUNCTION("""COMPUTED_VALUE"""),45553.0) -> 45553 | AP21: =IFERROR(__xludf.DUMMYFUNCTION("""COMPUTED_VALUE"""),"SP") -> SP | AQ21: =IFERROR(__xludf.DUMMYFUNCTION("""COMPUTED_VALUE"""),"ANDRE VALENTIM") -> ANDRE VALENTIM | AR21: =IFERROR(__xludf.DUMMYFUNCTION("""COMPUTED_VALUE"""),"RAQUEL AGUIAR") -> RAQUEL AGUIAR | AS21: =IFERROR(__xludf.DUMMYFUNCTION("""COMPUTED_VALUE"""),"NATHALIE MERTENS") -> NATHALIE MERTENS | AT21: =IFERROR(__xludf.DUMMYFUNCTION("""COMPUTED_VALUE"""),"CIBELE OLIVEIRA") -> CIBELE OLIVEIRA | AU21: =IFERROR(__xludf.DUMMYFUNCTION("""COMPUTED_VALUE"""),0.0) -> 0 | AV21: =IFERROR(__xludf.DUMMYFUNCTION("""COMPUTED_VALUE"""),0.0) -> 0 | AW21: =IFERROR(__xludf.DUMMYFUNCTION("""COMPUTED_VALUE"""),0.0) -> 0 | AX21: =IFERROR(__xludf.DUMMYFUNCTION("""COMPUTED_VALUE"""),0.0) -> 0 | AZ21: =IFERROR(__xludf.DUMMYFUNCTION("""COMPUTED_VALUE"""),"Pizza") -> Pizza | BA21: =IFERROR(__xludf.DUMMYFUNCTION("""COMPUTED_VALUE"""),80.0) -> 80 | BB21: =IFERROR(__xludf.DUMMYFUNCTION("""COMPUTED_VALUE"""),"Fast Casual - Sushi") -> Fast Casual - Sushi | BC21: =IFERROR(__xludf.DUMMYFUNCTION("""COMPUTED_VALUE"""),"Regional") -> Regional | BE21: =IFERROR(__xludf.DUMMYFUNCTION("""COMPUTED_VALUE"""),65.0) -> 65 | BF21: =IFERROR(__xludf.DUMMYFUNCTION("""COMPUTED_VALUE"""),0.75) -> 0.75 | BG21: =IFERROR(__xludf.DUMMYFUNCTION("""COMPUTED_VALUE"""),"Aderência forte ao 3S: PDV atual não identificado. 3S oferece PDV robusto, KDS integrado e mobilidade (3SGO) para gestão em tempo real - ideal para operações multi-canal.") -> Aderência forte ao 3S: PDV atual não identificado. 3S oferece PDV robusto, KDS integrado e mobilidade (3SGO) para gestão em tempo real - ideal para operações multi-canal. | BH21: Winfood | BI21: 0.42857143
A22: =IFERROR(__xludf.DUMMYFUNCTION("""COMPUTED_VALUE"""),"BENDITA ESFIHA") -> BENDITA ESFIHA | B22: =IFERROR(__xludf.DUMMYFUNCTION("""COMPUTED_VALUE"""),"João Biagiotti") -> João Biagiotti | C22: =IFERROR(__xludf.DUMMYFUNCTION("""COMPUTED_VALUE"""),"Diego Santos") -> Diego Santos | D22: =IFERROR(__xludf.DUMMYFUNCTION("""COMPUTED_VALUE"""),"0. Não Iniciado") -> 0. Não Iniciado | F22: =IFERROR(__xludf.DUMMYFUNCTION("""COMPUTED_VALUE"""),"P") -> P | AA22: =IFERROR(__xludf.DUMMYFUNCTION("""COMPUTED_VALUE"""),5.0) -> 5 | AB22: =IFERROR(__xludf.DUMMYFUNCTION("""COMPUTED_VALUE"""),"CE") -> CE | AC22: =IFERROR(__xludf.DUMMYFUNCTION("""COMPUTED_VALUE"""),"Sim") -> Sim | AD22: =IFERROR(__xludf.DUMMYFUNCTION("""COMPUTED_VALUE"""),"Ifood") -> Ifood | AM22: =IFERROR(__xludf.DUMMYFUNCTION("""COMPUTED_VALUE"""),"FY27") -> FY27 | AO22: =IFERROR(__xludf.DUMMYFUNCTION("""COMPUTED_VALUE"""),45553.0) -> 45553 | AP22: =IFERROR(__xludf.DUMMYFUNCTION("""COMPUTED_VALUE"""),"SP") -> SP | AQ22: =IFERROR(__xludf.DUMMYFUNCTION("""COMPUTED_VALUE"""),"KAREN SOUTO") -> KAREN SOUTO | AR22: =IFERROR(__xludf.DUMMYFUNCTION("""COMPUTED_VALUE"""),"FILIPE FERNANDES") -> FILIPE FERNANDES | AS22: =IFERROR(__xludf.DUMMYFUNCTION("""COMPUTED_VALUE"""),"NATHALIE MERTENS") -> NATHALIE MERTENS | AT22: =IFERROR(__xludf.DUMMYFUNCTION("""COMPUTED_VALUE"""),"CIBELE OLIVEIRA") -> CIBELE OLIVEIRA | AU22: =IFERROR(__xludf.DUMMYFUNCTION("""COMPUTED_VALUE"""),0.0) -> 0 | AV22: =IFERROR(__xludf.DUMMYFUNCTION("""COMPUTED_VALUE"""),0.0) -> 0 | AW22: =IFERROR(__xludf.DUMMYFUNCTION("""COMPUTED_VALUE"""),0.0) -> 0 | AX22: =IFERROR(__xludf.DUMMYFUNCTION("""COMPUTED_VALUE"""),0.0) -> 0 | AZ22: =IFERROR(__xludf.DUMMYFUNCTION("""COMPUTED_VALUE"""),"Brasileira") -> Brasileira | BA22: =IFERROR(__xludf.DUMMYFUNCTION("""COMPUTED_VALUE"""),45.0) -> 45 | BB22: =IFERROR(__xludf.DUMMYFUNCTION("""COMPUTED_VALUE"""),"Fast Casual - Esfiharia") -> Fast Casual - Esfiharia | BC22: =IFERROR(__xludf.DUMMYFUNCTION("""COMPUTED_VALUE"""),"São Bernardo do Campo/SP") -> São Bernardo do Campo/SP | BE22: =IFERROR(__xludf.DUMMYFUNCTION("""COMPUTED_VALUE"""),65.0) -> 65 | BF22: =IFERROR(__xludf.DUMMYFUNCTION("""COMPUTED_VALUE"""),0.75) -> 0.75 | BG22: =IFERROR(__xludf.DUMMYFUNCTION("""COMPUTED_VALUE"""),"Aderência forte ao 3S: PDV atual não identificado. 3S oferece PDV robusto, KDS integrado e mobilidade (3SGO) para gestão em tempo real - ideal para operações multi-canal.") -> Aderência forte ao 3S: PDV atual não identificado. 3S oferece PDV robusto, KDS integrado e mobilidade (3SGO) para gestão em tempo real - ideal para operações multi-canal. | BH22: Eclética Tecnologia | BI22: 0.6
A23: =IFERROR(__xludf.DUMMYFUNCTION("""COMPUTED_VALUE"""),"BENTO ACAITERIA") -> BENTO ACAITERIA | B23: =IFERROR(__xludf.DUMMYFUNCTION("""COMPUTED_VALUE"""),"Lídia Esteves") -> Lídia Esteves | C23: =IFERROR(__xludf.DUMMYFUNCTION("""COMPUTED_VALUE"""),"Gabriela Roma") -> Gabriela Roma | D23: =IFERROR(__xludf.DUMMYFUNCTION("""COMPUTED_VALUE"""),"0. Não Iniciado") -> 0. Não Iniciado | F23: =IFERROR(__xludf.DUMMYFUNCTION("""COMPUTED_VALUE"""),"P") -> P | AA23: =IFERROR(__xludf.DUMMYFUNCTION("""COMPUTED_VALUE"""),10.0) -> 10 | AB23: =IFERROR(__xludf.DUMMYFUNCTION("""COMPUTED_VALUE"""),"CE") -> CE | AC23: =IFERROR(__xludf.DUMMYFUNCTION("""COMPUTED_VALUE"""),"Sim") -> Sim | AD23: =IFERROR(__xludf.DUMMYFUNCTION("""COMPUTED_VALUE"""),"Ifood") -> Ifood | AM23: =IFERROR(__xludf.DUMMYFUNCTION("""COMPUTED_VALUE"""),"FY27") -> FY27 | AO23: =IFERROR(__xludf.DUMMYFUNCTION("""COMPUTED_VALUE"""),45553.0) -> 45553 | AP23: =IFERROR(__xludf.DUMMYFUNCTION("""COMPUTED_VALUE"""),"RS") -> RS | AQ23: =IFERROR(__xludf.DUMMYFUNCTION("""COMPUTED_VALUE"""),"SHAYANA JACOM") -> SHAYANA JACOM | AR23: =IFERROR(__xludf.DUMMYFUNCTION("""COMPUTED_VALUE"""),"GABRIEL RUAS") -> GABRIEL RUAS | AS23: =IFERROR(__xludf.DUMMYFUNCTION("""COMPUTED_VALUE"""),"FABIO DONATO") -> FABIO DONATO | AT23: =IFERROR(__xludf.DUMMYFUNCTION("""COMPUTED_VALUE"""),"CAMILA HOLANDA") -> CAMILA HOLANDA | AU23: =IFERROR(__xludf.DUMMYFUNCTION("""COMPUTED_VALUE"""),0.0) -> 0 | AV23: =IFERROR(__xludf.DUMMYFUNCTION("""COMPUTED_VALUE"""),0.0) -> 0 | AW23: =IFERROR(__xludf.DUMMYFUNCTION("""COMPUTED_VALUE"""),0.0) -> 0 | AX23: =IFERROR(__xludf.DUMMYFUNCTION("""COMPUTED_VALUE"""),0.0) -> 0 | AZ23: =IFERROR(__xludf.DUMMYFUNCTION("""COMPUTED_VALUE"""),"Açaí") -> Açaí | BA23: =IFERROR(__xludf.DUMMYFUNCTION("""COMPUTED_VALUE"""),"") | BB23: =IFERROR(__xludf.DUMMYFUNCTION("""COMPUTED_VALUE"""),"") | BC23: =IFERROR(__xludf.DUMMYFUNCTION("""COMPUTED_VALUE"""),"") | BD23: =IFERROR(__xludf.DUMMYFUNCTION("""COMPUTED_VALUE"""),"") | BE23: =IFERROR(__xludf.DUMMYFUNCTION("""COMPUTED_VALUE"""),"") | BF23: =IFERROR(__xludf.DUMMYFUNCTION("""COMPUTED_VALUE"""),"") | BG23: =IFERROR(__xludf.DUMMYFUNCTION("""COMPUTED_VALUE"""),"")
A24: =IFERROR(__xludf.DUMMYFUNCTION("""COMPUTED_VALUE"""),"BERCY VILLAGE") -> BERCY VILLAGE | B24: =IFERROR(__xludf.DUMMYFUNCTION("""COMPUTED_VALUE"""),"João Biagiotti") -> João Biagiotti | C24: =IFERROR(__xludf.DUMMYFUNCTION("""COMPUTED_VALUE"""),"Diego Santos") -> Diego Santos | D24: =IFERROR(__xludf.DUMMYFUNCTION("""COMPUTED_VALUE"""),"10. Perdido") -> 10. Perdido | E24: =IFERROR(__xludf.DUMMYFUNCTION("""COMPUTED_VALUE"""),"Perdido - Momento do restaurante não favorável") -> Perdido - Momento do restaurante não favorável | F24: =IFERROR(__xludf.DUMMYFUNCTION("""COMPUTED_VALUE"""),"P") -> P | G24: =IFERROR(__xludf.DUMMYFUNCTION("""COMPUTED_VALUE"""),46119.0) -> 46119 | H24: =IFERROR(__xludf.DUMMYFUNCTION("""COMPUTED_VALUE"""),"Já foi realizado uma agenda presencial com a marca, no qual a diretoria nao quer seguir. ") -> Já foi realizado uma agenda presencial com a marca, no qual a diretoria nao quer seguir. | I24: =IFERROR(__xludf.DUMMYFUNCTION("""COMPUTED_VALUE"""),46120.59670476852) -> 46120.597 | J24: =IFERROR(__xludf.DUMMYFUNCTION("""COMPUTED_VALUE"""),46125.436089201394) -> 46125.436 | R24: =IFERROR(__xludf.DUMMYFUNCTION("""COMPUTED_VALUE"""),46129.49547576389) -> 46129.495 | V24: =IFERROR(__xludf.DUMMYFUNCTION("""COMPUTED_VALUE"""),"Sem interesse em mudar de PDV") -> Sem interesse em mudar de PDV | AA24: =IFERROR(__xludf.DUMMYFUNCTION("""COMPUTED_VALUE"""),8.0) -> 8 | AB24: =IFERROR(__xludf.DUMMYFUNCTION("""COMPUTED_VALUE"""),"CE") -> CE | AC24: =IFERROR(__xludf.DUMMYFUNCTION("""COMPUTED_VALUE"""),"Sim") -> Sim | AD24: =IFERROR(__xludf.DUMMYFUNCTION("""COMPUTED_VALUE"""),"Ifood") -> Ifood | AM24: =IFERROR(__xludf.DUMMYFUNCTION("""COMPUTED_VALUE"""),"FY27") -> FY27 | AO24: =IFERROR(__xludf.DUMMYFUNCTION("""COMPUTED_VALUE"""),96.0) -> 96 | AP24: =IFERROR(__xludf.DUMMYFUNCTION("""COMPUTED_VALUE"""),"SP") -> SP | AQ24: =IFERROR(__xludf.DUMMYFUNCTION("""COMPUTED_VALUE"""),"JENNIFER SIQUEIRA") -> JENNIFER SIQUEIRA | AR24: =IFERROR(__xludf.DUMMYFUNCTION("""COMPUTED_VALUE"""),"TERESA SIMOES") -> TERESA SIMOES | AS24: =IFERROR(__xludf.DUMMYFUNCTION("""COMPUTED_VALUE"""),"THIAGO ROMAGNOLE") -> THIAGO ROMAGNOLE | AT24: =IFERROR(__xludf.DUMMYFUNCTION("""COMPUTED_VALUE"""),"ANDERSON LAUREANO") -> ANDERSON LAUREANO | AU24: =IFERROR(__xludf.DUMMYFUNCTION("""COMPUTED_VALUE"""),0.0) -> 0 | AV24: =IFERROR(__xludf.DUMMYFUNCTION("""COMPUTED_VALUE"""),0.0) -> 0 | AW24: =IFERROR(__xludf.DUMMYFUNCTION("""COMPUTED_VALUE"""),0.0) -> 0 | AX24: =IFERROR(__xludf.DUMMYFUNCTION("""COMPUTED_VALUE"""),0.0) -> 0 | AZ24: =IFERROR(__xludf.DUMMYFUNCTION("""COMPUTED_VALUE"""),"Saudável") -> Saudável | BA24: =IFERROR(__xludf.DUMMYFUNCTION("""COMPUTED_VALUE"""),"") | BB24: =IFERROR(__xludf.DUMMYFUNCTION("""COMPUTED_VALUE"""),"") | BC24: =IFERROR(__xludf.DUMMYFUNCTION("""COMPUTED_VALUE"""),"") | BD24: =IFERROR(__xludf.DUMMYFUNCTION("""COMPUTED_VALUE"""),"") | BE24: =IFERROR(__xludf.DUMMYFUNCTION("""COMPUTED_VALUE"""),"") | BF24: =IFERROR(__xludf.DUMMYFUNCTION("""COMPUTED_VALUE"""),"") | BG24: =IFERROR(__xludf.DUMMYFUNCTION("""COMPUTED_VALUE"""),"") | BH24: Stone Co. | BI24: 1
A25: =IFERROR(__xludf.DUMMYFUNCTION("""COMPUTED_VALUE"""),"BERRYS - CONTA PAI") -> BERRYS - CONTA PAI | B25: =IFERROR(__xludf.DUMMYFUNCTION("""COMPUTED_VALUE"""),"João Biagiotti") -> João Biagiotti | C25: =IFERROR(__xludf.DUMMYFUNCTION("""COMPUTED_VALUE"""),"Diego Santos") -> Diego Santos | D25: =IFERROR(__xludf.DUMMYFUNCTION("""COMPUTED_VALUE"""),"2. Primeiro Contato com a marca") -> 2. Primeiro Contato com a marca | E25: =IFERROR(__xludf.DUMMYFUNCTION("""COMPUTED_VALUE"""),"Parceiro - Aguardando retorno parceiro") -> Parceiro - Aguardando retorno parceiro | F25: =IFERROR(__xludf.DUMMYFUNCTION("""COMPUTED_VALUE"""),"M") -> M | G25: =IFERROR(__xludf.DUMMYFUNCTION("""COMPUTED_VALUE"""),46135.0) -> 46135 | H25: =IFERROR(__xludf.DUMMYFUNCTION("""COMPUTED_VALUE"""),"Foi enviado mensagem para o Henrique, aguardando retorno") -> Foi enviado mensagem para o Henrique, aguardando retorno | I25: =IFERROR(__xludf.DUMMYFUNCTION("""COMPUTED_VALUE"""),46125.39505331019) -> 46125.395 | J25: =IFERROR(__xludf.DUMMYFUNCTION("""COMPUTED_VALUE"""),46125.4362820949) -> 46125.436 | AA25: =IFERROR(__xludf.DUMMYFUNCTION("""COMPUTED_VALUE"""),40.0) -> 40 | AB25: =IFERROR(__xludf.DUMMYFUNCTION("""COMPUTED_VALUE"""),"-") -> - | AC25: =IFERROR(__xludf.DUMMYFUNCTION("""COMPUTED_VALUE"""),"Sim") -> Sim | AD25: =IFERROR(__xludf.DUMMYFUNCTION("""COMPUTED_VALUE"""),"Unika Sistemas Ltda") -> Unika Sistemas Ltda | AM25: =IFERROR(__xludf.DUMMYFUNCTION("""COMPUTED_VALUE"""),"FY27") -> FY27 | AO25: =IFERROR(__xludf.DUMMYFUNCTION("""COMPUTED_VALUE"""),80.0) -> 80 | AP25: =IFERROR(__xludf.DUMMYFUNCTION("""COMPUTED_VALUE"""),"MG") -> MG | AQ25: =IFERROR(__xludf.DUMMYFUNCTION("""COMPUTED_VALUE"""),"CARLOS JESUS") -> CARLOS JESUS | AR25: =IFERROR(__xludf.DUMMYFUNCTION("""COMPUTED_VALUE"""),"RODRIGO BRITO") -> RODRIGO BRITO | AS25: =IFERROR(__xludf.DUMMYFUNCTION("""COMPUTED_VALUE"""),"FABIO DONATO") -> FABIO DONATO | AT25: =IFERROR(__xludf.DUMMYFUNCTION("""COMPUTED_VALUE"""),"GILSON JUNIOR") -> GILSON JUNIOR | AU25: =IFERROR(__xludf.DUMMYFUNCTION("""COMPUTED_VALUE"""),0.0) -> 0 | AV25: =IFERROR(__xludf.DUMMYFUNCTION("""COMPUTED_VALUE"""),0.0) -> 0 | AW25: =IFERROR(__xludf.DUMMYFUNCTION("""COMPUTED_VALUE"""),0.0) -> 0 | AX25: =IFERROR(__xludf.DUMMYFUNCTION("""COMPUTED_VALUE"""),0.0) -> 0 | AZ25: =IFERROR(__xludf.DUMMYFUNCTION("""COMPUTED_VALUE"""),"Sorvetes") -> Sorvetes | BA25: =IFERROR(__xludf.DUMMYFUNCTION("""COMPUTED_VALUE"""),"") | BB25: =IFERROR(__xludf.DUMMYFUNCTION("""COMPUTED_VALUE"""),"") | BC25: =IFERROR(__xludf.DUMMYFUNCTION("""COMPUTED_VALUE"""),"") | BD25: =IFERROR(__xludf.DUMMYFUNCTION("""COMPUTED_VALUE"""),"") | BE25: =IFERROR(__xludf.DUMMYFUNCTION("""COMPUTED_VALUE"""),"") | BF25: =IFERROR(__xludf.DUMMYFUNCTION("""COMPUTED_VALUE"""),"") | BG25: =IFERROR(__xludf.DUMMYFUNCTION("""COMPUTED_VALUE"""),"") | BH25: null | BI25: 0.73333333
A26: =IFERROR(__xludf.DUMMYFUNCTION("""COMPUTED_VALUE"""),"BEST - UBERLANDIA") -> BEST - UBERLANDIA | B26: =IFERROR(__xludf.DUMMYFUNCTION("""COMPUTED_VALUE"""),"João Biagiotti") -> João Biagiotti | C26: =IFERROR(__xludf.DUMMYFUNCTION("""COMPUTED_VALUE"""),"Diego Santos") -> Diego Santos | D26: =IFERROR(__xludf.DUMMYFUNCTION("""COMPUTED_VALUE"""),"9. Contrato assinado") -> 9. Contrato assinado | E26: =IFERROR(__xludf.DUMMYFUNCTION("""COMPUTED_VALUE"""),"Projetos - Em piloto") -> Projetos - Em piloto | F26: =IFERROR(__xludf.DUMMYFUNCTION("""COMPUTED_VALUE"""),"P") -> P | G26: =IFERROR(__xludf.DUMMYFUNCTION("""COMPUTED_VALUE"""),46160.0) -> 46160 | H26: =IFERROR(__xludf.DUMMYFUNCTION("""COMPUTED_VALUE"""),"iniciar fluxo com time de projetos") -> iniciar fluxo com time de projetos | I26: =IFERROR(__xludf.DUMMYFUNCTION("""COMPUTED_VALUE"""),46120.45318547454) -> 46120.453 | J26: =IFERROR(__xludf.DUMMYFUNCTION("""COMPUTED_VALUE"""),46127.64286841435) -> 46127.643 | K26: =IFERROR(__xludf.DUMMYFUNCTION("""COMPUTED_VALUE"""),46128.64338699074) -> 46128.643 | L26: =IFERROR(__xludf.DUMMYFUNCTION("""COMPUTED_VALUE"""),46140.6621059375) -> 46140.662 | M26: =IFERROR(__xludf.DUMMYFUNCTION("""COMPUTED_VALUE"""),46140.662663229166) -> 46140.663 | N26: =IFERROR(__xludf.DUMMYFUNCTION("""COMPUTED_VALUE"""),46155.397801875) -> 46155.398 | O26: =IFERROR(__xludf.DUMMYFUNCTION("""COMPUTED_VALUE"""),46160.62193255787) -> 46160.622 | P26: =IFERROR(__xludf.DUMMYFUNCTION("""COMPUTED_VALUE"""),46160.62347851852) -> 46160.623 | Q26: =IFERROR(__xludf.DUMMYFUNCTION("""COMPUTED_VALUE"""),46160.62356586805) -> 46160.624 | W26: =IFERROR(__xludf.DUMMYFUNCTION("""COMPUTED_VALUE"""),470.0) -> 470 | X26: =IFERROR(__xludf.DUMMYFUNCTION("""COMPUTED_VALUE"""),"1 ano") -> 1 ano | Y26: =IFERROR(__xludf.DUMMYFUNCTION("""COMPUTED_VALUE"""),0.0) -> 0 | Z26: =IFERROR(__xludf.DUMMYFUNCTION("""COMPUTED_VALUE"""),2500.0) -> 2500 | AA26: =IFERROR(__xludf.DUMMYFUNCTION("""COMPUTED_VALUE"""),5.0) -> 5 | AB26: =IFERROR(__xludf.DUMMYFUNCTION("""COMPUTED_VALUE"""),"CE") -> CE | AC26: =IFERROR(__xludf.DUMMYFUNCTION("""COMPUTED_VALUE"""),"Sim") -> Sim | AD26: =IFERROR(__xludf.DUMMYFUNCTION("""COMPUTED_VALUE"""),"Ifood") -> Ifood | AE26: =IFERROR(__xludf.DUMMYFUNCTION("""COMPUTED_VALUE"""),1.0) -> 1 | AF26: =IFERROR(__xludf.DUMMYFUNCTION("""COMPUTED_VALUE"""),6.0) -> 6 | AG26: =IFERROR(__xludf.DUMMYFUNCTION("""COMPUTED_VALUE"""),"30 dias") -> 30 dias | AH26: =IFERROR(__xludf.DUMMYFUNCTION("""COMPUTED_VALUE"""),12.0) -> 12 | AI26: =IFERROR(__xludf.DUMMYFUNCTION("""COMPUTED_VALUE"""),"200k") -> 200k | AJ26: =IFERROR(__xludf.DUMMYFUNCTION("""COMPUTED_VALUE"""),"não informado") -> não informado | AK26: =IFERROR(__xludf.DUMMYFUNCTION("""COMPUTED_VALUE"""),"pdv") -> pdv | AL26: =IFERROR(__xludf.DUMMYFUNCTION("""COMPUTED_VALUE"""),"SIM") -> SIM | AM26: =IFERROR(__xludf.DUMMYFUNCTION("""COMPUTED_VALUE"""),"FY27") -> FY27 | AO26: =IFERROR(__xludf.DUMMYFUNCTION("""COMPUTED_VALUE"""),55.0) -> 55 | AP26: =IFERROR(__xludf.DUMMYFUNCTION("""COMPUTED_VALUE"""),"MG") -> MG | AQ26: =IFERROR(__xludf.DUMMYFUNCTION("""COMPUTED_VALUE"""),"THIAGO FERREIRA") -> THIAGO FERREIRA | AR26: =IFERROR(__xludf.DUMMYFUNCTION("""COMPUTED_VALUE"""),"MONICA MORAIS") -> MONICA MORAIS | AS26: =IFERROR(__xludf.DUMMYFUNCTION("""COMPUTED_VALUE"""),"FABIO DONATO") -> FABIO DONATO | AT26: =IFERROR(__xludf.DUMMYFUNCTION("""COMPUTED_VALUE"""),"GILSON JUNIOR") -> GILSON JUNIOR | AU26: =IFERROR(__xludf.DUMMYFUNCTION("""COMPUTED_VALUE"""),0.0) -> 0 | AV26: =IFERROR(__xludf.DUMMYFUNCTION("""COMPUTED_VALUE"""),0.0) -> 0 | AW26: =IFERROR(__xludf.DUMMYFUNCTION("""COMPUTED_VALUE"""),0.0) -> 0 | AX26: =IFERROR(__xludf.DUMMYFUNCTION("""COMPUTED_VALUE"""),0.0) -> 0 | AZ26: =IFERROR(__xludf.DUMMYFUNCTION("""COMPUTED_VALUE"""),"Lanches") -> Lanches | BA26: =IFERROR(__xludf.DUMMYFUNCTION("""COMPUTED_VALUE"""),"") | BB26: =IFERROR(__xludf.DUMMYFUNCTION("""COMPUTED_VALUE"""),"") | BC26: =IFERROR(__xludf.DUMMYFUNCTION("""COMPUTED_VALUE"""),"") | BD26: =IFERROR(__xludf.DUMMYFUNCTION("""COMPUTED_VALUE"""),"") | BE26: =IFERROR(__xludf.DUMMYFUNCTION("""COMPUTED_VALUE"""),"") | BF26: =IFERROR(__xludf.DUMMYFUNCTION("""COMPUTED_VALUE"""),"") | BG26: =IFERROR(__xludf.DUMMYFUNCTION("""COMPUTED_VALUE"""),"") | BH26: null | BI26: 0.71428571
A27: =IFERROR(__xludf.DUMMYFUNCTION("""COMPUTED_VALUE"""),"BIBI RESTAURANTE") -> BIBI RESTAURANTE | B27: =IFERROR(__xludf.DUMMYFUNCTION("""COMPUTED_VALUE"""),"João Biagiotti") -> João Biagiotti | C27: =IFERROR(__xludf.DUMMYFUNCTION("""COMPUTED_VALUE"""),"Diego Santos") -> Diego Santos | D27: =IFERROR(__xludf.DUMMYFUNCTION("""COMPUTED_VALUE"""),"0. Não Iniciado") -> 0. Não Iniciado | F27: =IFERROR(__xludf.DUMMYFUNCTION("""COMPUTED_VALUE"""),"P") -> P | AA27: =IFERROR(__xludf.DUMMYFUNCTION("""COMPUTED_VALUE"""),5.0) -> 5 | AB27: =IFERROR(__xludf.DUMMYFUNCTION("""COMPUTED_VALUE"""),"CE") -> CE | AC27: =IFERROR(__xludf.DUMMYFUNCTION("""COMPUTED_VALUE"""),"Sim") -> Sim | AD27: =IFERROR(__xludf.DUMMYFUNCTION("""COMPUTED_VALUE"""),"Ifood") -> Ifood | AM27: =IFERROR(__xludf.DUMMYFUNCTION("""COMPUTED_VALUE"""),"FY27") -> FY27 | AO27: =IFERROR(__xludf.DUMMYFUNCTION("""COMPUTED_VALUE"""),45553.0) -> 45553 | AP27: =IFERROR(__xludf.DUMMYFUNCTION("""COMPUTED_VALUE"""),"SP") -> SP | AQ27: =IFERROR(__xludf.DUMMYFUNCTION("""COMPUTED_VALUE"""),"FABRYCIO MORI") -> FABRYCIO MORI | AR27: =IFERROR(__xludf.DUMMYFUNCTION("""COMPUTED_VALUE"""),"RODRIGO IGNACIO") -> RODRIGO IGNACIO | AS27: =IFERROR(__xludf.DUMMYFUNCTION("""COMPUTED_VALUE"""),"NATHALIE MERTENS") -> NATHALIE MERTENS | AT27: =IFERROR(__xludf.DUMMYFUNCTION("""COMPUTED_VALUE"""),"MATHEUS LESSA") -> MATHEUS LESSA | AU27: =IFERROR(__xludf.DUMMYFUNCTION("""COMPUTED_VALUE"""),0.0) -> 0 | AV27: =IFERROR(__xludf.DUMMYFUNCTION("""COMPUTED_VALUE"""),0.0) -> 0 | AW27: =IFERROR(__xludf.DUMMYFUNCTION("""COMPUTED_VALUE"""),0.0) -> 0 | AX27: =IFERROR(__xludf.DUMMYFUNCTION("""COMPUTED_VALUE"""),0.0) -> 0 | AY27: =IFERROR(__xludf.DUMMYFUNCTION("""COMPUTED_VALUE"""),"Anota Ai Solucoes Digitais S/a") -> Anota Ai Solucoes Digitais S/a | AZ27: =IFERROR(__xludf.DUMMYFUNCTION("""COMPUTED_VALUE"""),"Brasileira") -> Brasileira | BA27: =IFERROR(__xludf.DUMMYFUNCTION("""COMPUTED_VALUE"""),"") | BB27: =IFERROR(__xludf.DUMMYFUNCTION("""COMPUTED_VALUE"""),"") | BC27: =IFERROR(__xludf.DUMMYFUNCTION("""COMPUTED_VALUE"""),"") | BD27: =IFERROR(__xludf.DUMMYFUNCTION("""COMPUTED_VALUE"""),"") | BE27: =IFERROR(__xludf.DUMMYFUNCTION("""COMPUTED_VALUE"""),"") | BF27: =IFERROR(__xludf.DUMMYFUNCTION("""COMPUTED_VALUE"""),"") | BG27: =IFERROR(__xludf.DUMMYFUNCTION("""COMPUTED_VALUE"""),"") | BH27: Anota Ai Solucoes Digitais S/a | BI27: 1
A28: =IFERROR(__xludf.DUMMYFUNCTION("""COMPUTED_VALUE"""),"BISTROGONOFE") -> BISTROGONOFE | B28: =IFERROR(__xludf.DUMMYFUNCTION("""COMPUTED_VALUE"""),"Lídia Esteves") -> Lídia Esteves | C28: =IFERROR(__xludf.DUMMYFUNCTION("""COMPUTED_VALUE"""),"Gabriela Roma") -> Gabriela Roma | D28: =IFERROR(__xludf.DUMMYFUNCTION("""COMPUTED_VALUE"""),"0. Não Iniciado") -> 0. Não Iniciado | F28: =IFERROR(__xludf.DUMMYFUNCTION("""COMPUTED_VALUE"""),"P") -> P | AA28: =IFERROR(__xludf.DUMMYFUNCTION("""COMPUTED_VALUE"""),6.0) -> 6 | AB28: =IFERROR(__xludf.DUMMYFUNCTION("""COMPUTED_VALUE"""),"CE") -> CE | AC28: =IFERROR(__xludf.DUMMYFUNCTION("""COMPUTED_VALUE"""),"Sim") -> Sim | AD28: =IFERROR(__xludf.DUMMYFUNCTION("""COMPUTED_VALUE"""),"Ifood") -> Ifood | AM28: =IFERROR(__xludf.DUMMYFUNCTION("""COMPUTED_VALUE"""),"FY27") -> FY27 | AO28: =IFERROR(__xludf.DUMMYFUNCTION("""COMPUTED_VALUE"""),45553.0) -> 45553 | AP28: =IFERROR(__xludf.DUMMYFUNCTION("""COMPUTED_VALUE"""),"GO") -> GO | AQ28: =IFERROR(__xludf.DUMMYFUNCTION("""COMPUTED_VALUE"""),"RAFAEL ROSSATO") -> RAFAEL ROSSATO | AR28: =IFERROR(__xludf.DUMMYFUNCTION("""COMPUTED_VALUE"""),"NAYARA FERREIRA") -> NAYARA FERREIRA | AS28: =IFERROR(__xludf.DUMMYFUNCTION("""COMPUTED_VALUE"""),"THIAGO ROMAGNOLE") -> THIAGO ROMAGNOLE | AT28: =IFERROR(__xludf.DUMMYFUNCTION("""COMPUTED_VALUE"""),"BRUNA TASSINARI") -> BRUNA TASSINARI | AU28: =IFERROR(__xludf.DUMMYFUNCTION("""COMPUTED_VALUE"""),0.0) -> 0 | AV28: =IFERROR(__xludf.DUMMYFUNCTION("""COMPUTED_VALUE"""),0.0) -> 0 | AW28: =IFERROR(__xludf.DUMMYFUNCTION("""COMPUTED_VALUE"""),0.0) -> 0 | AX28: =IFERROR(__xludf.DUMMYFUNCTION("""COMPUTED_VALUE"""),0.0) -> 0 | AY28: =IFERROR(__xludf.DUMMYFUNCTION("""COMPUTED_VALUE"""),"Saipos Serviços De Software") -> Saipos Serviços De Software | AZ28: =IFERROR(__xludf.DUMMYFUNCTION("""COMPUTED_VALUE"""),"Brasileira") -> Brasileira | BA28: =IFERROR(__xludf.DUMMYFUNCTION("""COMPUTED_VALUE"""),"") | BB28: =IFERROR(__xludf.DUMMYFUNCTION("""COMPUTED_VALUE"""),"") | BC28: =IFERROR(__xludf.DUMMYFUNCTION("""COMPUTED_VALUE"""),"") | BD28: =IFERROR(__xludf.DUMMYFUNCTION("""COMPUTED_VALUE"""),"") | BE28: =IFERROR(__xludf.DUMMYFUNCTION("""COMPUTED_VALUE"""),"") | BF28: =IFERROR(__xludf.DUMMYFUNCTION("""COMPUTED_VALUE"""),"") | BG28: =IFERROR(__xludf.DUMMYFUNCTION("""COMPUTED_VALUE"""),"") | BH28: null | BI28: 1
A29: =IFERROR(__xludf.DUMMYFUNCTION("""COMPUTED_VALUE"""),"BKO - CONTA MARCA") -> BKO - CONTA MARCA | B29: =IFERROR(__xludf.DUMMYFUNCTION("""COMPUTED_VALUE"""),"Lídia Esteves") -> Lídia Esteves | C29: =IFERROR(__xludf.DUMMYFUNCTION("""COMPUTED_VALUE"""),"Gabriela Roma") -> Gabriela Roma | D29: =IFERROR(__xludf.DUMMYFUNCTION("""COMPUTED_VALUE"""),"0. Não Iniciado") -> 0. Não Iniciado | F29: =IFERROR(__xludf.DUMMYFUNCTION("""COMPUTED_VALUE"""),"P") -> P | AA29: =IFERROR(__xludf.DUMMYFUNCTION("""COMPUTED_VALUE"""),25.0) -> 25 | AB29: =IFERROR(__xludf.DUMMYFUNCTION("""COMPUTED_VALUE"""),"-") -> - | AC29: =IFERROR(__xludf.DUMMYFUNCTION("""COMPUTED_VALUE"""),"Sim") -> Sim | AD29: =IFERROR(__xludf.DUMMYFUNCTION("""COMPUTED_VALUE"""),"Ifood") -> Ifood | AM29: =IFERROR(__xludf.DUMMYFUNCTION("""COMPUTED_VALUE"""),"FY27") -> FY27 | AO29: =IFERROR(__xludf.DUMMYFUNCTION("""COMPUTED_VALUE"""),45553.0) -> 45553 | AP29: =IFERROR(__xludf.DUMMYFUNCTION("""COMPUTED_VALUE"""),"RS") -> RS | AQ29: =IFERROR(__xludf.DUMMYFUNCTION("""COMPUTED_VALUE"""),"SHAYANA JACOM") -> SHAYANA JACOM | AR29: =IFERROR(__xludf.DUMMYFUNCTION("""COMPUTED_VALUE"""),"GABRIEL RUAS") -> GABRIEL RUAS | AS29: =IFERROR(__xludf.DUMMYFUNCTION("""COMPUTED_VALUE"""),"FABIO DONATO") -> FABIO DONATO | AT29: =IFERROR(__xludf.DUMMYFUNCTION("""COMPUTED_VALUE"""),"CAMILA HOLANDA") -> CAMILA HOLANDA | AU29: =IFERROR(__xludf.DUMMYFUNCTION("""COMPUTED_VALUE"""),0.0) -> 0 | AV29: =IFERROR(__xludf.DUMMYFUNCTION("""COMPUTED_VALUE"""),0.0) -> 0 | AW29: =IFERROR(__xludf.DUMMYFUNCTION("""COMPUTED_VALUE"""),0.0) -> 0 | AX29: =IFERROR(__xludf.DUMMYFUNCTION("""COMPUTED_VALUE"""),0.0) -> 0 | AZ29: =IFERROR(__xludf.DUMMYFUNCTION("""COMPUTED_VALUE"""),"Japonesa") -> Japonesa | BA29: =IFERROR(__xludf.DUMMYFUNCTION("""COMPUTED_VALUE"""),40.0) -> 40 | BB29: =IFERROR(__xludf.DUMMYFUNCTION("""COMPUTED_VALUE"""),"QSR - Fast Food") -> QSR - Fast Food | BC29: =IFERROR(__xludf.DUMMYFUNCTION("""COMPUTED_VALUE"""),"Regional/Nacional") -> Regional/Nacional | BE29: =IFERROR(__xludf.DUMMYFUNCTION("""COMPUTED_VALUE"""),70.0) -> 70 | BF29: =IFERROR(__xludf.DUMMYFUNCTION("""COMPUTED_VALUE"""),0.9) -> 0.9 | BG29: =IFERROR(__xludf.DUMMYFUNCTION("""COMPUTED_VALUE"""),"Alta aderência ao 3S: PDV atual não identificado. 3S oferece Kiosk nativo, Hub Delivery integrado e gestão centralizada multi-loja - diferenciais competitivos para expansão e redução de filas.") -> Alta aderência ao 3S: PDV atual não identificado. 3S oferece Kiosk nativo, Hub Delivery integrado e gestão centralizada multi-loja - diferenciais competitivos para expansão e redução de filas. | BH29: Saipos Serviços De Software | BI29: 0.95833333
A30: =IFERROR(__xludf.DUMMYFUNCTION("""COMPUTED_VALUE"""),"BOCA DO FORNO") -> BOCA DO FORNO | B30: =IFERROR(__xludf.DUMMYFUNCTION("""COMPUTED_VALUE"""),"João Biagiotti") -> João Biagiotti | C30: =IFERROR(__xludf.DUMMYFUNCTION("""COMPUTED_VALUE"""),"Diego Santos") -> Diego Santos | D30: =IFERROR(__xludf.DUMMYFUNCTION("""COMPUTED_VALUE"""),"10. Perdido") -> 10. Perdido | E30: =IFERROR(__xludf.DUMMYFUNCTION("""COMPUTED_VALUE"""),"Perdido - Outro (detalhar ao lado)") -> Perdido - Outro (detalhar ao lado) | F30: =IFERROR(__xludf.DUMMYFUNCTION("""COMPUTED_VALUE"""),"P") -> P | G30: =IFERROR(__xludf.DUMMYFUNCTION("""COMPUTED_VALUE"""),46125.0) -> 46125 | H30: =IFERROR(__xludf.DUMMYFUNCTION("""COMPUTED_VALUE"""),"Em conversa com o coordenador de delivery, fui informado que eles possuem teknisa, já foi ofertado Saipos, no entanto a marca nao tem interesse em mudança de PDV") -> Em conversa com o coordenador de delivery, fui informado que eles possuem teknisa, já foi ofertado Saipos, no entanto a marca nao tem interesse em mudança de PDV | I30: =IFERROR(__xludf.DUMMYFUNCTION("""COMPUTED_VALUE"""),46125.58499047454) -> 46125.585 | AA30: =IFERROR(__xludf.DUMMYFUNCTION("""COMPUTED_VALUE"""),16.0) -> 16 | AB30: =IFERROR(__xludf.DUMMYFUNCTION("""COMPUTED_VALUE"""),"-") -> - | AC30: =IFERROR(__xludf.DUMMYFUNCTION("""COMPUTED_VALUE"""),"Sim") -> Sim | AD30: =IFERROR(__xludf.DUMMYFUNCTION("""COMPUTED_VALUE"""),"Ifood") -> Ifood | AJ30: =IFERROR(__xludf.DUMMYFUNCTION("""COMPUTED_VALUE"""),"Teknisa") -> Teknisa | AK30: =IFERROR(__xludf.DUMMYFUNCTION("""COMPUTED_VALUE"""),"Salão / Delivery") -> Salão / Delivery | AL30: =IFERROR(__xludf.DUMMYFUNCTION("""COMPUTED_VALUE"""),"Não") -> Não | AM30: =IFERROR(__xludf.DUMMYFUNCTION("""COMPUTED_VALUE"""),"FY27") -> FY27 | AO30: =IFERROR(__xludf.DUMMYFUNCTION("""COMPUTED_VALUE"""),90.0) -> 90 | AP30: =IFERROR(__xludf.DUMMYFUNCTION("""COMPUTED_VALUE"""),"MG") -> MG | AQ30: =IFERROR(__xludf.DUMMYFUNCTION("""COMPUTED_VALUE"""),"JOAO BAR") -> JOAO BAR | AR30: =IFERROR(__xludf.DUMMYFUNCTION("""COMPUTED_VALUE"""),"LEONARDO NEVES") -> LEONARDO NEVES | AS30: =IFERROR(__xludf.DUMMYFUNCTION("""COMPUTED_VALUE"""),"FABIO DONATO") -> FABIO DONATO | AT30: =IFERROR(__xludf.DUMMYFUNCTION("""COMPUTED_VALUE"""),"GILSON JUNIOR") -> GILSON JUNIOR | AU30: =IFERROR(__xludf.DUMMYFUNCTION("""COMPUTED_VALUE"""),0.0) -> 0 | AV30: =IFERROR(__xludf.DUMMYFUNCTION("""COMPUTED_VALUE"""),0.0) -> 0 | AW30: =IFERROR(__xludf.DUMMYFUNCTION("""COMPUTED_VALUE"""),0.0) -> 0 | AX30: =IFERROR(__xludf.DUMMYFUNCTION("""COMPUTED_VALUE"""),0.0) -> 0 | AZ30: =IFERROR(__xludf.DUMMYFUNCTION("""COMPUTED_VALUE"""),"Lanches") -> Lanches | BA30: =IFERROR(__xludf.DUMMYFUNCTION("""COMPUTED_VALUE"""),"") | BB30: =IFERROR(__xludf.DUMMYFUNCTION("""COMPUTED_VALUE"""),"") | BC30: =IFERROR(__xludf.DUMMYFUNCTION("""COMPUTED_VALUE"""),"") | BD30: =IFERROR(__xludf.DUMMYFUNCTION("""COMPUTED_VALUE"""),"") | BE30: =IFERROR(__xludf.DUMMYFUNCTION("""COMPUTED_VALUE"""),"") | BF30: =IFERROR(__xludf.DUMMYFUNCTION("""COMPUTED_VALUE"""),"") | BG30: =IFERROR(__xludf.DUMMYFUNCTION("""COMPUTED_VALUE"""),"")
A31: =IFERROR(__xludf.DUMMYFUNCTION("""COMPUTED_VALUE"""),"BODE DO NÓ") -> BODE DO NÓ | B31: =IFERROR(__xludf.DUMMYFUNCTION("""COMPUTED_VALUE"""),"João Biagiotti") -> João Biagiotti | C31: =IFERROR(__xludf.DUMMYFUNCTION("""COMPUTED_VALUE"""),"Diego Santos") -> Diego Santos | D31: =IFERROR(__xludf.DUMMYFUNCTION("""COMPUTED_VALUE"""),"10. Perdido") -> 10. Perdido | E31: =IFERROR(__xludf.DUMMYFUNCTION("""COMPUTED_VALUE"""),"Perdido - Outro (detalhar ao lado)") -> Perdido - Outro (detalhar ao lado) | F31: =IFERROR(__xludf.DUMMYFUNCTION("""COMPUTED_VALUE"""),"P") -> P | G31: =IFERROR(__xludf.DUMMYFUNCTION("""COMPUTED_VALUE"""),46119.0) -> 46119 | H31: =IFERROR(__xludf.DUMMYFUNCTION("""COMPUTED_VALUE"""),"Ja tentaram apresentar SAIPOS e o iFood salão, porem o parceiro informou que não ira mudar a integradora dele") -> Ja tentaram apresentar SAIPOS e o iFood salão, porem o parceiro informou que não ira mudar a integradora dele | I31: =IFERROR(__xludf.DUMMYFUNCTION("""COMPUTED_VALUE"""),46120.5978058912) -> 46120.598 | R31: =IFERROR(__xludf.DUMMYFUNCTION("""COMPUTED_VALUE"""),46129.503317361115) -> 46129.503 | V31: =IFERROR(__xludf.DUMMYFUNCTION("""COMPUTED_VALUE"""),"Sem interesse em mudar de PDV") -> Sem interesse em mudar de PDV | AA31: =IFERROR(__xludf.DUMMYFUNCTION("""COMPUTED_VALUE"""),8.0) -> 8 | AB31: =IFERROR(__xludf.DUMMYFUNCTION("""COMPUTED_VALUE"""),"CE") -> CE | AC31: =IFERROR(__xludf.DUMMYFUNCTION("""COMPUTED_VALUE"""),"Sim") -> Sim | AD31: =IFERROR(__xludf.DUMMYFUNCTION("""COMPUTED_VALUE"""),0.0) -> 0 | AM31: =IFERROR(__xludf.DUMMYFUNCTION("""COMPUTED_VALUE"""),"FY27") -> FY27 | AO31: =IFERROR(__xludf.DUMMYFUNCTION("""COMPUTED_VALUE"""),96.0) -> 96 | AP31: =IFERROR(__xludf.DUMMYFUNCTION("""COMPUTED_VALUE"""),"PE") -> PE | AQ31: =IFERROR(__xludf.DUMMYFUNCTION("""COMPUTED_VALUE"""),"JENNIFER SIQUEIRA") -> JENNIFER SIQUEIRA | AR31: =IFERROR(__xludf.DUMMYFUNCTION("""COMPUTED_VALUE"""),0.0) -> 0 | AS31: =IFERROR(__xludf.DUMMYFUNCTION("""COMPUTED_VALUE"""),0.0) -> 0 | AT31: =IFERROR(__xludf.DUMMYFUNCTION("""COMPUTED_VALUE"""),0.0) -> 0 | AU31: =IFERROR(__xludf.DUMMYFUNCTION("""COMPUTED_VALUE"""),0.0) -> 0 | AV31: =IFERROR(__xludf.DUMMYFUNCTION("""COMPUTED_VALUE"""),0.0) -> 0 | AW31: =IFERROR(__xludf.DUMMYFUNCTION("""COMPUTED_VALUE"""),0.0) -> 0 | AX31: =IFERROR(__xludf.DUMMYFUNCTION("""COMPUTED_VALUE"""),0.0) -> 0 | AZ31: =IFERROR(__xludf.DUMMYFUNCTION("""COMPUTED_VALUE"""),"Lanches") -> Lanches | BA31: =IFERROR(__xludf.DUMMYFUNCTION("""COMPUTED_VALUE"""),"") | BB31: =IFERROR(__xludf.DUMMYFUNCTION("""COMPUTED_VALUE"""),"") | BC31: =IFERROR(__xludf.DUMMYFUNCTION("""COMPUTED_VALUE"""),"") | BD31: =IFERROR(__xludf.DUMMYFUNCTION("""COMPUTED_VALUE"""),"") | BE31: =IFERROR(__xludf.DUMMYFUNCTION("""COMPUTED_VALUE"""),"") | BF31: =IFERROR(__xludf.DUMMYFUNCTION("""COMPUTED_VALUE"""),"") | BG31: =IFERROR(__xludf.DUMMYFUNCTION("""COMPUTED_VALUE"""),"")
A32: =IFERROR(__xludf.DUMMYFUNCTION("""COMPUTED_VALUE"""),"BOLOS DO SITIO") -> BOLOS DO SITIO | B32: =IFERROR(__xludf.DUMMYFUNCTION("""COMPUTED_VALUE"""),"Emerson") -> Emerson | C32: =IFERROR(__xludf.DUMMYFUNCTION("""COMPUTED_VALUE"""),"Emerson") -> Emerson | D32: =IFERROR(__xludf.DUMMYFUNCTION("""COMPUTED_VALUE"""),"0. Não Iniciado") -> 0. Não Iniciado | F32: =IFERROR(__xludf.DUMMYFUNCTION("""COMPUTED_VALUE"""),"M") -> M | AA32: =IFERROR(__xludf.DUMMYFUNCTION("""COMPUTED_VALUE"""),42.0) -> 42 | AB32: =IFERROR(__xludf.DUMMYFUNCTION("""COMPUTED_VALUE"""),"-") -> - | AC32: =IFERROR(__xludf.DUMMYFUNCTION("""COMPUTED_VALUE"""),"Sim") -> Sim | AD32: =IFERROR(__xludf.DUMMYFUNCTION("""COMPUTED_VALUE"""),"Ifood") -> Ifood | AM32: =IFERROR(__xludf.DUMMYFUNCTION("""COMPUTED_VALUE"""),"FY27") -> FY27 | AO32: =IFERROR(__xludf.DUMMYFUNCTION("""COMPUTED_VALUE"""),45553.0) -> 45553 | AP32: =IFERROR(__xludf.DUMMYFUNCTION("""COMPUTED_VALUE"""),"GO") -> GO | AQ32: =IFERROR(__xludf.DUMMYFUNCTION("""COMPUTED_VALUE"""),"RAFAEL ROSSATO") -> RAFAEL ROSSATO | AR32: =IFERROR(__xludf.DUMMYFUNCTION("""COMPUTED_VALUE"""),"GUILHERME CHAVEIRO") -> GUILHERME CHAVEIRO | AS32: =IFERROR(__xludf.DUMMYFUNCTION("""COMPUTED_VALUE"""),"THIAGO ROMAGNOLE") -> THIAGO ROMAGNOLE | AT32: =IFERROR(__xludf.DUMMYFUNCTION("""COMPUTED_VALUE"""),"BRUNA TASSINARI") -> BRUNA TASSINARI | AU32: =IFERROR(__xludf.DUMMYFUNCTION("""COMPUTED_VALUE"""),0.0) -> 0 | AV32: =IFERROR(__xludf.DUMMYFUNCTION("""COMPUTED_VALUE"""),0.0) -> 0 | AW32: =IFERROR(__xludf.DUMMYFUNCTION("""COMPUTED_VALUE"""),0.0) -> 0 | AX32: =IFERROR(__xludf.DUMMYFUNCTION("""COMPUTED_VALUE"""),0.0) -> 0 | AZ32: =IFERROR(__xludf.DUMMYFUNCTION("""COMPUTED_VALUE"""),"Doces & Bolos") -> Doces & Bolos | BA32: =IFERROR(__xludf.DUMMYFUNCTION("""COMPUTED_VALUE"""),"") | BB32: =IFERROR(__xludf.DUMMYFUNCTION("""COMPUTED_VALUE"""),"") | BC32: =IFERROR(__xludf.DUMMYFUNCTION("""COMPUTED_VALUE"""),"") | BD32: =IFERROR(__xludf.DUMMYFUNCTION("""COMPUTED_VALUE"""),"") | BE32: =IFERROR(__xludf.DUMMYFUNCTION("""COMPUTED_VALUE"""),"") | BF32: =IFERROR(__xludf.DUMMYFUNCTION("""COMPUTED_VALUE"""),"") | BG32: =IFERROR(__xludf.DUMMYFUNCTION("""COMPUTED_VALUE"""),"")
A33: =IFERROR(__xludf.DUMMYFUNCTION("""COMPUTED_VALUE"""),"BOLOS ROSA") -> BOLOS ROSA | B33: =IFERROR(__xludf.DUMMYFUNCTION("""COMPUTED_VALUE"""),"João Biagiotti") -> João Biagiotti | C33: =IFERROR(__xludf.DUMMYFUNCTION("""COMPUTED_VALUE"""),"Diego Santos") -> Diego Santos | D33: =IFERROR(__xludf.DUMMYFUNCTION("""COMPUTED_VALUE"""),"0. Não Iniciado") -> 0. Não Iniciado | F33: =IFERROR(__xludf.DUMMYFUNCTION("""COMPUTED_VALUE"""),"P") -> P | AA33: =IFERROR(__xludf.DUMMYFUNCTION("""COMPUTED_VALUE"""),5.0) -> 5 | AB33: =IFERROR(__xludf.DUMMYFUNCTION("""COMPUTED_VALUE"""),"CE") -> CE | AC33: =IFERROR(__xludf.DUMMYFUNCTION("""COMPUTED_VALUE"""),"Sim") -> Sim | AD33: =IFERROR(__xludf.DUMMYFUNCTION("""COMPUTED_VALUE"""),"Cardápio Web") -> Cardápio Web | AM33: =IFERROR(__xludf.DUMMYFUNCTION("""COMPUTED_VALUE"""),"FY27") -> FY27 | AO33: =IFERROR(__xludf.DUMMYFUNCTION("""COMPUTED_VALUE"""),45553.0) -> 45553 | AP33: =IFERROR(__xludf.DUMMYFUNCTION("""COMPUTED_VALUE"""),"SP") -> SP | AQ33: =IFERROR(__xludf.DUMMYFUNCTION("""COMPUTED_VALUE"""),"RODRIGO ALBANESE") -> RODRIGO ALBANESE | AR33: =IFERROR(__xludf.DUMMYFUNCTION("""COMPUTED_VALUE"""),"BEATRIZ CERVONE") -> BEATRIZ CERVONE | AS33: =IFERROR(__xludf.DUMMYFUNCTION("""COMPUTED_VALUE"""),"NATHALIE MERTENS") -> NATHALIE MERTENS | AT33: =IFERROR(__xludf.DUMMYFUNCTION("""COMPUTED_VALUE"""),"MATHEUS LESSA") -> MATHEUS LESSA | AU33: =IFERROR(__xludf.DUMMYFUNCTION("""COMPUTED_VALUE"""),0.0) -> 0 | AV33: =IFERROR(__xludf.DUMMYFUNCTION("""COMPUTED_VALUE"""),0.0) -> 0 | AW33: =IFERROR(__xludf.DUMMYFUNCTION("""COMPUTED_VALUE"""),0.0) -> 0 | AX33: =IFERROR(__xludf.DUMMYFUNCTION("""COMPUTED_VALUE"""),0.0) -> 0 | AZ33: =IFERROR(__xludf.DUMMYFUNCTION("""COMPUTED_VALUE"""),"Doces & Bolos") -> Doces & Bolos | BA33: =IFERROR(__xludf.DUMMYFUNCTION("""COMPUTED_VALUE"""),50.0) -> 50 | BB33: =IFERROR(__xludf.DUMMYFUNCTION("""COMPUTED_VALUE"""),"Varejo - Confeitaria") -> Varejo - Confeitaria | BC33: =IFERROR(__xludf.DUMMYFUNCTION("""COMPUTED_VALUE"""),"Regional") -> Regional | BE33: =IFERROR(__xludf.DUMMYFUNCTION("""COMPUTED_VALUE"""),40.0) -> 40 | BF33: =IFERROR(__xludf.DUMMYFUNCTION("""COMPUTED_VALUE"""),0.5) -> 0.5 | BG33: =IFERROR(__xludf.DUMMYFUNCTION("""COMPUTED_VALUE"""),"Aderência moderada ao 3S: PDV atual não identificado. 3S pode agregar valor com padronização multi-loja e integração delivery, mas necessário Discovery para validar fit completo.") -> Aderência moderada ao 3S: PDV atual não identificado. 3S pode agregar valor com padronização multi-loja e integração delivery, mas necessário Discovery para validar fit completo. | BH33: Cardápio Web | BI33: 1
A34: =IFERROR(__xludf.DUMMYFUNCTION("""COMPUTED_VALUE"""),"BORDA E LENHA") -> BORDA E LENHA | B34: =IFERROR(__xludf.DUMMYFUNCTION("""COMPUTED_VALUE"""),"Lídia Esteves") -> Lídia Esteves | C34: =IFERROR(__xludf.DUMMYFUNCTION("""COMPUTED_VALUE"""),"Gabriela Roma") -> Gabriela Roma | D34: =IFERROR(__xludf.DUMMYFUNCTION("""COMPUTED_VALUE"""),"1. Iniciado") -> 1. Iniciado | E34: =IFERROR(__xludf.DUMMYFUNCTION("""COMPUTED_VALUE"""),"Delivery - Aguardando retorno / Conciliação agenda") -> Delivery - Aguardando retorno / Conciliação agenda | F34: =IFERROR(__xludf.DUMMYFUNCTION("""COMPUTED_VALUE"""),"P") -> P | I34: =IFERROR(__xludf.DUMMYFUNCTION("""COMPUTED_VALUE"""),46121.673242372686) -> 46121.673 | AA34: =IFERROR(__xludf.DUMMYFUNCTION("""COMPUTED_VALUE"""),16.0) -> 16 | AB34: =IFERROR(__xludf.DUMMYFUNCTION("""COMPUTED_VALUE"""),"-") -> - | AC34: =IFERROR(__xludf.DUMMYFUNCTION("""COMPUTED_VALUE"""),"Sim") -> Sim | AD34: =IFERROR(__xludf.DUMMYFUNCTION("""COMPUTED_VALUE"""),"Ifood") -> Ifood | AM34: =IFERROR(__xludf.DUMMYFUNCTION("""COMPUTED_VALUE"""),"FY27") -> FY27 | AO34: =IFERROR(__xludf.DUMMYFUNCTION("""COMPUTED_VALUE"""),45553.0) -> 45553 | AP34: =IFERROR(__xludf.DUMMYFUNCTION("""COMPUTED_VALUE"""),"RJ") -> RJ | AQ34: =IFERROR(__xludf.DUMMYFUNCTION("""COMPUTED_VALUE"""),"BRUNO MEIRA") -> BRUNO MEIRA | AR34: =IFERROR(__xludf.DUMMYFUNCTION("""COMPUTED_VALUE"""),"RAFAEL CESAR") -> RAFAEL CESAR | AS34: =IFERROR(__xludf.DUMMYFUNCTION("""COMPUTED_VALUE"""),"NATHALIE MERTENS") -> NATHALIE MERTENS | AT34: =IFERROR(__xludf.DUMMYFUNCTION("""COMPUTED_VALUE"""),"NATALIA COUTINHO") -> NATALIA COUTINHO | AU34: =IFERROR(__xludf.DUMMYFUNCTION("""COMPUTED_VALUE"""),0.0) -> 0 | AV34: =IFERROR(__xludf.DUMMYFUNCTION("""COMPUTED_VALUE"""),0.0) -> 0 | AW34: =IFERROR(__xludf.DUMMYFUNCTION("""COMPUTED_VALUE"""),0.0) -> 0 | AX34: =IFERROR(__xludf.DUMMYFUNCTION("""COMPUTED_VALUE"""),0.0) -> 0 | AZ34: =IFERROR(__xludf.DUMMYFUNCTION("""COMPUTED_VALUE"""),"Pizza") -> Pizza | BA34: =IFERROR(__xludf.DUMMYFUNCTION("""COMPUTED_VALUE"""),75.0) -> 75 | BB34: =IFERROR(__xludf.DUMMYFUNCTION("""COMPUTED_VALUE"""),"Fast Casual - Pizzaria Forno Lenha") -> Fast Casual - Pizzaria Forno Lenha | BC34: =IFERROR(__xludf.DUMMYFUNCTION("""COMPUTED_VALUE"""),"Regional") -> Regional | BE34: =IFERROR(__xludf.DUMMYFUNCTION("""COMPUTED_VALUE"""),65.0) -> 65 | BF34: =IFERROR(__xludf.DUMMYFUNCTION("""COMPUTED_VALUE"""),0.75) -> 0.75 | BG34: =IFERROR(__xludf.DUMMYFUNCTION("""COMPUTED_VALUE"""),"Aderência forte ao 3S: PDV atual não identificado. 3S oferece PDV robusto, KDS integrado e mobilidade (3SGO) para gestão em tempo real - ideal para operações multi-canal.") -> Aderência forte ao 3S: PDV atual não identificado. 3S oferece PDV robusto, KDS integrado e mobilidade (3SGO) para gestão em tempo real - ideal para operações multi-canal. | BH34: Saipos Serviços De Software | BI34: 0.875
A35: =IFERROR(__xludf.DUMMYFUNCTION("""COMPUTED_VALUE"""),"BOTECO COLARINHO") -> BOTECO COLARINHO | B35: =IFERROR(__xludf.DUMMYFUNCTION("""COMPUTED_VALUE"""),"Lídia Esteves") -> Lídia Esteves | C35: =IFERROR(__xludf.DUMMYFUNCTION("""COMPUTED_VALUE"""),"Gabriela Roma") -> Gabriela Roma | D35: =IFERROR(__xludf.DUMMYFUNCTION("""COMPUTED_VALUE"""),"1. Iniciado") -> 1. Iniciado | E35: =IFERROR(__xludf.DUMMYFUNCTION("""COMPUTED_VALUE"""),"Delivery - Aguardando retorno / Conciliação agenda") -> Delivery - Aguardando retorno / Conciliação agenda | F35: =IFERROR(__xludf.DUMMYFUNCTION("""COMPUTED_VALUE"""),"P") -> P | I35: =IFERROR(__xludf.DUMMYFUNCTION("""COMPUTED_VALUE"""),46121.67330630787) -> 46121.673 | AA35: =IFERROR(__xludf.DUMMYFUNCTION("""COMPUTED_VALUE"""),6.0) -> 6 | AB35: =IFERROR(__xludf.DUMMYFUNCTION("""COMPUTED_VALUE"""),"CE") -> CE | AC35: =IFERROR(__xludf.DUMMYFUNCTION("""COMPUTED_VALUE"""),"Sim") -> Sim | AD35: =IFERROR(__xludf.DUMMYFUNCTION("""COMPUTED_VALUE"""),"Ifood") -> Ifood | AM35: =IFERROR(__xludf.DUMMYFUNCTION("""COMPUTED_VALUE"""),"FY27") -> FY27 | AO35: =IFERROR(__xludf.DUMMYFUNCTION("""COMPUTED_VALUE"""),45553.0) -> 45553 | AP35: =IFERROR(__xludf.DUMMYFUNCTION("""COMPUTED_VALUE"""),"RJ") -> RJ | AQ35: =IFERROR(__xludf.DUMMYFUNCTION("""COMPUTED_VALUE"""),"BRUNO MEIRA") -> BRUNO MEIRA | AR35: =IFERROR(__xludf.DUMMYFUNCTION("""COMPUTED_VALUE"""),"DANIEL PELAEZ") -> DANIEL PELAEZ | AS35: =IFERROR(__xludf.DUMMYFUNCTION("""COMPUTED_VALUE"""),"NATHALIE MERTENS") -> NATHALIE MERTENS | AT35: =IFERROR(__xludf.DUMMYFUNCTION("""COMPUTED_VALUE"""),"NATALIA COUTINHO") -> NATALIA COUTINHO | AU35: =IFERROR(__xludf.DUMMYFUNCTION("""COMPUTED_VALUE"""),0.0) -> 0 | AV35: =IFERROR(__xludf.DUMMYFUNCTION("""COMPUTED_VALUE"""),0.0) -> 0 | AW35: =IFERROR(__xludf.DUMMYFUNCTION("""COMPUTED_VALUE"""),0.0) -> 0 | AX35: =IFERROR(__xludf.DUMMYFUNCTION("""COMPUTED_VALUE"""),0.0) -> 0 | AZ35: =IFERROR(__xludf.DUMMYFUNCTION("""COMPUTED_VALUE"""),"Frangos") -> Frangos | BA35: =IFERROR(__xludf.DUMMYFUNCTION("""COMPUTED_VALUE"""),70.0) -> 70 | BB35: =IFERROR(__xludf.DUMMYFUNCTION("""COMPUTED_VALUE"""),"Table Service - Boteco") -> Table Service - Boteco | BC35: =IFERROR(__xludf.DUMMYFUNCTION("""COMPUTED_VALUE"""),"Regional") -> Regional | BE35: =IFERROR(__xludf.DUMMYFUNCTION("""COMPUTED_VALUE"""),55.0) -> 55 | BF35: =IFERROR(__xludf.DUMMYFUNCTION("""COMPUTED_VALUE"""),0.65) -> 0.65 | BG35: =IFERROR(__xludf.DUMMYFUNCTION("""COMPUTED_VALUE"""),"Aderência forte ao 3S: PDV atual não identificado. 3S oferece PDV robusto, KDS integrado e mobilidade (3SGO) para gestão em tempo real - ideal para operações multi-canal.") -> Aderência forte ao 3S: PDV atual não identificado. 3S oferece PDV robusto, KDS integrado e mobilidade (3SGO) para gestão em tempo real - ideal para operações multi-canal.
A36: =IFERROR(__xludf.DUMMYFUNCTION("""COMPUTED_VALUE"""),"BOTECO CONFRARIA") -> BOTECO CONFRARIA | B36: =IFERROR(__xludf.DUMMYFUNCTION("""COMPUTED_VALUE"""),"Lídia Esteves") -> Lídia Esteves | C36: =IFERROR(__xludf.DUMMYFUNCTION("""COMPUTED_VALUE"""),"Gabriela Roma") -> Gabriela Roma | D36: =IFERROR(__xludf.DUMMYFUNCTION("""COMPUTED_VALUE"""),"6. Negociação") -> 6. Negociação | E36: =IFERROR(__xludf.DUMMYFUNCTION("""COMPUTED_VALUE"""),"Parceiro - Aguardando retorno parceiro") -> Parceiro - Aguardando retorno parceiro | F36: =IFERROR(__xludf.DUMMYFUNCTION("""COMPUTED_VALUE"""),"P") -> P | G36: =IFERROR(__xludf.DUMMYFUNCTION("""COMPUTED_VALUE"""),46154.0) -> 46154 | H36: =IFERROR(__xludf.DUMMYFUNCTION("""COMPUTED_VALUE"""),"demo agendada 15/5") -> demo agendada 15/5 | I36: =IFERROR(__xludf.DUMMYFUNCTION("""COMPUTED_VALUE"""),46139.69141547453) -> 46139.691 | J36: =IFERROR(__xludf.DUMMYFUNCTION("""COMPUTED_VALUE"""),46139.69151267361) -> 46139.692 | K36: =IFERROR(__xludf.DUMMYFUNCTION("""COMPUTED_VALUE"""),46140.40487471065) -> 46140.405 | L36: =IFERROR(__xludf.DUMMYFUNCTION("""COMPUTED_VALUE"""),46153.67977137731) -> 46153.68 | M36: =IFERROR(__xludf.DUMMYFUNCTION("""COMPUTED_VALUE"""),46153.68049569444) -> 46153.681 | N36: =IFERROR(__xludf.DUMMYFUNCTION("""COMPUTED_VALUE"""),46161.40003415509) -> 46161.4 | AA36: =IFERROR(__xludf.DUMMYFUNCTION("""COMPUTED_VALUE"""),6.0) -> 6 | AB36: =IFERROR(__xludf.DUMMYFUNCTION("""COMPUTED_VALUE"""),"CE") -> CE | AC36: =IFERROR(__xludf.DUMMYFUNCTION("""COMPUTED_VALUE"""),"Sim") -> Sim | AD36: =IFERROR(__xludf.DUMMYFUNCTION("""COMPUTED_VALUE"""),"Ifood") -> Ifood | AH36: =IFERROR(__xludf.DUMMYFUNCTION("""COMPUTED_VALUE"""),5.0) -> 5 | AI36: =IFERROR(__xludf.DUMMYFUNCTION("""COMPUTED_VALUE"""),400000.0) -> 400000 | AJ36: =IFERROR(__xludf.DUMMYFUNCTION("""COMPUTED_VALUE"""),"sistema local") -> sistema local | AK36: =IFERROR(__xludf.DUMMYFUNCTION("""COMPUTED_VALUE"""),"delivery,take away e salão") -> delivery,take away e salão | AL36: =IFERROR(__xludf.DUMMYFUNCTION("""COMPUTED_VALUE"""),"SIM") -> SIM | AM36: =IFERROR(__xludf.DUMMYFUNCTION("""COMPUTED_VALUE"""),"FY27") -> FY27 | AO36: =IFERROR(__xludf.DUMMYFUNCTION("""COMPUTED_VALUE"""),61.0) -> 61 | AP36: =IFERROR(__xludf.DUMMYFUNCTION("""COMPUTED_VALUE"""),"RJ") -> RJ | AQ36: =IFERROR(__xludf.DUMMYFUNCTION("""COMPUTED_VALUE"""),"JUAN CHAROTTA") -> JUAN CHAROTTA | AR36: =IFERROR(__xludf.DUMMYFUNCTION("""COMPUTED_VALUE"""),"RIBAMAR GUSMAO") -> RIBAMAR GUSMAO | AS36: =IFERROR(__xludf.DUMMYFUNCTION("""COMPUTED_VALUE"""),"NATHALIE MERTENS") -> NATHALIE MERTENS | AT36: =IFERROR(__xludf.DUMMYFUNCTION("""COMPUTED_VALUE"""),"NATALIA COUTINHO") -> NATALIA COUTINHO | AU36: =IFERROR(__xludf.DUMMYFUNCTION("""COMPUTED_VALUE"""),0.0) -> 0 | AV36: =IFERROR(__xludf.DUMMYFUNCTION("""COMPUTED_VALUE"""),0.0) -> 0 | AW36: =IFERROR(__xludf.DUMMYFUNCTION("""COMPUTED_VALUE"""),0.0) -> 0 | AX36: =IFERROR(__xludf.DUMMYFUNCTION("""COMPUTED_VALUE"""),0.0) -> 0 | AZ36: =IFERROR(__xludf.DUMMYFUNCTION("""COMPUTED_VALUE"""),"Lanches") -> Lanches | BA36: =IFERROR(__xludf.DUMMYFUNCTION("""COMPUTED_VALUE"""),65.0) -> 65 | BB36: =IFERROR(__xludf.DUMMYFUNCTION("""COMPUTED_VALUE"""),"Table Service - Boteco") -> Table Service - Boteco | BC36: =IFERROR(__xludf.DUMMYFUNCTION("""COMPUTED_VALUE"""),"Regional") -> Regional | BE36: =IFERROR(__xludf.DUMMYFUNCTION("""COMPUTED_VALUE"""),55.0) -> 55 | BF36: =IFERROR(__xludf.DUMMYFUNCTION("""COMPUTED_VALUE"""),0.65) -> 0.65 | BG36: =IFERROR(__xludf.DUMMYFUNCTION("""COMPUTED_VALUE"""),"Aderência forte ao 3S: PDV atual não identificado. 3S oferece PDV robusto, KDS integrado e mobilidade (3SGO) para gestão em tempo real - ideal para operações multi-canal.") -> Aderência forte ao 3S: PDV atual não identificado. 3S oferece PDV robusto, KDS integrado e mobilidade (3SGO) para gestão em tempo real - ideal para operações multi-canal.
A37: =IFERROR(__xludf.DUMMYFUNCTION("""COMPUTED_VALUE"""),"BRAVA SUSHI - CONTA MARCA") -> BRAVA SUSHI - CONTA MARCA | B37: =IFERROR(__xludf.DUMMYFUNCTION("""COMPUTED_VALUE"""),"Lídia Esteves") -> Lídia Esteves | C37: =IFERROR(__xludf.DUMMYFUNCTION("""COMPUTED_VALUE"""),"Gabriela Roma") -> Gabriela Roma | D37: =IFERROR(__xludf.DUMMYFUNCTION("""COMPUTED_VALUE"""),"1. Iniciado") -> 1. Iniciado | E37: =IFERROR(__xludf.DUMMYFUNCTION("""COMPUTED_VALUE"""),"Delivery - Aguardando retorno / Conciliação agenda") -> Delivery - Aguardando retorno / Conciliação agenda | F37: =IFERROR(__xludf.DUMMYFUNCTION("""COMPUTED_VALUE"""),"P") -> P | I37: =IFERROR(__xludf.DUMMYFUNCTION("""COMPUTED_VALUE"""),46121.67342309028) -> 46121.673 | AA37: =IFERROR(__xludf.DUMMYFUNCTION("""COMPUTED_VALUE"""),23.0) -> 23 | AB37: =IFERROR(__xludf.DUMMYFUNCTION("""COMPUTED_VALUE"""),"-") -> - | AC37: =IFERROR(__xludf.DUMMYFUNCTION("""COMPUTED_VALUE"""),"Sim") -> Sim | AD37: =IFERROR(__xludf.DUMMYFUNCTION("""COMPUTED_VALUE"""),"Ifood") -> Ifood | AM37: =IFERROR(__xludf.DUMMYFUNCTION("""COMPUTED_VALUE"""),"FY27") -> FY27 | AO37: =IFERROR(__xludf.DUMMYFUNCTION("""COMPUTED_VALUE"""),45553.0) -> 45553 | AP37: =IFERROR(__xludf.DUMMYFUNCTION("""COMPUTED_VALUE"""),"SC") -> SC | AQ37: =IFERROR(__xludf.DUMMYFUNCTION("""COMPUTED_VALUE"""),"BIANCA COUTINHO") -> BIANCA COUTINHO | AR37: =IFERROR(__xludf.DUMMYFUNCTION("""COMPUTED_VALUE"""),"LEANDRO ANKUDAVICIUS") -> LEANDRO ANKUDAVICIUS | AS37: =IFERROR(__xludf.DUMMYFUNCTION("""COMPUTED_VALUE"""),"FABIO DONATO") -> FABIO DONATO | AT37: =IFERROR(__xludf.DUMMYFUNCTION("""COMPUTED_VALUE"""),"CAMILA HOLANDA") -> CAMILA HOLANDA | AU37: =IFERROR(__xludf.DUMMYFUNCTION("""COMPUTED_VALUE"""),0.0) -> 0 | AV37: =IFERROR(__xludf.DUMMYFUNCTION("""COMPUTED_VALUE"""),0.0) -> 0 | AW37: =IFERROR(__xludf.DUMMYFUNCTION("""COMPUTED_VALUE"""),0.0) -> 0 | AX37: =IFERROR(__xludf.DUMMYFUNCTION("""COMPUTED_VALUE"""),0.0) -> 0 | AZ37: =IFERROR(__xludf.DUMMYFUNCTION("""COMPUTED_VALUE"""),"Pizza") -> Pizza | BA37: =IFERROR(__xludf.DUMMYFUNCTION("""COMPUTED_VALUE"""),70.0) -> 70 | BB37: =IFERROR(__xludf.DUMMYFUNCTION("""COMPUTED_VALUE"""),"Fast Casual/Delivery - Comida Japonesa") -> Fast Casual/Delivery - Comida Japonesa | BC37: =IFERROR(__xludf.DUMMYFUNCTION("""COMPUTED_VALUE"""),"Regional/Nacional") -> Regional/Nacional | BD37: =IFERROR(__xludf.DUMMYFUNCTION("""COMPUTED_VALUE"""),"Dado não disponível - Necessário Discovery") -> Dado não disponível - Necessário Discovery | BE37: =IFERROR(__xludf.DUMMYFUNCTION("""COMPUTED_VALUE"""),70.0) -> 70 | BF37: =IFERROR(__xludf.DUMMYFUNCTION("""COMPUTED_VALUE"""),0.8) -> 0.8 | BG37: =IFERROR(__xludf.DUMMYFUNCTION("""COMPUTED_VALUE"""),"Alta aderência ao 3S: PDV atual não identificado. 3S oferece Kiosk nativo, Hub Delivery integrado e gestão centralizada multi-loja - diferenciais competitivos para expansão e redução de filas.") -> Alta aderência ao 3S: PDV atual não identificado. 3S oferece Kiosk nativo, Hub Delivery integrado e gestão centralizada multi-loja - diferenciais competitivos para expansão e redução de filas. | BH37: Saipos Serviços De Software | BI37: 0.75
A38: =IFERROR(__xludf.DUMMYFUNCTION("""COMPUTED_VALUE"""),"BRAZZATTO PIZZA") -> BRAZZATTO PIZZA | B38: =IFERROR(__xludf.DUMMYFUNCTION("""COMPUTED_VALUE"""),"João Biagiotti") -> João Biagiotti | C38: =IFERROR(__xludf.DUMMYFUNCTION("""COMPUTED_VALUE"""),"Diego Santos") -> Diego Santos | D38: =IFERROR(__xludf.DUMMYFUNCTION("""COMPUTED_VALUE"""),"0. Não Iniciado") -> 0. Não Iniciado | F38: =IFERROR(__xludf.DUMMYFUNCTION("""COMPUTED_VALUE"""),"P") -> P | G38: =IFERROR(__xludf.DUMMYFUNCTION("""COMPUTED_VALUE"""),46120.0) -> 46120 | H38: =IFERROR(__xludf.DUMMYFUNCTION("""COMPUTED_VALUE"""),"Executiva delivery está de férias") -> Executiva delivery está de férias | AA38: =IFERROR(__xludf.DUMMYFUNCTION("""COMPUTED_VALUE"""),5.0) -> 5 | AB38: =IFERROR(__xludf.DUMMYFUNCTION("""COMPUTED_VALUE"""),"CE") -> CE | AC38: =IFERROR(__xludf.DUMMYFUNCTION("""COMPUTED_VALUE"""),"Sim") -> Sim | AD38: =IFERROR(__xludf.DUMMYFUNCTION("""COMPUTED_VALUE"""),0.0) -> 0 | AM38: =IFERROR(__xludf.DUMMYFUNCTION("""COMPUTED_VALUE"""),"FY27") -> FY27 | AO38: =IFERROR(__xludf.DUMMYFUNCTION("""COMPUTED_VALUE"""),95.0) -> 95 | AP38: =IFERROR(__xludf.DUMMYFUNCTION("""COMPUTED_VALUE"""),"SP") -> SP | AQ38: =IFERROR(__xludf.DUMMYFUNCTION("""COMPUTED_VALUE"""),"GABRIEL CAMACHO") -> GABRIEL CAMACHO | AR38: =IFERROR(__xludf.DUMMYFUNCTION("""COMPUTED_VALUE"""),"LARISSA GABRIELA") -> LARISSA GABRIELA | AS38: =IFERROR(__xludf.DUMMYFUNCTION("""COMPUTED_VALUE"""),"NATHALIE MERTENS") -> NATHALIE MERTENS | AT38: =IFERROR(__xludf.DUMMYFUNCTION("""COMPUTED_VALUE"""),"MATHEUS LESSA") -> MATHEUS LESSA | AU38: =IFERROR(__xludf.DUMMYFUNCTION("""COMPUTED_VALUE"""),0.0) -> 0 | AV38: =IFERROR(__xludf.DUMMYFUNCTION("""COMPUTED_VALUE"""),0.0) -> 0 | AW38: =IFERROR(__xludf.DUMMYFUNCTION("""COMPUTED_VALUE"""),0.0) -> 0 | AX38: =IFERROR(__xludf.DUMMYFUNCTION("""COMPUTED_VALUE"""),0.0) -> 0 | AZ38: =IFERROR(__xludf.DUMMYFUNCTION("""COMPUTED_VALUE"""),"Pizza") -> Pizza | BA38: =IFERROR(__xludf.DUMMYFUNCTION("""COMPUTED_VALUE"""),68.0) -> 68 | BB38: =IFERROR(__xludf.DUMMYFUNCTION("""COMPUTED_VALUE"""),"Fast Casual - Pizzaria") -> Fast Casual - Pizzaria | BC38: =IFERROR(__xludf.DUMMYFUNCTION("""COMPUTED_VALUE"""),"Regional") -> Regional | BD38: =IFERROR(__xludf.DUMMYFUNCTION("""COMPUTED_VALUE"""),"Dado não disponível - Necessário Discovery") -> Dado não disponível - Necessário Discovery | BE38: =IFERROR(__xludf.DUMMYFUNCTION("""COMPUTED_VALUE"""),70.0) -> 70 | BF38: =IFERROR(__xludf.DUMMYFUNCTION("""COMPUTED_VALUE"""),0.75) -> 0.75 | BG38: =IFERROR(__xludf.DUMMYFUNCTION("""COMPUTED_VALUE"""),"Aderência forte ao 3S: PDV atual não identificado. 3S oferece PDV robusto, KDS integrado e mobilidade (3SGO) para gestão em tempo real - ideal para operações multi-canal.") -> Aderência forte ao 3S: PDV atual não identificado. 3S oferece PDV robusto, KDS integrado e mobilidade (3SGO) para gestão em tempo real - ideal para operações multi-canal. | BH38: Latech Informatica Ltda | BI38: 1
A39: =IFERROR(__xludf.DUMMYFUNCTION("""COMPUTED_VALUE"""),"BRONCO BURGER") -> BRONCO BURGER | B39: =IFERROR(__xludf.DUMMYFUNCTION("""COMPUTED_VALUE"""),"Lídia Esteves") -> Lídia Esteves | C39: =IFERROR(__xludf.DUMMYFUNCTION("""COMPUTED_VALUE"""),"Gabriela Roma") -> Gabriela Roma | D39: =IFERROR(__xludf.DUMMYFUNCTION("""COMPUTED_VALUE"""),"0. Não Iniciado") -> 0. Não Iniciado | F39: =IFERROR(__xludf.DUMMYFUNCTION("""COMPUTED_VALUE"""),"P") -> P | AA39: =IFERROR(__xludf.DUMMYFUNCTION("""COMPUTED_VALUE"""),5.0) -> 5 | AB39: =IFERROR(__xludf.DUMMYFUNCTION("""COMPUTED_VALUE"""),"CE") -> CE | AC39: =IFERROR(__xludf.DUMMYFUNCTION("""COMPUTED_VALUE"""),"Sim") -> Sim | AD39: =IFERROR(__xludf.DUMMYFUNCTION("""COMPUTED_VALUE"""),"Ifood") -> Ifood | AM39: =IFERROR(__xludf.DUMMYFUNCTION("""COMPUTED_VALUE"""),"FY27") -> FY27 | AO39: =IFERROR(__xludf.DUMMYFUNCTION("""COMPUTED_VALUE"""),45553.0) -> 45553 | AP39: =IFERROR(__xludf.DUMMYFUNCTION("""COMPUTED_VALUE"""),"SP") -> SP | AQ39: =IFERROR(__xludf.DUMMYFUNCTION("""COMPUTED_VALUE"""),"VITOR SERRANO") -> VITOR SERRANO | AR39: =IFERROR(__xludf.DUMMYFUNCTION("""COMPUTED_VALUE"""),"LEONARDO FERRARI") -> LEONARDO FERRARI | AS39: =IFERROR(__xludf.DUMMYFUNCTION("""COMPUTED_VALUE"""),"ALAN HADDAD") -> ALAN HADDAD | AT39: =IFERROR(__xludf.DUMMYFUNCTION("""COMPUTED_VALUE"""),"ISABELA DINIZ") -> ISABELA DINIZ | AU39: =IFERROR(__xludf.DUMMYFUNCTION("""COMPUTED_VALUE"""),0.0) -> 0 | AV39: =IFERROR(__xludf.DUMMYFUNCTION("""COMPUTED_VALUE"""),0.0) -> 0 | AW39: =IFERROR(__xludf.DUMMYFUNCTION("""COMPUTED_VALUE"""),0.0) -> 0 | AX39: =IFERROR(__xludf.DUMMYFUNCTION("""COMPUTED_VALUE"""),0.0) -> 0 | AZ39: =IFERROR(__xludf.DUMMYFUNCTION("""COMPUTED_VALUE"""),"Lanches") -> Lanches | BA39: =IFERROR(__xludf.DUMMYFUNCTION("""COMPUTED_VALUE"""),60.0) -> 60 | BB39: =IFERROR(__xludf.DUMMYFUNCTION("""COMPUTED_VALUE"""),"Fast Casual - Hamburgueria") -> Fast Casual - Hamburgueria | BC39: =IFERROR(__xludf.DUMMYFUNCTION("""COMPUTED_VALUE"""),"Regional") -> Regional | BD39: =IFERROR(__xludf.DUMMYFUNCTION("""COMPUTED_VALUE"""),"Dado não disponível - Necessário Discovery") -> Dado não disponível - Necessário Discovery | BE39: =IFERROR(__xludf.DUMMYFUNCTION("""COMPUTED_VALUE"""),70.0) -> 70 | BF39: =IFERROR(__xludf.DUMMYFUNCTION("""COMPUTED_VALUE"""),0.75) -> 0.75 | BG39: =IFERROR(__xludf.DUMMYFUNCTION("""COMPUTED_VALUE"""),"Aderência forte ao 3S: PDV atual não identificado. 3S oferece PDV robusto, KDS integrado e mobilidade (3SGO) para gestão em tempo real - ideal para operações multi-canal.") -> Aderência forte ao 3S: PDV atual não identificado. 3S oferece PDV robusto, KDS integrado e mobilidade (3SGO) para gestão em tempo real - ideal para operações multi-canal. | BH39: Ncr | BI39: 1
A40: =IFERROR(__xludf.DUMMYFUNCTION("""COMPUTED_VALUE"""),"BRUTUS BURGER") -> BRUTUS BURGER | B40: =IFERROR(__xludf.DUMMYFUNCTION("""COMPUTED_VALUE"""),"João Biagiotti") -> João Biagiotti | C40: =IFERROR(__xludf.DUMMYFUNCTION("""COMPUTED_VALUE"""),"Diego Santos") -> Diego Santos | D40: =IFERROR(__xludf.DUMMYFUNCTION("""COMPUTED_VALUE"""),"0. Não Iniciado") -> 0. Não Iniciado | F40: =IFERROR(__xludf.DUMMYFUNCTION("""COMPUTED_VALUE"""),"P") -> P | AA40: =IFERROR(__xludf.DUMMYFUNCTION("""COMPUTED_VALUE"""),7.0) -> 7 | AB40: =IFERROR(__xludf.DUMMYFUNCTION("""COMPUTED_VALUE"""),"CE") -> CE | AC40: =IFERROR(__xludf.DUMMYFUNCTION("""COMPUTED_VALUE"""),"Sim") -> Sim | AD40: =IFERROR(__xludf.DUMMYFUNCTION("""COMPUTED_VALUE"""),"Ifood") -> Ifood | AM40: =IFERROR(__xludf.DUMMYFUNCTION("""COMPUTED_VALUE"""),"FY27") -> FY27 | AO40: =IFERROR(__xludf.DUMMYFUNCTION("""COMPUTED_VALUE"""),45553.0) -> 45553 | AP40: =IFERROR(__xludf.DUMMYFUNCTION("""COMPUTED_VALUE"""),"BA") -> BA | AQ40: =IFERROR(__xludf.DUMMYFUNCTION("""COMPUTED_VALUE"""),"VIDOLIN EDUARDO") -> VIDOLIN EDUARDO | AR40: =IFERROR(__xludf.DUMMYFUNCTION("""COMPUTED_VALUE"""),"VALERIA VASCONCELOS") -> VALERIA VASCONCELOS | AS40: =IFERROR(__xludf.DUMMYFUNCTION("""COMPUTED_VALUE"""),"FABIO DONATO") -> FABIO DONATO | AT40: =IFERROR(__xludf.DUMMYFUNCTION("""COMPUTED_VALUE"""),"GILSON JUNIOR") -> GILSON JUNIOR | AU40: =IFERROR(__xludf.DUMMYFUNCTION("""COMPUTED_VALUE"""),0.0) -> 0 | AV40: =IFERROR(__xludf.DUMMYFUNCTION("""COMPUTED_VALUE"""),0.0) -> 0 | AW40: =IFERROR(__xludf.DUMMYFUNCTION("""COMPUTED_VALUE"""),0.0) -> 0 | AX40: =IFERROR(__xludf.DUMMYFUNCTION("""COMPUTED_VALUE"""),0.0) -> 0 | AZ40: =IFERROR(__xludf.DUMMYFUNCTION("""COMPUTED_VALUE"""),"Lanches") -> Lanches | BA40: =IFERROR(__xludf.DUMMYFUNCTION("""COMPUTED_VALUE"""),68.0) -> 68 | BB40: =IFERROR(__xludf.DUMMYFUNCTION("""COMPUTED_VALUE"""),"Fast Casual - Hamburgueria Artesanal") -> Fast Casual - Hamburgueria Artesanal | BC40: =IFERROR(__xludf.DUMMYFUNCTION("""COMPUTED_VALUE"""),"Salvador e RMS/BA") -> Salvador e RMS/BA | BD40: =IFERROR(__xludf.DUMMYFUNCTION("""COMPUTED_VALUE"""),"Dado não disponível - Necessário Discovery") -> Dado não disponível - Necessário Discovery | BE40: =IFERROR(__xludf.DUMMYFUNCTION("""COMPUTED_VALUE"""),70.0) -> 70 | BF40: =IFERROR(__xludf.DUMMYFUNCTION("""COMPUTED_VALUE"""),0.75) -> 0.75 | BG40: =IFERROR(__xludf.DUMMYFUNCTION("""COMPUTED_VALUE"""),"Aderência forte ao 3S: PDV atual não identificado. 3S oferece PDV robusto, KDS integrado e mobilidade (3SGO) para gestão em tempo real - ideal para operações multi-canal.") -> Aderência forte ao 3S: PDV atual não identificado. 3S oferece PDV robusto, KDS integrado e mobilidade (3SGO) para gestão em tempo real - ideal para operações multi-canal. | BH40: Menew - Linx | BI40: 0.85714286
A41: =IFERROR(__xludf.DUMMYFUNCTION("""COMPUTED_VALUE"""),"BURGER X") -> BURGER X | B41: =IFERROR(__xludf.DUMMYFUNCTION("""COMPUTED_VALUE"""),"João Biagiotti") -> João Biagiotti | C41: =IFERROR(__xludf.DUMMYFUNCTION("""COMPUTED_VALUE"""),"Diego Santos") -> Diego Santos | D41: =IFERROR(__xludf.DUMMYFUNCTION("""COMPUTED_VALUE"""),"0. Não Iniciado") -> 0. Não Iniciado | F41: =IFERROR(__xludf.DUMMYFUNCTION("""COMPUTED_VALUE"""),"M") -> M | AA41: =IFERROR(__xludf.DUMMYFUNCTION("""COMPUTED_VALUE"""),33.0) -> 33 | AB41: =IFERROR(__xludf.DUMMYFUNCTION("""COMPUTED_VALUE"""),"-") -> - | AC41: =IFERROR(__xludf.DUMMYFUNCTION("""COMPUTED_VALUE"""),"Sim") -> Sim | AD41: =IFERROR(__xludf.DUMMYFUNCTION("""COMPUTED_VALUE"""),"Gfr Tec") -> Gfr Tec | AM41: =IFERROR(__xludf.DUMMYFUNCTION("""COMPUTED_VALUE"""),"FY27") -> FY27 | AO41: =IFERROR(__xludf.DUMMYFUNCTION("""COMPUTED_VALUE"""),45553.0) -> 45553 | AP41: =IFERROR(__xludf.DUMMYFUNCTION("""COMPUTED_VALUE"""),"MG") -> MG | AQ41: =IFERROR(__xludf.DUMMYFUNCTION("""COMPUTED_VALUE"""),"FABRYCIO MORI") -> FABRYCIO MORI | AR41: =IFERROR(__xludf.DUMMYFUNCTION("""COMPUTED_VALUE"""),"JOAO MAURICIO") -> JOAO MAURICIO | AS41: =IFERROR(__xludf.DUMMYFUNCTION("""COMPUTED_VALUE"""),"NATHALIE MERTENS") -> NATHALIE MERTENS | AT41: =IFERROR(__xludf.DUMMYFUNCTION("""COMPUTED_VALUE"""),"MATHEUS LESSA") -> MATHEUS LESSA | AU41: =IFERROR(__xludf.DUMMYFUNCTION("""COMPUTED_VALUE"""),0.0) -> 0 | AV41: =IFERROR(__xludf.DUMMYFUNCTION("""COMPUTED_VALUE"""),0.0) -> 0 | AW41: =IFERROR(__xludf.DUMMYFUNCTION("""COMPUTED_VALUE"""),0.0) -> 0 | AX41: =IFERROR(__xludf.DUMMYFUNCTION("""COMPUTED_VALUE"""),0.0) -> 0 | AZ41: =IFERROR(__xludf.DUMMYFUNCTION("""COMPUTED_VALUE"""),"Lanches") -> Lanches | BA41: =IFERROR(__xludf.DUMMYFUNCTION("""COMPUTED_VALUE"""),55.0) -> 55 | BB41: =IFERROR(__xludf.DUMMYFUNCTION("""COMPUTED_VALUE"""),"Fast Casual - Hamburgueria") -> Fast Casual - Hamburgueria | BC41: =IFERROR(__xludf.DUMMYFUNCTION("""COMPUTED_VALUE"""),"Regional") -> Regional | BD41: =IFERROR(__xludf.DUMMYFUNCTION("""COMPUTED_VALUE"""),"Dado não disponível - Necessário Discovery") -> Dado não disponível - Necessário Discovery | BE41: =IFERROR(__xludf.DUMMYFUNCTION("""COMPUTED_VALUE"""),65.0) -> 65 | BF41: =IFERROR(__xludf.DUMMYFUNCTION("""COMPUTED_VALUE"""),0.75) -> 0.75 | BG41: =IFERROR(__xludf.DUMMYFUNCTION("""COMPUTED_VALUE"""),"Aderência forte ao 3S: PDV atual não identificado. 3S oferece PDV robusto, KDS integrado e mobilidade (3SGO) para gestão em tempo real - ideal para operações multi-canal.") -> Aderência forte ao 3S: PDV atual não identificado. 3S oferece PDV robusto, KDS integrado e mobilidade (3SGO) para gestão em tempo real - ideal para operações multi-canal. | BH41: Hubster | BI41: 0.95652174
A42: =IFERROR(__xludf.DUMMYFUNCTION("""COMPUTED_VALUE"""),"BURGERS RIO") -> BURGERS RIO | B42: =IFERROR(__xludf.DUMMYFUNCTION("""COMPUTED_VALUE"""),"Lídia Esteves") -> Lídia Esteves | C42: =IFERROR(__xludf.DUMMYFUNCTION("""COMPUTED_VALUE"""),"Gabriela Roma") -> Gabriela Roma | D42: =IFERROR(__xludf.DUMMYFUNCTION("""COMPUTED_VALUE"""),"1. Iniciado") -> 1. Iniciado | E42: =IFERROR(__xludf.DUMMYFUNCTION("""COMPUTED_VALUE"""),"Delivery - Momento inadequado de abordagem (ex. 99)") -> Delivery - Momento inadequado de abordagem (ex. 99) | F42: =IFERROR(__xludf.DUMMYFUNCTION("""COMPUTED_VALUE"""),"P") -> P | G42: =IFERROR(__xludf.DUMMYFUNCTION("""COMPUTED_VALUE"""),46120.0) -> 46120 | H42: =IFERROR(__xludf.DUMMYFUNCTION("""COMPUTED_VALUE"""),"contato com coord de delivery , informou que o parceiro está em implantação com Saipos ") -> contato com coord de delivery , informou que o parceiro está em implantação com Saipos | I42: =IFERROR(__xludf.DUMMYFUNCTION("""COMPUTED_VALUE"""),46120.72112502315) -> 46120.721 | AA42: =IFERROR(__xludf.DUMMYFUNCTION("""COMPUTED_VALUE"""),5.0) -> 5 | AB42: =IFERROR(__xludf.DUMMYFUNCTION("""COMPUTED_VALUE"""),"CE") -> CE | AC42: =IFERROR(__xludf.DUMMYFUNCTION("""COMPUTED_VALUE"""),"Sim") -> Sim | AD42: =IFERROR(__xludf.DUMMYFUNCTION("""COMPUTED_VALUE"""),"Ifood") -> Ifood | AM42: =IFERROR(__xludf.DUMMYFUNCTION("""COMPUTED_VALUE"""),"FY27") -> FY27 | AO42: =IFERROR(__xludf.DUMMYFUNCTION("""COMPUTED_VALUE"""),95.0) -> 95 | AP42: =IFERROR(__xludf.DUMMYFUNCTION("""COMPUTED_VALUE"""),"RJ") -> RJ | AQ42: =IFERROR(__xludf.DUMMYFUNCTION("""COMPUTED_VALUE"""),"BRUNO MEIRA") -> BRUNO MEIRA | AR42: =IFERROR(__xludf.DUMMYFUNCTION("""COMPUTED_VALUE"""),"GONCALVES GUILHERME") -> GONCALVES GUILHERME | AS42: =IFERROR(__xludf.DUMMYFUNCTION("""COMPUTED_VALUE"""),"NATHALIE MERTENS") -> NATHALIE MERTENS | AT42: =IFERROR(__xludf.DUMMYFUNCTION("""COMPUTED_VALUE"""),"NATALIA COUTINHO") -> NATALIA COUTINHO | AU42: =IFERROR(__xludf.DUMMYFUNCTION("""COMPUTED_VALUE"""),0.0) -> 0 | AV42: =IFERROR(__xludf.DUMMYFUNCTION("""COMPUTED_VALUE"""),0.0) -> 0 | AW42: =IFERROR(__xludf.DUMMYFUNCTION("""COMPUTED_VALUE"""),0.0) -> 0 | AX42: =IFERROR(__xludf.DUMMYFUNCTION("""COMPUTED_VALUE"""),0.0) -> 0 | AY42: =IFERROR(__xludf.DUMMYFUNCTION("""COMPUTED_VALUE"""),"Saipos Serviços De Software") -> Saipos Serviços De Software | AZ42: =IFERROR(__xludf.DUMMYFUNCTION("""COMPUTED_VALUE"""),"Lanches") -> Lanches | BA42: =IFERROR(__xludf.DUMMYFUNCTION("""COMPUTED_VALUE"""),62.0) -> 62 | BB42: =IFERROR(__xludf.DUMMYFUNCTION("""COMPUTED_VALUE"""),"Fast Casual - Hamburgueria") -> Fast Casual - Hamburgueria | BC42: =IFERROR(__xludf.DUMMYFUNCTION("""COMPUTED_VALUE"""),"Rio de Janeiro/RJ") -> Rio de Janeiro/RJ | BD42: =IFERROR(__xludf.DUMMYFUNCTION("""COMPUTED_VALUE"""),"Dado não disponível - Necessário Discovery") -> Dado não disponível - Necessário Discovery | BE42: =IFERROR(__xludf.DUMMYFUNCTION("""COMPUTED_VALUE"""),70.0) -> 70 | BF42: =IFERROR(__xludf.DUMMYFUNCTION("""COMPUTED_VALUE"""),0.75) -> 0.75 | BG42: =IFERROR(__xludf.DUMMYFUNCTION("""COMPUTED_VALUE"""),"Aderência forte ao 3S: PDV atual não identificado. 3S oferece PDV robusto, KDS integrado e mobilidade (3SGO) para gestão em tempo real - ideal para operações multi-canal.") -> Aderência forte ao 3S: PDV atual não identificado. 3S oferece PDV robusto, KDS integrado e mobilidade (3SGO) para gestão em tempo real - ideal para operações multi-canal. | BH42: Saipos Serviços De Software | BI42: 0.66666667
A43: =IFERROR(__xludf.DUMMYFUNCTION("""COMPUTED_VALUE"""),"CACHORRAO DO CLAUDIAO OFICIAL") -> CACHORRAO DO CLAUDIAO OFICIAL | B43: =IFERROR(__xludf.DUMMYFUNCTION("""COMPUTED_VALUE"""),"Lídia Esteves") -> Lídia Esteves | C43: =IFERROR(__xludf.DUMMYFUNCTION("""COMPUTED_VALUE"""),"Gabriela Roma") -> Gabriela Roma | D43: =IFERROR(__xludf.DUMMYFUNCTION("""COMPUTED_VALUE"""),"0. Não Iniciado") -> 0. Não Iniciado | F43: =IFERROR(__xludf.DUMMYFUNCTION("""COMPUTED_VALUE"""),"P") -> P | AA43: =IFERROR(__xludf.DUMMYFUNCTION("""COMPUTED_VALUE"""),3.0) -> 3 | AB43: =IFERROR(__xludf.DUMMYFUNCTION("""COMPUTED_VALUE"""),"CE") -> CE | AC43: =IFERROR(__xludf.DUMMYFUNCTION("""COMPUTED_VALUE"""),"Sim") -> Sim | AD43: =IFERROR(__xludf.DUMMYFUNCTION("""COMPUTED_VALUE"""),"Ifood") -> Ifood | AM43: =IFERROR(__xludf.DUMMYFUNCTION("""COMPUTED_VALUE"""),"FY27") -> FY27 | AO43: =IFERROR(__xludf.DUMMYFUNCTION("""COMPUTED_VALUE"""),45553.0) -> 45553 | AP43: =IFERROR(__xludf.DUMMYFUNCTION("""COMPUTED_VALUE"""),"SC") -> SC | AQ43: =IFERROR(__xludf.DUMMYFUNCTION("""COMPUTED_VALUE"""),"DANIELLY SOARES") -> DANIELLY SOARES | AR43: =IFERROR(__xludf.DUMMYFUNCTION("""COMPUTED_VALUE"""),"DARLAN TOSO") -> DARLAN TOSO | AS43: =IFERROR(__xludf.DUMMYFUNCTION("""COMPUTED_VALUE"""),"FABIO DONATO") -> FABIO DONATO | AT43: =IFERROR(__xludf.DUMMYFUNCTION("""COMPUTED_VALUE"""),"CAMILA HOLANDA") -> CAMILA HOLANDA | AU43: =IFERROR(__xludf.DUMMYFUNCTION("""COMPUTED_VALUE"""),0.0) -> 0 | AV43: =IFERROR(__xludf.DUMMYFUNCTION("""COMPUTED_VALUE"""),0.0) -> 0 | AW43: =IFERROR(__xludf.DUMMYFUNCTION("""COMPUTED_VALUE"""),0.0) -> 0 | AX43: =IFERROR(__xludf.DUMMYFUNCTION("""COMPUTED_VALUE"""),0.0) -> 0 | AY43: =IFERROR(__xludf.DUMMYFUNCTION("""COMPUTED_VALUE"""),"Suitable Tecnologia E Gestao") -> Suitable Tecnologia E Gestao | AZ43: =IFERROR(__xludf.DUMMYFUNCTION("""COMPUTED_VALUE"""),"Lanches") -> Lanches | BA43: =IFERROR(__xludf.DUMMYFUNCTION("""COMPUTED_VALUE"""),"") | BB43: =IFERROR(__xludf.DUMMYFUNCTION("""COMPUTED_VALUE"""),"") | BC43: =IFERROR(__xludf.DUMMYFUNCTION("""COMPUTED_VALUE"""),"") | BD43: =IFERROR(__xludf.DUMMYFUNCTION("""COMPUTED_VALUE"""),"") | BE43: =IFERROR(__xludf.DUMMYFUNCTION("""COMPUTED_VALUE"""),"") | BF43: =IFERROR(__xludf.DUMMYFUNCTION("""COMPUTED_VALUE"""),"") | BG43: =IFERROR(__xludf.DUMMYFUNCTION("""COMPUTED_VALUE"""),"") | BH43: Suitable Tecnologia E Gestao | BI43: 0.7
A44: =IFERROR(__xludf.DUMMYFUNCTION("""COMPUTED_VALUE"""),"CAFE CULTURA SC - CONTA MARCA") -> CAFE CULTURA SC - CONTA MARCA | B44: =IFERROR(__xludf.DUMMYFUNCTION("""COMPUTED_VALUE"""),"Lídia Esteves") -> Lídia Esteves | C44: =IFERROR(__xludf.DUMMYFUNCTION("""COMPUTED_VALUE"""),"Gabriela Roma") -> Gabriela Roma | D44: =IFERROR(__xludf.DUMMYFUNCTION("""COMPUTED_VALUE"""),"0. Não Iniciado") -> 0. Não Iniciado | F44: =IFERROR(__xludf.DUMMYFUNCTION("""COMPUTED_VALUE"""),"M") -> M | AA44: =IFERROR(__xludf.DUMMYFUNCTION("""COMPUTED_VALUE"""),49.0) -> 49 | AB44: =IFERROR(__xludf.DUMMYFUNCTION("""COMPUTED_VALUE"""),"-") -> - | AC44: =IFERROR(__xludf.DUMMYFUNCTION("""COMPUTED_VALUE"""),"Sim") -> Sim | AD44: =IFERROR(__xludf.DUMMYFUNCTION("""COMPUTED_VALUE"""),"Ifood") -> Ifood | AM44: =IFERROR(__xludf.DUMMYFUNCTION("""COMPUTED_VALUE"""),"FY27") -> FY27 | AO44: =IFERROR(__xludf.DUMMYFUNCTION("""COMPUTED_VALUE"""),45553.0) -> 45553 | AP44: =IFERROR(__xludf.DUMMYFUNCTION("""COMPUTED_VALUE"""),"RS") -> RS | AQ44: =IFERROR(__xludf.DUMMYFUNCTION("""COMPUTED_VALUE"""),"MARIA SILVEIRA") -> MARIA SILVEIRA | AR44: =IFERROR(__xludf.DUMMYFUNCTION("""COMPUTED_VALUE"""),"MAYARA CABRAL") -> MAYARA CABRAL | AS44: =IFERROR(__xludf.DUMMYFUNCTION("""COMPUTED_VALUE"""),"FABIO DONATO") -> FABIO DONATO | AT44: =IFERROR(__xludf.DUMMYFUNCTION("""COMPUTED_VALUE"""),"CAMILA HOLANDA") -> CAMILA HOLANDA | AU44: =IFERROR(__xludf.DUMMYFUNCTION("""COMPUTED_VALUE"""),0.0) -> 0 | AV44: =IFERROR(__xludf.DUMMYFUNCTION("""COMPUTED_VALUE"""),0.0) -> 0 | AW44: =IFERROR(__xludf.DUMMYFUNCTION("""COMPUTED_VALUE"""),0.0) -> 0 | AX44: =IFERROR(__xludf.DUMMYFUNCTION("""COMPUTED_VALUE"""),0.0) -> 0 | AY44: =IFERROR(__xludf.DUMMYFUNCTION("""COMPUTED_VALUE"""),"Totvs Large Enterprise Tecnologia S.a.") -> Totvs Large Enterprise Tecnologia S.a. | AZ44: =IFERROR(__xludf.DUMMYFUNCTION("""COMPUTED_VALUE"""),"Cafeteria") -> Cafeteria | BA44: =IFERROR(__xludf.DUMMYFUNCTION("""COMPUTED_VALUE"""),38.0) -> 38 | BB44: =IFERROR(__xludf.DUMMYFUNCTION("""COMPUTED_VALUE"""),"Fast Casual - Cafeteria") -> Fast Casual - Cafeteria | BC44: =IFERROR(__xludf.DUMMYFUNCTION("""COMPUTED_VALUE"""),"Santa Catarina") -> Santa Catarina | BD44: =IFERROR(__xludf.DUMMYFUNCTION("""COMPUTED_VALUE"""),"Dado não disponível - Necessário Discovery") -> Dado não disponível - Necessário Discovery | BE44: =IFERROR(__xludf.DUMMYFUNCTION("""COMPUTED_VALUE"""),70.0) -> 70 | BF44: =IFERROR(__xludf.DUMMYFUNCTION("""COMPUTED_VALUE"""),0.75) -> 0.75 | BG44: =IFERROR(__xludf.DUMMYFUNCTION("""COMPUTED_VALUE"""),"Aderência forte ao 3S: PDV atual não identificado. 3S oferece PDV robusto, KDS integrado e mobilidade (3SGO) para gestão em tempo real - ideal para operações multi-canal.") -> Aderência forte ao 3S: PDV atual não identificado. 3S oferece PDV robusto, KDS integrado e mobilidade (3SGO) para gestão em tempo real - ideal para operações multi-canal. | BH44: Totvs Large Enterprise Tecnologia S.a. | BI44: 0.61904762
A45: =IFERROR(__xludf.DUMMYFUNCTION("""COMPUTED_VALUE"""),"CAMARAO TO GO") -> CAMARAO TO GO | B45: =IFERROR(__xludf.DUMMYFUNCTION("""COMPUTED_VALUE"""),"João Biagiotti") -> João Biagiotti | C45: =IFERROR(__xludf.DUMMYFUNCTION("""COMPUTED_VALUE"""),"Diego Santos") -> Diego Santos | D45: =IFERROR(__xludf.DUMMYFUNCTION("""COMPUTED_VALUE"""),"0. Não Iniciado") -> 0. Não Iniciado | F45: =IFERROR(__xludf.DUMMYFUNCTION("""COMPUTED_VALUE"""),"P") -> P | AA45: =IFERROR(__xludf.DUMMYFUNCTION("""COMPUTED_VALUE"""),10.0) -> 10 | AB45: =IFERROR(__xludf.DUMMYFUNCTION("""COMPUTED_VALUE"""),"CE") -> CE | AC45: =IFERROR(__xludf.DUMMYFUNCTION("""COMPUTED_VALUE"""),"Sim") -> Sim | AD45: =IFERROR(__xludf.DUMMYFUNCTION("""COMPUTED_VALUE"""),0.0) -> 0 | AM45: =IFERROR(__xludf.DUMMYFUNCTION("""COMPUTED_VALUE"""),"FY27") -> FY27 | AO45: =IFERROR(__xludf.DUMMYFUNCTION("""COMPUTED_VALUE"""),45553.0) -> 45553 | AP45: =IFERROR(__xludf.DUMMYFUNCTION("""COMPUTED_VALUE"""),"CE") -> CE | AQ45: =IFERROR(__xludf.DUMMYFUNCTION("""COMPUTED_VALUE"""),"FABIO MAKARON") -> FABIO MAKARON | AR45: =IFERROR(__xludf.DUMMYFUNCTION("""COMPUTED_VALUE"""),0.0) -> 0 | AS45: =IFERROR(__xludf.DUMMYFUNCTION("""COMPUTED_VALUE"""),0.0) -> 0 | AT45: =IFERROR(__xludf.DUMMYFUNCTION("""COMPUTED_VALUE"""),0.0) -> 0 | AU45: =IFERROR(__xludf.DUMMYFUNCTION("""COMPUTED_VALUE"""),0.0) -> 0 | AV45: =IFERROR(__xludf.DUMMYFUNCTION("""COMPUTED_VALUE"""),0.0) -> 0 | AW45: =IFERROR(__xludf.DUMMYFUNCTION("""COMPUTED_VALUE"""),0.0) -> 0 | AX45: =IFERROR(__xludf.DUMMYFUNCTION("""COMPUTED_VALUE"""),0.0) -> 0 | AZ45: =IFERROR(__xludf.DUMMYFUNCTION("""COMPUTED_VALUE"""),"Brasileira") -> Brasileira | BA45: =IFERROR(__xludf.DUMMYFUNCTION("""COMPUTED_VALUE"""),"") | BB45: =IFERROR(__xludf.DUMMYFUNCTION("""COMPUTED_VALUE"""),"") | BC45: =IFERROR(__xludf.DUMMYFUNCTION("""COMPUTED_VALUE"""),"") | BD45: =IFERROR(__xludf.DUMMYFUNCTION("""COMPUTED_VALUE"""),"") | BE45: =IFERROR(__xludf.DUMMYFUNCTION("""COMPUTED_VALUE"""),"") | BF45: =IFERROR(__xludf.DUMMYFUNCTION("""COMPUTED_VALUE"""),"") | BG45: =IFERROR(__xludf.DUMMYFUNCTION("""COMPUTED_VALUE"""),"")
A46: =IFERROR(__xludf.DUMMYFUNCTION("""COMPUTED_VALUE"""),"CAMAROES") -> CAMAROES | B46: =IFERROR(__xludf.DUMMYFUNCTION("""COMPUTED_VALUE"""),"João Biagiotti") -> João Biagiotti | C46: =IFERROR(__xludf.DUMMYFUNCTION("""COMPUTED_VALUE"""),"Diego Santos") -> Diego Santos | D46: =IFERROR(__xludf.DUMMYFUNCTION("""COMPUTED_VALUE"""),"0. Não Iniciado") -> 0. Não Iniciado | F46: =IFERROR(__xludf.DUMMYFUNCTION("""COMPUTED_VALUE"""),"P") -> P | AA46: =IFERROR(__xludf.DUMMYFUNCTION("""COMPUTED_VALUE"""),5.0) -> 5 | AB46: =IFERROR(__xludf.DUMMYFUNCTION("""COMPUTED_VALUE"""),"CE") -> CE | AC46: =IFERROR(__xludf.DUMMYFUNCTION("""COMPUTED_VALUE"""),"Sim") -> Sim | AD46: =IFERROR(__xludf.DUMMYFUNCTION("""COMPUTED_VALUE"""),"Ifood") -> Ifood | AM46: =IFERROR(__xludf.DUMMYFUNCTION("""COMPUTED_VALUE"""),"FY27") -> FY27 | AO46: =IFERROR(__xludf.DUMMYFUNCTION("""COMPUTED_VALUE"""),45553.0) -> 45553 | AP46: =IFERROR(__xludf.DUMMYFUNCTION("""COMPUTED_VALUE"""),"RN") -> RN | AQ46: =IFERROR(__xludf.DUMMYFUNCTION("""COMPUTED_VALUE"""),"TATIANY MEDEIROS") -> TATIANY MEDEIROS | AR46: =IFERROR(__xludf.DUMMYFUNCTION("""COMPUTED_VALUE"""),"HUMBERTO FILHO") -> HUMBERTO FILHO | AS46: =IFERROR(__xludf.DUMMYFUNCTION("""COMPUTED_VALUE"""),"THIAGO ROMAGNOLE") -> THIAGO ROMAGNOLE | AT46: =IFERROR(__xludf.DUMMYFUNCTION("""COMPUTED_VALUE"""),"ANDERSON LAUREANO") -> ANDERSON LAUREANO | AU46: =IFERROR(__xludf.DUMMYFUNCTION("""COMPUTED_VALUE"""),0.0) -> 0 | AV46: =IFERROR(__xludf.DUMMYFUNCTION("""COMPUTED_VALUE"""),0.0) -> 0 | AW46: =IFERROR(__xludf.DUMMYFUNCTION("""COMPUTED_VALUE"""),0.0) -> 0 | AX46: =IFERROR(__xludf.DUMMYFUNCTION("""COMPUTED_VALUE"""),0.0) -> 0 | AY46: =IFERROR(__xludf.DUMMYFUNCTION("""COMPUTED_VALUE"""),"Venditx Ltda") -> Venditx Ltda | AZ46: =IFERROR(__xludf.DUMMYFUNCTION("""COMPUTED_VALUE"""),"Frutos Do Mar") -> Frutos Do Mar | BA46: =IFERROR(__xludf.DUMMYFUNCTION("""COMPUTED_VALUE"""),"") | BB46: =IFERROR(__xludf.DUMMYFUNCTION("""COMPUTED_VALUE"""),"") | BC46: =IFERROR(__xludf.DUMMYFUNCTION("""COMPUTED_VALUE"""),"") | BD46: =IFERROR(__xludf.DUMMYFUNCTION("""COMPUTED_VALUE"""),"") | BE46: =IFERROR(__xludf.DUMMYFUNCTION("""COMPUTED_VALUE"""),"") | BF46: =IFERROR(__xludf.DUMMYFUNCTION("""COMPUTED_VALUE"""),"") | BG46: =IFERROR(__xludf.DUMMYFUNCTION("""COMPUTED_VALUE"""),"") | BH46: Venditx Ltda | BI46: 0.57142857
A47: =IFERROR(__xludf.DUMMYFUNCTION("""COMPUTED_VALUE"""),"CANTINHO DO PASTEL") -> CANTINHO DO PASTEL | B47: =IFERROR(__xludf.DUMMYFUNCTION("""COMPUTED_VALUE"""),"João Biagiotti") -> João Biagiotti | C47: =IFERROR(__xludf.DUMMYFUNCTION("""COMPUTED_VALUE"""),"Diego Santos") -> Diego Santos | D47: =IFERROR(__xludf.DUMMYFUNCTION("""COMPUTED_VALUE"""),"0. Não Iniciado") -> 0. Não Iniciado | F47: =IFERROR(__xludf.DUMMYFUNCTION("""COMPUTED_VALUE"""),"P") -> P | AA47: =IFERROR(__xludf.DUMMYFUNCTION("""COMPUTED_VALUE"""),10.0) -> 10 | AB47: =IFERROR(__xludf.DUMMYFUNCTION("""COMPUTED_VALUE"""),"CE") -> CE | AC47: =IFERROR(__xludf.DUMMYFUNCTION("""COMPUTED_VALUE"""),"Sim") -> Sim | AD47: =IFERROR(__xludf.DUMMYFUNCTION("""COMPUTED_VALUE"""),"Ifood") -> Ifood | AM47: =IFERROR(__xludf.DUMMYFUNCTION("""COMPUTED_VALUE"""),"FY27") -> FY27 | AO47: =IFERROR(__xludf.DUMMYFUNCTION("""COMPUTED_VALUE"""),45553.0) -> 45553 | AP47: =IFERROR(__xludf.DUMMYFUNCTION("""COMPUTED_VALUE"""),"SP") -> SP | AQ47: =IFERROR(__xludf.DUMMYFUNCTION("""COMPUTED_VALUE"""),"DANIELLE SENA") -> DANIELLE SENA | AR47: =IFERROR(__xludf.DUMMYFUNCTION("""COMPUTED_VALUE"""),"TBH-INDAIATUBA02") -> TBH-INDAIATUBA02 | AS47: =IFERROR(__xludf.DUMMYFUNCTION("""COMPUTED_VALUE"""),"ALAN HADDAD") -> ALAN HADDAD | AT47: =IFERROR(__xludf.DUMMYFUNCTION("""COMPUTED_VALUE"""),"ISABELA DINIZ") -> ISABELA DINIZ | AU47: =IFERROR(__xludf.DUMMYFUNCTION("""COMPUTED_VALUE"""),0.0) -> 0 | AV47: =IFERROR(__xludf.DUMMYFUNCTION("""COMPUTED_VALUE"""),0.0) -> 0 | AW47: =IFERROR(__xludf.DUMMYFUNCTION("""COMPUTED_VALUE"""),0.0) -> 0 | AX47: =IFERROR(__xludf.DUMMYFUNCTION("""COMPUTED_VALUE"""),0.0) -> 0 | AZ47: =IFERROR(__xludf.DUMMYFUNCTION("""COMPUTED_VALUE"""),"Brasileira") -> Brasileira | BA47: =IFERROR(__xludf.DUMMYFUNCTION("""COMPUTED_VALUE"""),25.0) -> 25 | BB47: =IFERROR(__xludf.DUMMYFUNCTION("""COMPUTED_VALUE"""),"QSR - Pastelaria") -> QSR - Pastelaria | BC47: =IFERROR(__xludf.DUMMYFUNCTION("""COMPUTED_VALUE"""),"Regional") -> Regional | BD47: =IFERROR(__xludf.DUMMYFUNCTION("""COMPUTED_VALUE"""),"Dado não disponível - Necessário Discovery") -> Dado não disponível - Necessário Discovery | BE47: =IFERROR(__xludf.DUMMYFUNCTION("""COMPUTED_VALUE"""),70.0) -> 70 | BF47: =IFERROR(__xludf.DUMMYFUNCTION("""COMPUTED_VALUE"""),0.85) -> 0.85 | BG47: =IFERROR(__xludf.DUMMYFUNCTION("""COMPUTED_VALUE"""),"Alta aderência ao 3S: PDV atual não identificado. 3S oferece Kiosk nativo, Hub Delivery integrado e gestão centralizada multi-loja - diferenciais competitivos para expansão e redução de filas.") -> Alta aderência ao 3S: PDV atual não identificado. 3S oferece Kiosk nativo, Hub Delivery integrado e gestão centralizada multi-loja - diferenciais competitivos para expansão e redução de filas. | BH47: Saipos Serviços De Software | BI47: 0.42857143
A48: =IFERROR(__xludf.DUMMYFUNCTION("""COMPUTED_VALUE"""),"CANTINHO DO SABOR") -> CANTINHO DO SABOR | B48: =IFERROR(__xludf.DUMMYFUNCTION("""COMPUTED_VALUE"""),"Lídia Esteves") -> Lídia Esteves | C48: =IFERROR(__xludf.DUMMYFUNCTION("""COMPUTED_VALUE"""),"Gabriela Roma") -> Gabriela Roma | D48: =IFERROR(__xludf.DUMMYFUNCTION("""COMPUTED_VALUE"""),"2. Primeiro Contato com a marca") -> 2. Primeiro Contato com a marca | E48: =IFERROR(__xludf.DUMMYFUNCTION("""COMPUTED_VALUE"""),"Delivery - Aguardando retorno / Conciliação agenda") -> Delivery - Aguardando retorno / Conciliação agenda | F48: =IFERROR(__xludf.DUMMYFUNCTION("""COMPUTED_VALUE"""),"P") -> P | I48: =IFERROR(__xludf.DUMMYFUNCTION("""COMPUTED_VALUE"""),46121.67391232639) -> 46121.674 | J48: =IFERROR(__xludf.DUMMYFUNCTION("""COMPUTED_VALUE"""),46126.71372636574) -> 46126.714 | AA48: =IFERROR(__xludf.DUMMYFUNCTION("""COMPUTED_VALUE"""),11.0) -> 11 | AB48: =IFERROR(__xludf.DUMMYFUNCTION("""COMPUTED_VALUE"""),"Não Encarteirado") -> Não Encarteirado | AC48: =IFERROR(__xludf.DUMMYFUNCTION("""COMPUTED_VALUE"""),"Sim") -> Sim | AD48: =IFERROR(__xludf.DUMMYFUNCTION("""COMPUTED_VALUE"""),0.0) -> 0 | AM48: =IFERROR(__xludf.DUMMYFUNCTION("""COMPUTED_VALUE"""),"FY27") -> FY27 | AO48: =IFERROR(__xludf.DUMMYFUNCTION("""COMPUTED_VALUE"""),45553.0) -> 45553 | AP48: =IFERROR(__xludf.DUMMYFUNCTION("""COMPUTED_VALUE"""),"RJ") -> RJ | AQ48: =IFERROR(__xludf.DUMMYFUNCTION("""COMPUTED_VALUE"""),"JUAN CHAROTTA") -> JUAN CHAROTTA | AR48: =IFERROR(__xludf.DUMMYFUNCTION("""COMPUTED_VALUE"""),0.0) -> 0 | AS48: =IFERROR(__xludf.DUMMYFUNCTION("""COMPUTED_VALUE"""),0.0) -> 0 | AT48: =IFERROR(__xludf.DUMMYFUNCTION("""COMPUTED_VALUE"""),0.0) -> 0 | AU48: =IFERROR(__xludf.DUMMYFUNCTION("""COMPUTED_VALUE"""),0.0) -> 0 | AV48: =IFERROR(__xludf.DUMMYFUNCTION("""COMPUTED_VALUE"""),0.0) -> 0 | AW48: =IFERROR(__xludf.DUMMYFUNCTION("""COMPUTED_VALUE"""),0.0) -> 0 | AX48: =IFERROR(__xludf.DUMMYFUNCTION("""COMPUTED_VALUE"""),0.0) -> 0 | AZ48: =IFERROR(__xludf.DUMMYFUNCTION("""COMPUTED_VALUE"""),"Brasileira") -> Brasileira | BA48: =IFERROR(__xludf.DUMMYFUNCTION("""COMPUTED_VALUE"""),30.0) -> 30 | BB48: =IFERROR(__xludf.DUMMYFUNCTION("""COMPUTED_VALUE"""),"QSR - Comida Caseira") -> QSR - Comida Caseira | BC48: =IFERROR(__xludf.DUMMYFUNCTION("""COMPUTED_VALUE"""),"Regional") -> Regional | BD48: =IFERROR(__xludf.DUMMYFUNCTION("""COMPUTED_VALUE"""),"Dado não disponível - Necessário Discovery") -> Dado não disponível - Necessário Discovery | BE48: =IFERROR(__xludf.DUMMYFUNCTION("""COMPUTED_VALUE"""),65.0) -> 65 | BF48: =IFERROR(__xludf.DUMMYFUNCTION("""COMPUTED_VALUE"""),0.85) -> 0.85 | BG48: =IFERROR(__xludf.DUMMYFUNCTION("""COMPUTED_VALUE"""),"Alta aderência ao 3S: PDV atual não identificado. 3S oferece Kiosk nativo, Hub Delivery integrado e gestão centralizada multi-loja - diferenciais competitivos para expansão e redução de filas.") -> Alta aderência ao 3S: PDV atual não identificado. 3S oferece Kiosk nativo, Hub Delivery integrado e gestão centralizada multi-loja - diferenciais competitivos para expansão e redução de filas. | BH48: Instadelivery | BI48: 0.33333333
A49: =IFERROR(__xludf.DUMMYFUNCTION("""COMPUTED_VALUE"""),"CANTUCCI OSTERIA") -> CANTUCCI OSTERIA | B49: =IFERROR(__xludf.DUMMYFUNCTION("""COMPUTED_VALUE"""),"Lídia Esteves") -> Lídia Esteves | C49: =IFERROR(__xludf.DUMMYFUNCTION("""COMPUTED_VALUE"""),"Gabriela Roma") -> Gabriela Roma | D49: =IFERROR(__xludf.DUMMYFUNCTION("""COMPUTED_VALUE"""),"0. Não Iniciado") -> 0. Não Iniciado | F49: =IFERROR(__xludf.DUMMYFUNCTION("""COMPUTED_VALUE"""),"P") -> P | AA49: =IFERROR(__xludf.DUMMYFUNCTION("""COMPUTED_VALUE"""),5.0) -> 5 | AB49: =IFERROR(__xludf.DUMMYFUNCTION("""COMPUTED_VALUE"""),"CE") -> CE | AC49: =IFERROR(__xludf.DUMMYFUNCTION("""COMPUTED_VALUE"""),"Sim") -> Sim | AD49: =IFERROR(__xludf.DUMMYFUNCTION("""COMPUTED_VALUE"""),"Netcontroll Xmenu") -> Netcontroll Xmenu | AM49: =IFERROR(__xludf.DUMMYFUNCTION("""COMPUTED_VALUE"""),"FY27") -> FY27 | AO49: =IFERROR(__xludf.DUMMYFUNCTION("""COMPUTED_VALUE"""),45553.0) -> 45553 | AP49: =IFERROR(__xludf.DUMMYFUNCTION("""COMPUTED_VALUE"""),"DF") -> DF | AQ49: =IFERROR(__xludf.DUMMYFUNCTION("""COMPUTED_VALUE"""),"ISABELLE NOGUEIRA") -> ISABELLE NOGUEIRA | AR49: =IFERROR(__xludf.DUMMYFUNCTION("""COMPUTED_VALUE"""),"MATHEUS BITENCOURT") -> MATHEUS BITENCOURT | AS49: =IFERROR(__xludf.DUMMYFUNCTION("""COMPUTED_VALUE"""),"THIAGO ROMAGNOLE") -> THIAGO ROMAGNOLE | AT49: =IFERROR(__xludf.DUMMYFUNCTION("""COMPUTED_VALUE"""),"PAULO MODESTO") -> PAULO MODESTO | AU49: =IFERROR(__xludf.DUMMYFUNCTION("""COMPUTED_VALUE"""),0.0) -> 0 | AV49: =IFERROR(__xludf.DUMMYFUNCTION("""COMPUTED_VALUE"""),0.0) -> 0 | AW49: =IFERROR(__xludf.DUMMYFUNCTION("""COMPUTED_VALUE"""),0.0) -> 0 | AX49: =IFERROR(__xludf.DUMMYFUNCTION("""COMPUTED_VALUE"""),0.0) -> 0 | AY49: =IFERROR(__xludf.DUMMYFUNCTION("""COMPUTED_VALUE"""),"Ncr") -> Ncr | AZ49: =IFERROR(__xludf.DUMMYFUNCTION("""COMPUTED_VALUE"""),"Italiana") -> Italiana | BA49: =IFERROR(__xludf.DUMMYFUNCTION("""COMPUTED_VALUE"""),95.0) -> 95 | BB49: =IFERROR(__xludf.DUMMYFUNCTION("""COMPUTED_VALUE"""),"Table Service - Italiano") -> Table Service - Italiano | BC49: =IFERROR(__xludf.DUMMYFUNCTION("""COMPUTED_VALUE"""),"Regional") -> Regional | BD49: =IFERROR(__xludf.DUMMYFUNCTION("""COMPUTED_VALUE"""),"Dado não disponível - Necessário Discovery") -> Dado não disponível - Necessário Discovery | BE49: =IFERROR(__xludf.DUMMYFUNCTION("""COMPUTED_VALUE"""),55.0) -> 55 | BF49: =IFERROR(__xludf.DUMMYFUNCTION("""COMPUTED_VALUE"""),0.65) -> 0.65 | BG49: =IFERROR(__xludf.DUMMYFUNCTION("""COMPUTED_VALUE"""),"Aderência forte ao 3S: PDV atual não identificado. 3S oferece PDV robusto, KDS integrado e mobilidade (3SGO) para gestão em tempo real - ideal para operações multi-canal.") -> Aderência forte ao 3S: PDV atual não identificado. 3S oferece PDV robusto, KDS integrado e mobilidade (3SGO) para gestão em tempo real - ideal para operações multi-canal. | BH49: Ncr | BI49: 0.81818182
A50: =IFERROR(__xludf.DUMMYFUNCTION("""COMPUTED_VALUE"""),"CARECA") -> CARECA | B50: =IFERROR(__xludf.DUMMYFUNCTION("""COMPUTED_VALUE"""),"João Biagiotti") -> João Biagiotti | C50: =IFERROR(__xludf.DUMMYFUNCTION("""COMPUTED_VALUE"""),"Diego Santos") -> Diego Santos | D50: =IFERROR(__xludf.DUMMYFUNCTION("""COMPUTED_VALUE"""),"0. Não Iniciado") -> 0. Não Iniciado | F50: =IFERROR(__xludf.DUMMYFUNCTION("""COMPUTED_VALUE"""),"P") -> P | AA50: =IFERROR(__xludf.DUMMYFUNCTION("""COMPUTED_VALUE"""),13.0) -> 13 | AB50: =IFERROR(__xludf.DUMMYFUNCTION("""COMPUTED_VALUE"""),"CE") -> CE | AC50: =IFERROR(__xludf.DUMMYFUNCTION("""COMPUTED_VALUE"""),"Sim") -> Sim | AD50: =IFERROR(__xludf.DUMMYFUNCTION("""COMPUTED_VALUE"""),"Ifood") -> Ifood | AM50: =IFERROR(__xludf.DUMMYFUNCTION("""COMPUTED_VALUE"""),"FY27") -> FY27 | AO50: =IFERROR(__xludf.DUMMYFUNCTION("""COMPUTED_VALUE"""),45553.0) -> 45553 | AP50: =IFERROR(__xludf.DUMMYFUNCTION("""COMPUTED_VALUE"""),"AL") -> AL | AQ50: =IFERROR(__xludf.DUMMYFUNCTION("""COMPUTED_VALUE"""),"MARCELO ESTEVES") -> MARCELO ESTEVES | AR50: =IFERROR(__xludf.DUMMYFUNCTION("""COMPUTED_VALUE"""),"ADIEL MATOS") -> ADIEL MATOS | AS50: =IFERROR(__xludf.DUMMYFUNCTION("""COMPUTED_VALUE"""),"THIAGO ROMAGNOLE") -> THIAGO ROMAGNOLE | AT50: =IFERROR(__xludf.DUMMYFUNCTION("""COMPUTED_VALUE"""),"ANDERSON LAUREANO") -> ANDERSON LAUREANO | AU50: =IFERROR(__xludf.DUMMYFUNCTION("""COMPUTED_VALUE"""),0.0) -> 0 | AV50: =IFERROR(__xludf.DUMMYFUNCTION("""COMPUTED_VALUE"""),0.0) -> 0 | AW50: =IFERROR(__xludf.DUMMYFUNCTION("""COMPUTED_VALUE"""),0.0) -> 0 | AX50: =IFERROR(__xludf.DUMMYFUNCTION("""COMPUTED_VALUE"""),0.0) -> 0 | AZ50: =IFERROR(__xludf.DUMMYFUNCTION("""COMPUTED_VALUE"""),"Chinesa") -> Chinesa | BA50: =IFERROR(__xludf.DUMMYFUNCTION("""COMPUTED_VALUE"""),50.0) -> 50 | BB50: =IFERROR(__xludf.DUMMYFUNCTION("""COMPUTED_VALUE"""),"Fast Casual - Multi-conceito") -> Fast Casual - Multi-conceito | BC50: =IFERROR(__xludf.DUMMYFUNCTION("""COMPUTED_VALUE"""),"Regional") -> Regional | BD50: =IFERROR(__xludf.DUMMYFUNCTION("""COMPUTED_VALUE"""),"Dado não disponível - Necessário Discovery") -> Dado não disponível - Necessário Discovery | BE50: =IFERROR(__xludf.DUMMYFUNCTION("""COMPUTED_VALUE"""),65.0) -> 65 | BF50: =IFERROR(__xludf.DUMMYFUNCTION("""COMPUTED_VALUE"""),0.75) -> 0.75 | BG50: =IFERROR(__xludf.DUMMYFUNCTION("""COMPUTED_VALUE"""),"Aderência forte ao 3S: PDV atual não identificado. 3S oferece PDV robusto, KDS integrado e mobilidade (3SGO) para gestão em tempo real - ideal para operações multi-canal.") -> Aderência forte ao 3S: PDV atual não identificado. 3S oferece PDV robusto, KDS integrado e mobilidade (3SGO) para gestão em tempo real - ideal para operações multi-canal. | BH50: Cardápio Web | BI50: 0.5
A51: =IFERROR(__xludf.DUMMYFUNCTION("""COMPUTED_VALUE"""),"CARNEIRO DO ORDONES - CONTA MARCA") -> CARNEIRO DO ORDONES - CONTA MARCA | B51: =IFERROR(__xludf.DUMMYFUNCTION("""COMPUTED_VALUE"""),"João Biagiotti") -> João Biagiotti | C51: =IFERROR(__xludf.DUMMYFUNCTION("""COMPUTED_VALUE"""),"Diego Santos") -> Diego Santos | D51: =IFERROR(__xludf.DUMMYFUNCTION("""COMPUTED_VALUE"""),"0. Não Iniciado") -> 0. Não Iniciado | F51: =IFERROR(__xludf.DUMMYFUNCTION("""COMPUTED_VALUE"""),"P") -> P | AA51: =IFERROR(__xludf.DUMMYFUNCTION("""COMPUTED_VALUE"""),9.0) -> 9 | AB51: =IFERROR(__xludf.DUMMYFUNCTION("""COMPUTED_VALUE"""),"CE") -> CE | AC51: =IFERROR(__xludf.DUMMYFUNCTION("""COMPUTED_VALUE"""),"Sim") -> Sim | AD51: =IFERROR(__xludf.DUMMYFUNCTION("""COMPUTED_VALUE"""),"Ifood") -> Ifood | AM51: =IFERROR(__xludf.DUMMYFUNCTION("""COMPUTED_VALUE"""),"FY27") -> FY27 | AO51: =IFERROR(__xludf.DUMMYFUNCTION("""COMPUTED_VALUE"""),45553.0) -> 45553 | AP51: =IFERROR(__xludf.DUMMYFUNCTION("""COMPUTED_VALUE"""),"CE") -> CE | AQ51: =IFERROR(__xludf.DUMMYFUNCTION("""COMPUTED_VALUE"""),"FABIO MAKARON") -> FABIO MAKARON | AR51: =IFERROR(__xludf.DUMMYFUNCTION("""COMPUTED_VALUE"""),"EVANDRO MENDONCA") -> EVANDRO MENDONCA | AS51: =IFERROR(__xludf.DUMMYFUNCTION("""COMPUTED_VALUE"""),"THIAGO ROMAGNOLE") -> THIAGO ROMAGNOLE | AT51: =IFERROR(__xludf.DUMMYFUNCTION("""COMPUTED_VALUE"""),"EDUARDO VAZ") -> EDUARDO VAZ | AU51: =IFERROR(__xludf.DUMMYFUNCTION("""COMPUTED_VALUE"""),0.0) -> 0 | AV51: =IFERROR(__xludf.DUMMYFUNCTION("""COMPUTED_VALUE"""),0.0) -> 0 | AW51: =IFERROR(__xludf.DUMMYFUNCTION("""COMPUTED_VALUE"""),0.0) -> 0 | AX51: =IFERROR(__xludf.DUMMYFUNCTION("""COMPUTED_VALUE"""),0.0) -> 0 | AY51: =IFERROR(__xludf.DUMMYFUNCTION("""COMPUTED_VALUE"""),"Solução Sistemas") -> Solução Sistemas | AZ51: =IFERROR(__xludf.DUMMYFUNCTION("""COMPUTED_VALUE"""),"Brasileira") -> Brasileira | BA51: =IFERROR(__xludf.DUMMYFUNCTION("""COMPUTED_VALUE"""),75.0) -> 75 | BB51: =IFERROR(__xludf.DUMMYFUNCTION("""COMPUTED_VALUE"""),"Fast Casual - Carneiro/Grelhados") -> Fast Casual - Carneiro/Grelhados | BC51: =IFERROR(__xludf.DUMMYFUNCTION("""COMPUTED_VALUE"""),"Regional") -> Regional | BD51: =IFERROR(__xludf.DUMMYFUNCTION("""COMPUTED_VALUE"""),"Dado não disponível - Necessário Discovery") -> Dado não disponível - Necessário Discovery | BE51: =IFERROR(__xludf.DUMMYFUNCTION("""COMPUTED_VALUE"""),70.0) -> 70 | BF51: =IFERROR(__xludf.DUMMYFUNCTION("""COMPUTED_VALUE"""),0.75) -> 0.75 | BG51: =IFERROR(__xludf.DUMMYFUNCTION("""COMPUTED_VALUE"""),"Aderência forte ao 3S: PDV atual não identificado. 3S oferece PDV robusto, KDS integrado e mobilidade (3SGO) para gestão em tempo real - ideal para operações multi-canal.") -> Aderência forte ao 3S: PDV atual não identificado. 3S oferece PDV robusto, KDS integrado e mobilidade (3SGO) para gestão em tempo real - ideal para operações multi-canal. | BH51: null | BI51: 0.33333333
A52: =IFERROR(__xludf.DUMMYFUNCTION("""COMPUTED_VALUE"""),"CASA DO PARA") -> CASA DO PARA | B52: =IFERROR(__xludf.DUMMYFUNCTION("""COMPUTED_VALUE"""),"João Biagiotti") -> João Biagiotti | C52: =IFERROR(__xludf.DUMMYFUNCTION("""COMPUTED_VALUE"""),"Diego Santos") -> Diego Santos | D52: =IFERROR(__xludf.DUMMYFUNCTION("""COMPUTED_VALUE"""),"2. Primeiro contato com a marca") -> 2. Primeiro contato com a marca | E52: =IFERROR(__xludf.DUMMYFUNCTION("""COMPUTED_VALUE"""),"Delivery - Conciliação agenda com parceiro") -> Delivery - Conciliação agenda com parceiro | F52: =IFERROR(__xludf.DUMMYFUNCTION("""COMPUTED_VALUE"""),"P") -> P | G52: =IFERROR(__xludf.DUMMYFUNCTION("""COMPUTED_VALUE"""),46120.0) -> 46120 | H52: =IFERROR(__xludf.DUMMYFUNCTION("""COMPUTED_VALUE"""),"Conciliando agenda online com o parceiro") -> Conciliando agenda online com o parceiro | I52: =IFERROR(__xludf.DUMMYFUNCTION("""COMPUTED_VALUE"""),46120.599758067125) -> 46120.6 | J52: =IFERROR(__xludf.DUMMYFUNCTION("""COMPUTED_VALUE"""),46120.67216530093) -> 46120.672 | AA52: =IFERROR(__xludf.DUMMYFUNCTION("""COMPUTED_VALUE"""),12.0) -> 12 | AB52: =IFERROR(__xludf.DUMMYFUNCTION("""COMPUTED_VALUE"""),"CE") -> CE | AC52: =IFERROR(__xludf.DUMMYFUNCTION("""COMPUTED_VALUE"""),"Sim") -> Sim | AD52: =IFERROR(__xludf.DUMMYFUNCTION("""COMPUTED_VALUE"""),"Ifood") -> Ifood | AH52: =IFERROR(__xludf.DUMMYFUNCTION("""COMPUTED_VALUE"""),16.0) -> 16 | AI52: =IFERROR(__xludf.DUMMYFUNCTION("""COMPUTED_VALUE"""),"1,2M") -> 1,2M | AJ52: =IFERROR(__xludf.DUMMYFUNCTION("""COMPUTED_VALUE"""),"Menew") -> Menew | AK52: =IFERROR(__xludf.DUMMYFUNCTION("""COMPUTED_VALUE"""),"Salão / Delivery") -> Salão / Delivery | AM52: =IFERROR(__xludf.DUMMYFUNCTION("""COMPUTED_VALUE"""),"FY27") -> FY27 | AO52: =IFERROR(__xludf.DUMMYFUNCTION("""COMPUTED_VALUE"""),95.0) -> 95 | AP52: =IFERROR(__xludf.DUMMYFUNCTION("""COMPUTED_VALUE"""),"PE") -> PE | AQ52: =IFERROR(__xludf.DUMMYFUNCTION("""COMPUTED_VALUE"""),"JENNIFER SIQUEIRA") -> JENNIFER SIQUEIRA | AR52: =IFERROR(__xludf.DUMMYFUNCTION("""COMPUTED_VALUE"""),"TERESA SIMOES") -> TERESA SIMOES | AS52: =IFERROR(__xludf.DUMMYFUNCTION("""COMPUTED_VALUE"""),"THIAGO ROMAGNOLE") -> THIAGO ROMAGNOLE | AT52: =IFERROR(__xludf.DUMMYFUNCTION("""COMPUTED_VALUE"""),"ANDERSON LAUREANO") -> ANDERSON LAUREANO | AU52: =IFERROR(__xludf.DUMMYFUNCTION("""COMPUTED_VALUE"""),0.0) -> 0 | AV52: =IFERROR(__xludf.DUMMYFUNCTION("""COMPUTED_VALUE"""),0.0) -> 0 | AW52: =IFERROR(__xludf.DUMMYFUNCTION("""COMPUTED_VALUE"""),0.0) -> 0 | AX52: =IFERROR(__xludf.DUMMYFUNCTION("""COMPUTED_VALUE"""),0.0) -> 0 | AZ52: =IFERROR(__xludf.DUMMYFUNCTION("""COMPUTED_VALUE"""),"Açaí") -> Açaí | BA52: =IFERROR(__xludf.DUMMYFUNCTION("""COMPUTED_VALUE"""),"") | BB52: =IFERROR(__xludf.DUMMYFUNCTION("""COMPUTED_VALUE"""),"") | BC52: =IFERROR(__xludf.DUMMYFUNCTION("""COMPUTED_VALUE"""),"") | BD52: =IFERROR(__xludf.DUMMYFUNCTION("""COMPUTED_VALUE"""),"") | BE52: =IFERROR(__xludf.DUMMYFUNCTION("""COMPUTED_VALUE"""),"") | BF52: =IFERROR(__xludf.DUMMYFUNCTION("""COMPUTED_VALUE"""),"") | BG52: =IFERROR(__xludf.DUMMYFUNCTION("""COMPUTED_VALUE"""),"") | BH52: null | BI52: 0.5
A53: =IFERROR(__xludf.DUMMYFUNCTION("""COMPUTED_VALUE"""),"CAVENDISH") -> CAVENDISH | B53: =IFERROR(__xludf.DUMMYFUNCTION("""COMPUTED_VALUE"""),"Lídia Esteves") -> Lídia Esteves | C53: =IFERROR(__xludf.DUMMYFUNCTION("""COMPUTED_VALUE"""),"Gabriela Roma") -> Gabriela Roma | D53: =IFERROR(__xludf.DUMMYFUNCTION("""COMPUTED_VALUE"""),"0. Não Iniciado") -> 0. Não Iniciado | F53: =IFERROR(__xludf.DUMMYFUNCTION("""COMPUTED_VALUE"""),"P") -> P | AA53: =IFERROR(__xludf.DUMMYFUNCTION("""COMPUTED_VALUE"""),6.0) -> 6 | AB53: =IFERROR(__xludf.DUMMYFUNCTION("""COMPUTED_VALUE"""),"CE") -> CE | AC53: =IFERROR(__xludf.DUMMYFUNCTION("""COMPUTED_VALUE"""),"Sim") -> Sim | AD53: =IFERROR(__xludf.DUMMYFUNCTION("""COMPUTED_VALUE"""),"Ifood") -> Ifood | AM53: =IFERROR(__xludf.DUMMYFUNCTION("""COMPUTED_VALUE"""),"FY27") -> FY27 | AO53: =IFERROR(__xludf.DUMMYFUNCTION("""COMPUTED_VALUE"""),45553.0) -> 45553 | AP53: =IFERROR(__xludf.DUMMYFUNCTION("""COMPUTED_VALUE"""),"ES") -> ES | AQ53: =IFERROR(__xludf.DUMMYFUNCTION("""COMPUTED_VALUE"""),"LORENA PACHECO") -> LORENA PACHECO | AR53: =IFERROR(__xludf.DUMMYFUNCTION("""COMPUTED_VALUE"""),"JOHANA TRAPUZZANO") -> JOHANA TRAPUZZANO | AS53: =IFERROR(__xludf.DUMMYFUNCTION("""COMPUTED_VALUE"""),"FABIO DONATO") -> FABIO DONATO | AT53: =IFERROR(__xludf.DUMMYFUNCTION("""COMPUTED_VALUE"""),"GILSON JUNIOR") -> GILSON JUNIOR | AU53: =IFERROR(__xludf.DUMMYFUNCTION("""COMPUTED_VALUE"""),0.0) -> 0 | AV53: =IFERROR(__xludf.DUMMYFUNCTION("""COMPUTED_VALUE"""),0.0) -> 0 | AW53: =IFERROR(__xludf.DUMMYFUNCTION("""COMPUTED_VALUE"""),0.0) -> 0 | AX53: =IFERROR(__xludf.DUMMYFUNCTION("""COMPUTED_VALUE"""),0.0) -> 0 | AY53: =IFERROR(__xludf.DUMMYFUNCTION("""COMPUTED_VALUE"""),"Saipos Serviços De Software") -> Saipos Serviços De Software | AZ53: =IFERROR(__xludf.DUMMYFUNCTION("""COMPUTED_VALUE"""),"Lanches") -> Lanches | BA53: =IFERROR(__xludf.DUMMYFUNCTION("""COMPUTED_VALUE"""),42.0) -> 42 | BB53: =IFERROR(__xludf.DUMMYFUNCTION("""COMPUTED_VALUE"""),"Fast Casual - Cafeteria") -> Fast Casual - Cafeteria | BC53: =IFERROR(__xludf.DUMMYFUNCTION("""COMPUTED_VALUE"""),"Regional") -> Regional | BD53: =IFERROR(__xludf.DUMMYFUNCTION("""COMPUTED_VALUE"""),"Dado não disponível - Necessário Discovery") -> Dado não disponível - Necessário Discovery | BE53: =IFERROR(__xludf.DUMMYFUNCTION("""COMPUTED_VALUE"""),65.0) -> 65 | BF53: =IFERROR(__xludf.DUMMYFUNCTION("""COMPUTED_VALUE"""),0.75) -> 0.75 | BG53: =IFERROR(__xludf.DUMMYFUNCTION("""COMPUTED_VALUE"""),"Aderência forte ao 3S: PDV atual não identificado. 3S oferece PDV robusto, KDS integrado e mobilidade (3SGO) para gestão em tempo real - ideal para operações multi-canal.") -> Aderência forte ao 3S: PDV atual não identificado. 3S oferece PDV robusto, KDS integrado e mobilidade (3SGO) para gestão em tempo real - ideal para operações multi-canal. | BH53: Saipos Serviços De Software | BI53: 1
A54: =IFERROR(__xludf.DUMMYFUNCTION("""COMPUTED_VALUE"""),"CELSINHO BH") -> CELSINHO BH | B54: =IFERROR(__xludf.DUMMYFUNCTION("""COMPUTED_VALUE"""),"João Biagiotti") -> João Biagiotti | C54: =IFERROR(__xludf.DUMMYFUNCTION("""COMPUTED_VALUE"""),"Diego Santos") -> Diego Santos | D54: =IFERROR(__xludf.DUMMYFUNCTION("""COMPUTED_VALUE"""),"10. Perdido") -> 10. Perdido | E54: =IFERROR(__xludf.DUMMYFUNCTION("""COMPUTED_VALUE"""),"Perdido - Outro (detalhar ao lado)") -> Perdido - Outro (detalhar ao lado) | F54: =IFERROR(__xludf.DUMMYFUNCTION("""COMPUTED_VALUE"""),"P") -> P | G54: =IFERROR(__xludf.DUMMYFUNCTION("""COMPUTED_VALUE"""),46119.0) -> 46119 | H54: =IFERROR(__xludf.DUMMYFUNCTION("""COMPUTED_VALUE"""),"já está rodando com saipos, não acho que tenha perfil para 3S") -> já está rodando com saipos, não acho que tenha perfil para 3S | I54: =IFERROR(__xludf.DUMMYFUNCTION("""COMPUTED_VALUE"""),46120.460824884256) -> 46120.461 | R54: =IFERROR(__xludf.DUMMYFUNCTION("""COMPUTED_VALUE"""),46129.503641550924) -> 46129.504 | V54: =IFERROR(__xludf.DUMMYFUNCTION("""COMPUTED_VALUE"""),"Sem perfil 3S - Perfil Saipos") -> Sem perfil 3S - Perfil Saipos | AA54: =IFERROR(__xludf.DUMMYFUNCTION("""COMPUTED_VALUE"""),5.0) -> 5 | AB54: =IFERROR(__xludf.DUMMYFUNCTION("""COMPUTED_VALUE"""),"CE") -> CE | AC54: =IFERROR(__xludf.DUMMYFUNCTION("""COMPUTED_VALUE"""),"Sim") -> Sim | AD54: =IFERROR(__xludf.DUMMYFUNCTION("""COMPUTED_VALUE"""),"Ifood") -> Ifood | AM54: =IFERROR(__xludf.DUMMYFUNCTION("""COMPUTED_VALUE"""),"FY27") -> FY27 | AO54: =IFERROR(__xludf.DUMMYFUNCTION("""COMPUTED_VALUE"""),96.0) -> 96 | AP54: =IFERROR(__xludf.DUMMYFUNCTION("""COMPUTED_VALUE"""),"MG") -> MG | AQ54: =IFERROR(__xludf.DUMMYFUNCTION("""COMPUTED_VALUE"""),"EDUARDA HALABI") -> EDUARDA HALABI | AR54: =IFERROR(__xludf.DUMMYFUNCTION("""COMPUTED_VALUE"""),"DIEGO PINTO") -> DIEGO PINTO | AS54: =IFERROR(__xludf.DUMMYFUNCTION("""COMPUTED_VALUE"""),"FABIO DONATO") -> FABIO DONATO | AT54: =IFERROR(__xludf.DUMMYFUNCTION("""COMPUTED_VALUE"""),"GILSON JUNIOR") -> GILSON JUNIOR | AU54: =IFERROR(__xludf.DUMMYFUNCTION("""COMPUTED_VALUE"""),0.0) -> 0 | AV54: =IFERROR(__xludf.DUMMYFUNCTION("""COMPUTED_VALUE"""),0.0) -> 0 | AW54: =IFERROR(__xludf.DUMMYFUNCTION("""COMPUTED_VALUE"""),0.0) -> 0 | AX54: =IFERROR(__xludf.DUMMYFUNCTION("""COMPUTED_VALUE"""),0.0) -> 0 | AZ54: =IFERROR(__xludf.DUMMYFUNCTION("""COMPUTED_VALUE"""),"Brasileira") -> Brasileira | BA54: =IFERROR(__xludf.DUMMYFUNCTION("""COMPUTED_VALUE"""),"") | BB54: =IFERROR(__xludf.DUMMYFUNCTION("""COMPUTED_VALUE"""),"") | BC54: =IFERROR(__xludf.DUMMYFUNCTION("""COMPUTED_VALUE"""),"") | BD54: =IFERROR(__xludf.DUMMYFUNCTION("""COMPUTED_VALUE"""),"") | BE54: =IFERROR(__xludf.DUMMYFUNCTION("""COMPUTED_VALUE"""),"") | BF54: =IFERROR(__xludf.DUMMYFUNCTION("""COMPUTED_VALUE"""),"") | BG54: =IFERROR(__xludf.DUMMYFUNCTION("""COMPUTED_VALUE"""),"") | BH54: Wps Sistemas Ltda | BI54: 0.75
A55: =IFERROR(__xludf.DUMMYFUNCTION("""COMPUTED_VALUE"""),"CHAVITOS HAMBURGUERIA ARTESANAL") -> CHAVITOS HAMBURGUERIA ARTESANAL | B55: =IFERROR(__xludf.DUMMYFUNCTION("""COMPUTED_VALUE"""),"Lídia Esteves") -> Lídia Esteves | C55: =IFERROR(__xludf.DUMMYFUNCTION("""COMPUTED_VALUE"""),"Gabriela Roma") -> Gabriela Roma | D55: =IFERROR(__xludf.DUMMYFUNCTION("""COMPUTED_VALUE"""),"1. Iniciado") -> 1. Iniciado | E55: =IFERROR(__xludf.DUMMYFUNCTION("""COMPUTED_VALUE"""),"Delivery - Aguardando retorno / Conciliação agenda") -> Delivery - Aguardando retorno / Conciliação agenda | F55: =IFERROR(__xludf.DUMMYFUNCTION("""COMPUTED_VALUE"""),"P") -> P | I55: =IFERROR(__xludf.DUMMYFUNCTION("""COMPUTED_VALUE"""),46121.67421900463) -> 46121.674 | AA55: =IFERROR(__xludf.DUMMYFUNCTION("""COMPUTED_VALUE"""),6.0) -> 6 | AB55: =IFERROR(__xludf.DUMMYFUNCTION("""COMPUTED_VALUE"""),"CE") -> CE | AC55: =IFERROR(__xludf.DUMMYFUNCTION("""COMPUTED_VALUE"""),"Sim") -> Sim | AD55: =IFERROR(__xludf.DUMMYFUNCTION("""COMPUTED_VALUE"""),"Ifood") -> Ifood | AM55: =IFERROR(__xludf.DUMMYFUNCTION("""COMPUTED_VALUE"""),"FY27") -> FY27 | AO55: =IFERROR(__xludf.DUMMYFUNCTION("""COMPUTED_VALUE"""),45553.0) -> 45553 | AP55: =IFERROR(__xludf.DUMMYFUNCTION("""COMPUTED_VALUE"""),"SP") -> SP | AQ55: =IFERROR(__xludf.DUMMYFUNCTION("""COMPUTED_VALUE"""),"ISADORA GARCIA") -> ISADORA GARCIA | AR55: =IFERROR(__xludf.DUMMYFUNCTION("""COMPUTED_VALUE"""),"FELIPE ABEZERRA") -> FELIPE ABEZERRA | AS55: =IFERROR(__xludf.DUMMYFUNCTION("""COMPUTED_VALUE"""),"NATHALIE MERTENS") -> NATHALIE MERTENS | AT55: =IFERROR(__xludf.DUMMYFUNCTION("""COMPUTED_VALUE"""),"MATHEUS LESSA") -> MATHEUS LESSA | AU55: =IFERROR(__xludf.DUMMYFUNCTION("""COMPUTED_VALUE"""),0.0) -> 0 | AV55: =IFERROR(__xludf.DUMMYFUNCTION("""COMPUTED_VALUE"""),0.0) -> 0 | AW55: =IFERROR(__xludf.DUMMYFUNCTION("""COMPUTED_VALUE"""),0.0) -> 0 | AX55: =IFERROR(__xludf.DUMMYFUNCTION("""COMPUTED_VALUE"""),0.0) -> 0 | AZ55: =IFERROR(__xludf.DUMMYFUNCTION("""COMPUTED_VALUE"""),"Lanches") -> Lanches | BA55: =IFERROR(__xludf.DUMMYFUNCTION("""COMPUTED_VALUE"""),65.0) -> 65 | BB55: =IFERROR(__xludf.DUMMYFUNCTION("""COMPUTED_VALUE"""),"Fast Casual - Hamburgueria Artesanal") -> Fast Casual - Hamburgueria Artesanal | BC55: =IFERROR(__xludf.DUMMYFUNCTION("""COMPUTED_VALUE"""),"Regional") -> Regional | BD55: =IFERROR(__xludf.DUMMYFUNCTION("""COMPUTED_VALUE"""),"Dado não disponível - Necessário Discovery") -> Dado não disponível - Necessário Discovery | BE55: =IFERROR(__xludf.DUMMYFUNCTION("""COMPUTED_VALUE"""),65.0) -> 65 | BF55: =IFERROR(__xludf.DUMMYFUNCTION("""COMPUTED_VALUE"""),0.75) -> 0.75 | BG55: =IFERROR(__xludf.DUMMYFUNCTION("""COMPUTED_VALUE"""),"Aderência forte ao 3S: PDV atual não identificado. 3S oferece PDV robusto, KDS integrado e mobilidade (3SGO) para gestão em tempo real - ideal para operações multi-canal.") -> Aderência forte ao 3S: PDV atual não identificado. 3S oferece PDV robusto, KDS integrado e mobilidade (3SGO) para gestão em tempo real - ideal para operações multi-canal.
A56: =IFERROR(__xludf.DUMMYFUNCTION("""COMPUTED_VALUE"""),"CHICKEN TOWN") -> CHICKEN TOWN | B56: =IFERROR(__xludf.DUMMYFUNCTION("""COMPUTED_VALUE"""),"Lídia Esteves") -> Lídia Esteves | C56: =IFERROR(__xludf.DUMMYFUNCTION("""COMPUTED_VALUE"""),"Gabriela Roma") -> Gabriela Roma | D56: =IFERROR(__xludf.DUMMYFUNCTION("""COMPUTED_VALUE"""),"1. Iniciado") -> 1. Iniciado | E56: =IFERROR(__xludf.DUMMYFUNCTION("""COMPUTED_VALUE"""),"Delivery - Aguardando retorno / Conciliação agenda") -> Delivery - Aguardando retorno / Conciliação agenda | F56: =IFERROR(__xludf.DUMMYFUNCTION("""COMPUTED_VALUE"""),"P") -> P | I56: =IFERROR(__xludf.DUMMYFUNCTION("""COMPUTED_VALUE"""),46121.67413471064) -> 46121.674 | AA56: =IFERROR(__xludf.DUMMYFUNCTION("""COMPUTED_VALUE"""),1.0) -> 1 | AB56: =IFERROR(__xludf.DUMMYFUNCTION("""COMPUTED_VALUE"""),"CE") -> CE | AC56: =IFERROR(__xludf.DUMMYFUNCTION("""COMPUTED_VALUE"""),"Sim") -> Sim | AD56: =IFERROR(__xludf.DUMMYFUNCTION("""COMPUTED_VALUE"""),"Ifood") -> Ifood | AM56: =IFERROR(__xludf.DUMMYFUNCTION("""COMPUTED_VALUE"""),"FY27") -> FY27 | AO56: =IFERROR(__xludf.DUMMYFUNCTION("""COMPUTED_VALUE"""),45553.0) -> 45553 | AP56: =IFERROR(__xludf.DUMMYFUNCTION("""COMPUTED_VALUE"""),"SP") -> SP | AQ56: =IFERROR(__xludf.DUMMYFUNCTION("""COMPUTED_VALUE"""),"ISADORA GARCIA") -> ISADORA GARCIA | AR56: =IFERROR(__xludf.DUMMYFUNCTION("""COMPUTED_VALUE"""),"GUSTAVO THOMPSON") -> GUSTAVO THOMPSON | AS56: =IFERROR(__xludf.DUMMYFUNCTION("""COMPUTED_VALUE"""),"NATHALIE MERTENS") -> NATHALIE MERTENS | AT56: =IFERROR(__xludf.DUMMYFUNCTION("""COMPUTED_VALUE"""),"MATHEUS LESSA") -> MATHEUS LESSA | AU56: =IFERROR(__xludf.DUMMYFUNCTION("""COMPUTED_VALUE"""),0.0) -> 0 | AV56: =IFERROR(__xludf.DUMMYFUNCTION("""COMPUTED_VALUE"""),0.0) -> 0 | AW56: =IFERROR(__xludf.DUMMYFUNCTION("""COMPUTED_VALUE"""),0.0) -> 0 | AX56: =IFERROR(__xludf.DUMMYFUNCTION("""COMPUTED_VALUE"""),0.0) -> 0 | AZ56: =IFERROR(__xludf.DUMMYFUNCTION("""COMPUTED_VALUE"""),"Lanches") -> Lanches | BA56: =IFERROR(__xludf.DUMMYFUNCTION("""COMPUTED_VALUE"""),45.0) -> 45 | BB56: =IFERROR(__xludf.DUMMYFUNCTION("""COMPUTED_VALUE"""),"QSR - Frango Frito") -> QSR - Frango Frito | BC56: =IFERROR(__xludf.DUMMYFUNCTION("""COMPUTED_VALUE"""),"Regional") -> Regional | BD56: =IFERROR(__xludf.DUMMYFUNCTION("""COMPUTED_VALUE"""),"Dado não disponível - Necessário Discovery") -> Dado não disponível - Necessário Discovery | BE56: =IFERROR(__xludf.DUMMYFUNCTION("""COMPUTED_VALUE"""),70.0) -> 70 | BF56: =IFERROR(__xludf.DUMMYFUNCTION("""COMPUTED_VALUE"""),0.85) -> 0.85 | BG56: =IFERROR(__xludf.DUMMYFUNCTION("""COMPUTED_VALUE"""),"Alta aderência ao 3S: PDV atual não identificado. 3S oferece Kiosk nativo, Hub Delivery integrado e gestão centralizada multi-loja - diferenciais competitivos para expansão e redução de filas.") -> Alta aderência ao 3S: PDV atual não identificado. 3S oferece Kiosk nativo, Hub Delivery integrado e gestão centralizada multi-loja - diferenciais competitivos para expansão e redução de filas. | BH56: null | BI56: 0.72727273
A57: =IFERROR(__xludf.DUMMYFUNCTION("""COMPUTED_VALUE"""),"CHILI BURGER HAMBURGUERIA ARTESANAL") -> CHILI BURGER HAMBURGUERIA ARTESANAL | B57: =IFERROR(__xludf.DUMMYFUNCTION("""COMPUTED_VALUE"""),"João Biagiotti") -> João Biagiotti | C57: =IFERROR(__xludf.DUMMYFUNCTION("""COMPUTED_VALUE"""),"Diego Santos") -> Diego Santos | D57: =IFERROR(__xludf.DUMMYFUNCTION("""COMPUTED_VALUE"""),"0. Não Iniciado") -> 0. Não Iniciado | F57: =IFERROR(__xludf.DUMMYFUNCTION("""COMPUTED_VALUE"""),"P") -> P | AA57: =IFERROR(__xludf.DUMMYFUNCTION("""COMPUTED_VALUE"""),10.0) -> 10 | AB57: =IFERROR(__xludf.DUMMYFUNCTION("""COMPUTED_VALUE"""),"CE") -> CE | AC57: =IFERROR(__xludf.DUMMYFUNCTION("""COMPUTED_VALUE"""),"Sim") -> Sim | AD57: =IFERROR(__xludf.DUMMYFUNCTION("""COMPUTED_VALUE"""),0.0) -> 0 | AM57: =IFERROR(__xludf.DUMMYFUNCTION("""COMPUTED_VALUE"""),"FY27") -> FY27 | AO57: =IFERROR(__xludf.DUMMYFUNCTION("""COMPUTED_VALUE"""),45553.0) -> 45553 | AP57: =IFERROR(__xludf.DUMMYFUNCTION("""COMPUTED_VALUE"""),0.0) -> 0 | AQ57: =IFERROR(__xludf.DUMMYFUNCTION("""COMPUTED_VALUE"""),0.0) -> 0 | AR57: =IFERROR(__xludf.DUMMYFUNCTION("""COMPUTED_VALUE"""),0.0) -> 0 | AS57: =IFERROR(__xludf.DUMMYFUNCTION("""COMPUTED_VALUE"""),0.0) -> 0 | AT57: =IFERROR(__xludf.DUMMYFUNCTION("""COMPUTED_VALUE"""),0.0) -> 0 | AU57: =IFERROR(__xludf.DUMMYFUNCTION("""COMPUTED_VALUE"""),0.0) -> 0 | AV57: =IFERROR(__xludf.DUMMYFUNCTION("""COMPUTED_VALUE"""),0.0) -> 0 | AW57: =IFERROR(__xludf.DUMMYFUNCTION("""COMPUTED_VALUE"""),0.0) -> 0 | AX57: =IFERROR(__xludf.DUMMYFUNCTION("""COMPUTED_VALUE"""),0.0) -> 0 | AY57: =IFERROR(__xludf.DUMMYFUNCTION("""COMPUTED_VALUE"""),"Expresso Delivery") -> Expresso Delivery | AZ57: =IFERROR(__xludf.DUMMYFUNCTION("""COMPUTED_VALUE"""),"NA") -> NA | BA57: =IFERROR(__xludf.DUMMYFUNCTION("""COMPUTED_VALUE"""),74.0) -> 74 | BB57: =IFERROR(__xludf.DUMMYFUNCTION("""COMPUTED_VALUE"""),"Fast Casual - Hamburgueria") -> Fast Casual - Hamburgueria | BC57: =IFERROR(__xludf.DUMMYFUNCTION("""COMPUTED_VALUE"""),"Sul") -> Sul | BD57: =IFERROR(__xludf.DUMMYFUNCTION("""COMPUTED_VALUE"""),"Dado não disponível publicamente - Necessário Discovery") -> Dado não disponível publicamente - Necessário Discovery | BE57: =IFERROR(__xludf.DUMMYFUNCTION("""COMPUTED_VALUE"""),70.0) -> 70 | BF57: =IFERROR(__xludf.DUMMYFUNCTION("""COMPUTED_VALUE"""),0.75) -> 0.75 | BG57: =IFERROR(__xludf.DUMMYFUNCTION("""COMPUTED_VALUE"""),"Aderência forte ao 3S: PDV atual não identificado. 3S oferece PDV robusto, KDS integrado e mobilidade (3SGO) para gestão em tempo real - ideal para operações multi-canal.") -> Aderência forte ao 3S: PDV atual não identificado. 3S oferece PDV robusto, KDS integrado e mobilidade (3SGO) para gestão em tempo real - ideal para operações multi-canal. | BH57: null | BI57: 1
A58: =IFERROR(__xludf.DUMMYFUNCTION("""COMPUTED_VALUE"""),"CHOPP DA FABRICA") -> CHOPP DA FABRICA | B58: =IFERROR(__xludf.DUMMYFUNCTION("""COMPUTED_VALUE"""),"João Biagiotti") -> João Biagiotti | C58: =IFERROR(__xludf.DUMMYFUNCTION("""COMPUTED_VALUE"""),"Diego Santos") -> Diego Santos | D58: =IFERROR(__xludf.DUMMYFUNCTION("""COMPUTED_VALUE"""),"1. Iniciado") -> 1. Iniciado | E58: =IFERROR(__xludf.DUMMYFUNCTION("""COMPUTED_VALUE"""),"Delivery - Conciliação agenda com parceiro") -> Delivery - Conciliação agenda com parceiro | F58: =IFERROR(__xludf.DUMMYFUNCTION("""COMPUTED_VALUE"""),"P") -> P | G58: =IFERROR(__xludf.DUMMYFUNCTION("""COMPUTED_VALUE"""),46125.0) -> 46125 | H58: =IFERROR(__xludf.DUMMYFUNCTION("""COMPUTED_VALUE"""),"Time de delivery ofertou SAIPOS mas 3S faz sentido, aguardando conciliação de agenda") -> Time de delivery ofertou SAIPOS mas 3S faz sentido, aguardando conciliação de agenda | I58: =IFERROR(__xludf.DUMMYFUNCTION("""COMPUTED_VALUE"""),46125.58500554398) -> 46125.585 | AA58: =IFERROR(__xludf.DUMMYFUNCTION("""COMPUTED_VALUE"""),5.0) -> 5 | AB58: =IFERROR(__xludf.DUMMYFUNCTION("""COMPUTED_VALUE"""),"CE") -> CE | AC58: =IFERROR(__xludf.DUMMYFUNCTION("""COMPUTED_VALUE"""),"Sim") -> Sim | AD58: =IFERROR(__xludf.DUMMYFUNCTION("""COMPUTED_VALUE"""),"Ifood") -> Ifood | AH58: =IFERROR(__xludf.DUMMYFUNCTION("""COMPUTED_VALUE"""),5.0) -> 5 | AJ58: =IFERROR(__xludf.DUMMYFUNCTION("""COMPUTED_VALUE"""),"SAIPOS") -> SAIPOS | AK58: =IFERROR(__xludf.DUMMYFUNCTION("""COMPUTED_VALUE"""),"Salão / Delivery") -> Salão / Delivery | AL58: =IFERROR(__xludf.DUMMYFUNCTION("""COMPUTED_VALUE"""),"Sim") -> Sim | AM58: =IFERROR(__xludf.DUMMYFUNCTION("""COMPUTED_VALUE"""),"FY27") -> FY27 | AO58: =IFERROR(__xludf.DUMMYFUNCTION("""COMPUTED_VALUE"""),90.0) -> 90 | AP58: =IFERROR(__xludf.DUMMYFUNCTION("""COMPUTED_VALUE"""),"MG") -> MG | AQ58: =IFERROR(__xludf.DUMMYFUNCTION("""COMPUTED_VALUE"""),"JOAO BAR") -> JOAO BAR | AR58: =IFERROR(__xludf.DUMMYFUNCTION("""COMPUTED_VALUE"""),"ARTHUR TAVARES") -> ARTHUR TAVARES | AS58: =IFERROR(__xludf.DUMMYFUNCTION("""COMPUTED_VALUE"""),"FABIO DONATO") -> FABIO DONATO | AT58: =IFERROR(__xludf.DUMMYFUNCTION("""COMPUTED_VALUE"""),"GILSON JUNIOR") -> GILSON JUNIOR | AU58: =IFERROR(__xludf.DUMMYFUNCTION("""COMPUTED_VALUE"""),0.0) -> 0 | AV58: =IFERROR(__xludf.DUMMYFUNCTION("""COMPUTED_VALUE"""),0.0) -> 0 | AW58: =IFERROR(__xludf.DUMMYFUNCTION("""COMPUTED_VALUE"""),0.0) -> 0 | AX58: =IFERROR(__xludf.DUMMYFUNCTION("""COMPUTED_VALUE"""),0.0) -> 0 | AY58: =IFERROR(__xludf.DUMMYFUNCTION("""COMPUTED_VALUE"""),"Teknisa Service Ltda") -> Teknisa Service Ltda | AZ58: =IFERROR(__xludf.DUMMYFUNCTION("""COMPUTED_VALUE"""),"Brasileira") -> Brasileira | BA58: =IFERROR(__xludf.DUMMYFUNCTION("""COMPUTED_VALUE"""),"") | BB58: =IFERROR(__xludf.DUMMYFUNCTION("""COMPUTED_VALUE"""),"") | BC58: =IFERROR(__xludf.DUMMYFUNCTION("""COMPUTED_VALUE"""),"") | BD58: =IFERROR(__xludf.DUMMYFUNCTION("""COMPUTED_VALUE"""),"") | BE58: =IFERROR(__xludf.DUMMYFUNCTION("""COMPUTED_VALUE"""),"") | BF58: =IFERROR(__xludf.DUMMYFUNCTION("""COMPUTED_VALUE"""),"") | BG58: =IFERROR(__xludf.DUMMYFUNCTION("""COMPUTED_VALUE"""),"") | BH58: Teknisa Service Ltda | BI58: 0.66666667
A59: =IFERROR(__xludf.DUMMYFUNCTION("""COMPUTED_VALUE"""),"COME ON BURGER") -> COME ON BURGER | B59: =IFERROR(__xludf.DUMMYFUNCTION("""COMPUTED_VALUE"""),"Lídia Esteves") -> Lídia Esteves | C59: =IFERROR(__xludf.DUMMYFUNCTION("""COMPUTED_VALUE"""),"Gabriela Roma") -> Gabriela Roma | D59: =IFERROR(__xludf.DUMMYFUNCTION("""COMPUTED_VALUE"""),"0. Não Iniciado") -> 0. Não Iniciado | F59: =IFERROR(__xludf.DUMMYFUNCTION("""COMPUTED_VALUE"""),"P") -> P | AA59: =IFERROR(__xludf.DUMMYFUNCTION("""COMPUTED_VALUE"""),5.0) -> 5 | AB59: =IFERROR(__xludf.DUMMYFUNCTION("""COMPUTED_VALUE"""),"CE") -> CE | AC59: =IFERROR(__xludf.DUMMYFUNCTION("""COMPUTED_VALUE"""),"Sim") -> Sim | AD59: =IFERROR(__xludf.DUMMYFUNCTION("""COMPUTED_VALUE"""),"Ifood") -> Ifood | AM59: =IFERROR(__xludf.DUMMYFUNCTION("""COMPUTED_VALUE"""),"FY27") -> FY27 | AO59: =IFERROR(__xludf.DUMMYFUNCTION("""COMPUTED_VALUE"""),45553.0) -> 45553 | AP59: =IFERROR(__xludf.DUMMYFUNCTION("""COMPUTED_VALUE"""),"SP") -> SP | AQ59: =IFERROR(__xludf.DUMMYFUNCTION("""COMPUTED_VALUE"""),"ISADORA GARCIA") -> ISADORA GARCIA | AR59: =IFERROR(__xludf.DUMMYFUNCTION("""COMPUTED_VALUE"""),"CARLA ARAUJO") -> CARLA ARAUJO | AS59: =IFERROR(__xludf.DUMMYFUNCTION("""COMPUTED_VALUE"""),"NATHALIE MERTENS") -> NATHALIE MERTENS | AT59: =IFERROR(__xludf.DUMMYFUNCTION("""COMPUTED_VALUE"""),"MATHEUS LESSA") -> MATHEUS LESSA | AU59: =IFERROR(__xludf.DUMMYFUNCTION("""COMPUTED_VALUE"""),0.0) -> 0 | AV59: =IFERROR(__xludf.DUMMYFUNCTION("""COMPUTED_VALUE"""),0.0) -> 0 | AW59: =IFERROR(__xludf.DUMMYFUNCTION("""COMPUTED_VALUE"""),0.0) -> 0 | AX59: =IFERROR(__xludf.DUMMYFUNCTION("""COMPUTED_VALUE"""),0.0) -> 0 | AZ59: =IFERROR(__xludf.DUMMYFUNCTION("""COMPUTED_VALUE"""),"Lanches") -> Lanches | BA59: =IFERROR(__xludf.DUMMYFUNCTION("""COMPUTED_VALUE"""),66.0) -> 66 | BB59: =IFERROR(__xludf.DUMMYFUNCTION("""COMPUTED_VALUE"""),"Fast Casual - Hamburgueria") -> Fast Casual - Hamburgueria | BC59: =IFERROR(__xludf.DUMMYFUNCTION("""COMPUTED_VALUE"""),"Regional") -> Regional | BD59: =IFERROR(__xludf.DUMMYFUNCTION("""COMPUTED_VALUE"""),"Dado não disponível publicamente - Necessário Discovery") -> Dado não disponível publicamente - Necessário Discovery | BE59: =IFERROR(__xludf.DUMMYFUNCTION("""COMPUTED_VALUE"""),70.0) -> 70 | BF59: =IFERROR(__xludf.DUMMYFUNCTION("""COMPUTED_VALUE"""),0.8) -> 0.8 | BG59: =IFERROR(__xludf.DUMMYFUNCTION("""COMPUTED_VALUE"""),"Alta aderência ao 3S: PDV atual não identificado. 3S oferece Kiosk nativo, Hub Delivery integrado e gestão centralizada multi-loja - diferenciais competitivos para expansão e redução de filas.") -> Alta aderência ao 3S: PDV atual não identificado. 3S oferece Kiosk nativo, Hub Delivery integrado e gestão centralizada multi-loja - diferenciais competitivos para expansão e redução de filas.
A60: =IFERROR(__xludf.DUMMYFUNCTION("""COMPUTED_VALUE"""),"CONECTA KITCHEN") -> CONECTA KITCHEN | B60: =IFERROR(__xludf.DUMMYFUNCTION("""COMPUTED_VALUE"""),"João Biagiotti") -> João Biagiotti | C60: =IFERROR(__xludf.DUMMYFUNCTION("""COMPUTED_VALUE"""),"Diego Santos") -> Diego Santos | D60: =IFERROR(__xludf.DUMMYFUNCTION("""COMPUTED_VALUE"""),"0. Não Iniciado") -> 0. Não Iniciado | F60: =IFERROR(__xludf.DUMMYFUNCTION("""COMPUTED_VALUE"""),"P") -> P | AA60: =IFERROR(__xludf.DUMMYFUNCTION("""COMPUTED_VALUE"""),10.0) -> 10 | AB60: =IFERROR(__xludf.DUMMYFUNCTION("""COMPUTED_VALUE"""),"CE") -> CE | AC60: =IFERROR(__xludf.DUMMYFUNCTION("""COMPUTED_VALUE"""),"Sim") -> Sim | AD60: =IFERROR(__xludf.DUMMYFUNCTION("""COMPUTED_VALUE"""),"Ifood") -> Ifood | AM60: =IFERROR(__xludf.DUMMYFUNCTION("""COMPUTED_VALUE"""),"FY27") -> FY27 | AO60: =IFERROR(__xludf.DUMMYFUNCTION("""COMPUTED_VALUE"""),45553.0) -> 45553 | AP60: =IFERROR(__xludf.DUMMYFUNCTION("""COMPUTED_VALUE"""),"PE") -> PE | AQ60: =IFERROR(__xludf.DUMMYFUNCTION("""COMPUTED_VALUE"""),"JENNIFER SIQUEIRA") -> JENNIFER SIQUEIRA | AR60: =IFERROR(__xludf.DUMMYFUNCTION("""COMPUTED_VALUE"""),"NEYDAIANE VIEIRA") -> NEYDAIANE VIEIRA | AS60: =IFERROR(__xludf.DUMMYFUNCTION("""COMPUTED_VALUE"""),"THIAGO ROMAGNOLE") -> THIAGO ROMAGNOLE | AT60: =IFERROR(__xludf.DUMMYFUNCTION("""COMPUTED_VALUE"""),"ANDERSON LAUREANO") -> ANDERSON LAUREANO | AU60: =IFERROR(__xludf.DUMMYFUNCTION("""COMPUTED_VALUE"""),0.0) -> 0 | AV60: =IFERROR(__xludf.DUMMYFUNCTION("""COMPUTED_VALUE"""),0.0) -> 0 | AW60: =IFERROR(__xludf.DUMMYFUNCTION("""COMPUTED_VALUE"""),0.0) -> 0 | AX60: =IFERROR(__xludf.DUMMYFUNCTION("""COMPUTED_VALUE"""),0.0) -> 0 | AY60: =IFERROR(__xludf.DUMMYFUNCTION("""COMPUTED_VALUE"""),"Saipos Serviços De Software") -> Saipos Serviços De Software | AZ60: =IFERROR(__xludf.DUMMYFUNCTION("""COMPUTED_VALUE"""),"Saudável") -> Saudável | BA60: =IFERROR(__xludf.DUMMYFUNCTION("""COMPUTED_VALUE"""),66.0) -> 66 | BB60: =IFERROR(__xludf.DUMMYFUNCTION("""COMPUTED_VALUE"""),"Fast Casual - Multi-conceito") -> Fast Casual - Multi-conceito | BC60: =IFERROR(__xludf.DUMMYFUNCTION("""COMPUTED_VALUE"""),"Brasília/DF") -> Brasília/DF | BD60: =IFERROR(__xludf.DUMMYFUNCTION("""COMPUTED_VALUE"""),"Dado não disponível publicamente - Necessário Discovery") -> Dado não disponível publicamente - Necessário Discovery | BE60: =IFERROR(__xludf.DUMMYFUNCTION("""COMPUTED_VALUE"""),65.0) -> 65 | BF60: =IFERROR(__xludf.DUMMYFUNCTION("""COMPUTED_VALUE"""),0.75) -> 0.75 | BG60: =IFERROR(__xludf.DUMMYFUNCTION("""COMPUTED_VALUE"""),"Aderência forte ao 3S: PDV atual não identificado. 3S oferece PDV robusto, KDS integrado e mobilidade (3SGO) para gestão em tempo real - ideal para operações multi-canal.") -> Aderência forte ao 3S: PDV atual não identificado. 3S oferece PDV robusto, KDS integrado e mobilidade (3SGO) para gestão em tempo real - ideal para operações multi-canal. | BH60: Saipos Serviços De Software | BI60: 0.5
A61: =IFERROR(__xludf.DUMMYFUNCTION("""COMPUTED_VALUE"""),"COOKIE DELIVERY OFICIAL") -> COOKIE DELIVERY OFICIAL | B61: =IFERROR(__xludf.DUMMYFUNCTION("""COMPUTED_VALUE"""),"João Biagiotti") -> João Biagiotti | C61: =IFERROR(__xludf.DUMMYFUNCTION("""COMPUTED_VALUE"""),"Diego Santos") -> Diego Santos | D61: =IFERROR(__xludf.DUMMYFUNCTION("""COMPUTED_VALUE"""),"1. Iniciado") -> 1. Iniciado | E61: =IFERROR(__xludf.DUMMYFUNCTION("""COMPUTED_VALUE"""),"Delivery - Aguardando retorno executivo") -> Delivery - Aguardando retorno executivo | F61: =IFERROR(__xludf.DUMMYFUNCTION("""COMPUTED_VALUE"""),"P") -> P | G61: =IFERROR(__xludf.DUMMYFUNCTION("""COMPUTED_VALUE"""),46153.0) -> 46153 | H61: =IFERROR(__xludf.DUMMYFUNCTION("""COMPUTED_VALUE"""),"Foi enviado mensagem para o executivo, aguardando retorno") -> Foi enviado mensagem para o executivo, aguardando retorno | I61: =IFERROR(__xludf.DUMMYFUNCTION("""COMPUTED_VALUE"""),46153.38236001157) -> 46153.382 | AA61: =IFERROR(__xludf.DUMMYFUNCTION("""COMPUTED_VALUE"""),10.0) -> 10 | AB61: =IFERROR(__xludf.DUMMYFUNCTION("""COMPUTED_VALUE"""),"CE") -> CE | AC61: =IFERROR(__xludf.DUMMYFUNCTION("""COMPUTED_VALUE"""),"Sim") -> Sim | AD61: =IFERROR(__xludf.DUMMYFUNCTION("""COMPUTED_VALUE"""),"Ifood") -> Ifood | AM61: =IFERROR(__xludf.DUMMYFUNCTION("""COMPUTED_VALUE"""),"FY27") -> FY27 | AO61: =IFERROR(__xludf.DUMMYFUNCTION("""COMPUTED_VALUE"""),62.0) -> 62 | AP61: =IFERROR(__xludf.DUMMYFUNCTION("""COMPUTED_VALUE"""),"SP") -> SP | AQ61: =IFERROR(__xludf.DUMMYFUNCTION("""COMPUTED_VALUE"""),"RAQUEL BATISTA") -> RAQUEL BATISTA | AR61: =IFERROR(__xludf.DUMMYFUNCTION("""COMPUTED_VALUE"""),"RENAN BELIZARE") -> RENAN BELIZARE | AS61: =IFERROR(__xludf.DUMMYFUNCTION("""COMPUTED_VALUE"""),"THIAGO ROMAGNOLE") -> THIAGO ROMAGNOLE | AT61: =IFERROR(__xludf.DUMMYFUNCTION("""COMPUTED_VALUE"""),"BRUNA TASSINARI") -> BRUNA TASSINARI | AU61: =IFERROR(__xludf.DUMMYFUNCTION("""COMPUTED_VALUE"""),0.0) -> 0 | AV61: =IFERROR(__xludf.DUMMYFUNCTION("""COMPUTED_VALUE"""),0.0) -> 0 | AW61: =IFERROR(__xludf.DUMMYFUNCTION("""COMPUTED_VALUE"""),0.0) -> 0 | AX61: =IFERROR(__xludf.DUMMYFUNCTION("""COMPUTED_VALUE"""),0.0) -> 0 | AZ61: =IFERROR(__xludf.DUMMYFUNCTION("""COMPUTED_VALUE"""),"Doces & Bolos") -> Doces & Bolos | BA61: =IFERROR(__xludf.DUMMYFUNCTION("""COMPUTED_VALUE"""),44.0) -> 44 | BB61: =IFERROR(__xludf.DUMMYFUNCTION("""COMPUTED_VALUE"""),"Varejo - Confeitaria") -> Varejo - Confeitaria | BC61: =IFERROR(__xludf.DUMMYFUNCTION("""COMPUTED_VALUE"""),"Regional") -> Regional | BD61: =IFERROR(__xludf.DUMMYFUNCTION("""COMPUTED_VALUE"""),"Dado não disponível publicamente - Necessário Discovery") -> Dado não disponível publicamente - Necessário Discovery | BE61: =IFERROR(__xludf.DUMMYFUNCTION("""COMPUTED_VALUE"""),35.0) -> 35 | BF61: =IFERROR(__xludf.DUMMYFUNCTION("""COMPUTED_VALUE"""),0.5) -> 0.5 | BG61: =IFERROR(__xludf.DUMMYFUNCTION("""COMPUTED_VALUE"""),"Aderência moderada ao 3S: PDV atual não identificado. 3S pode agregar valor com padronização multi-loja e integração delivery, mas necessário Discovery para validar fit completo.") -> Aderência moderada ao 3S: PDV atual não identificado. 3S pode agregar valor com padronização multi-loja e integração delivery, mas necessário Discovery para validar fit completo. | BH61: Netcontroll Xmenu | BI61: 0.36363636
A62: =IFERROR(__xludf.DUMMYFUNCTION("""COMPUTED_VALUE"""),"COOKIE MANIA") -> COOKIE MANIA | B62: =IFERROR(__xludf.DUMMYFUNCTION("""COMPUTED_VALUE"""),"João Biagiotti") -> João Biagiotti | C62: =IFERROR(__xludf.DUMMYFUNCTION("""COMPUTED_VALUE"""),"Diego Santos") -> Diego Santos | D62: =IFERROR(__xludf.DUMMYFUNCTION("""COMPUTED_VALUE"""),"0. Não Iniciado") -> 0. Não Iniciado | F62: =IFERROR(__xludf.DUMMYFUNCTION("""COMPUTED_VALUE"""),"P") -> P | AA62: =IFERROR(__xludf.DUMMYFUNCTION("""COMPUTED_VALUE"""),14.0) -> 14 | AB62: =IFERROR(__xludf.DUMMYFUNCTION("""COMPUTED_VALUE"""),"CE") -> CE | AC62: =IFERROR(__xludf.DUMMYFUNCTION("""COMPUTED_VALUE"""),"Sim") -> Sim | AD62: =IFERROR(__xludf.DUMMYFUNCTION("""COMPUTED_VALUE"""),0.0) -> 0 | AM62: =IFERROR(__xludf.DUMMYFUNCTION("""COMPUTED_VALUE"""),"FY27") -> FY27 | AO62: =IFERROR(__xludf.DUMMYFUNCTION("""COMPUTED_VALUE"""),45553.0) -> 45553 | AP62: =IFERROR(__xludf.DUMMYFUNCTION("""COMPUTED_VALUE"""),"CE") -> CE | AQ62: =IFERROR(__xludf.DUMMYFUNCTION("""COMPUTED_VALUE"""),"FABIO MAKARON") -> FABIO MAKARON | AR62: =IFERROR(__xludf.DUMMYFUNCTION("""COMPUTED_VALUE"""),"RAUL OLIVEIRA") -> RAUL OLIVEIRA | AS62: =IFERROR(__xludf.DUMMYFUNCTION("""COMPUTED_VALUE"""),"THIAGO ROMAGNOLE") -> THIAGO ROMAGNOLE | AT62: =IFERROR(__xludf.DUMMYFUNCTION("""COMPUTED_VALUE"""),"EDUARDO VAZ") -> EDUARDO VAZ | AU62: =IFERROR(__xludf.DUMMYFUNCTION("""COMPUTED_VALUE"""),0.0) -> 0 | AV62: =IFERROR(__xludf.DUMMYFUNCTION("""COMPUTED_VALUE"""),0.0) -> 0 | AW62: =IFERROR(__xludf.DUMMYFUNCTION("""COMPUTED_VALUE"""),0.0) -> 0 | AX62: =IFERROR(__xludf.DUMMYFUNCTION("""COMPUTED_VALUE"""),0.0) -> 0 | AY62: =IFERROR(__xludf.DUMMYFUNCTION("""COMPUTED_VALUE"""),"Hubster") -> Hubster | AZ62: =IFERROR(__xludf.DUMMYFUNCTION("""COMPUTED_VALUE"""),"Sorvetes") -> Sorvetes | BA62: =IFERROR(__xludf.DUMMYFUNCTION("""COMPUTED_VALUE"""),28.0) -> 28 | BB62: =IFERROR(__xludf.DUMMYFUNCTION("""COMPUTED_VALUE"""),"Varejo - Cookies Artesanais") -> Varejo - Cookies Artesanais | BC62: =IFERROR(__xludf.DUMMYFUNCTION("""COMPUTED_VALUE"""),"Nacional (CE, PE, SP, PA, MA, PI)") -> Nacional (CE, PE, SP, PA, MA, PI) | BD62: =IFERROR(__xludf.DUMMYFUNCTION("""COMPUTED_VALUE"""),"Dado não disponível publicamente - Necessário Discovery") -> Dado não disponível publicamente - Necessário Discovery | BE62: =IFERROR(__xludf.DUMMYFUNCTION("""COMPUTED_VALUE"""),40.0) -> 40 | BF62: =IFERROR(__xludf.DUMMYFUNCTION("""COMPUTED_VALUE"""),0.55) -> 0.55 | BG62: =IFERROR(__xludf.DUMMYFUNCTION("""COMPUTED_VALUE"""),"Aderência moderada ao 3S: PDV atual não identificado. 3S pode agregar valor com padronização multi-loja e integração delivery, mas necessário Discovery para validar fit completo.") -> Aderência moderada ao 3S: PDV atual não identificado. 3S pode agregar valor com padronização multi-loja e integração delivery, mas necessário Discovery para validar fit completo.
A63: =IFERROR(__xludf.DUMMYFUNCTION("""COMPUTED_VALUE"""),"COXA COXINHA") -> COXA COXINHA | B63: =IFERROR(__xludf.DUMMYFUNCTION("""COMPUTED_VALUE"""),"João Biagiotti") -> João Biagiotti | C63: =IFERROR(__xludf.DUMMYFUNCTION("""COMPUTED_VALUE"""),"Diego Santos") -> Diego Santos | D63: =IFERROR(__xludf.DUMMYFUNCTION("""COMPUTED_VALUE"""),"2. Primeiro Contato com a marca") -> 2. Primeiro Contato com a marca | E63: =IFERROR(__xludf.DUMMYFUNCTION("""COMPUTED_VALUE"""),"Parceiro - Aguardando retorno parceiro") -> Parceiro - Aguardando retorno parceiro | F63: =IFERROR(__xludf.DUMMYFUNCTION("""COMPUTED_VALUE"""),"P") -> P | G63: =IFERROR(__xludf.DUMMYFUNCTION("""COMPUTED_VALUE"""),46153.0) -> 46153 | H63: =IFERROR(__xludf.DUMMYFUNCTION("""COMPUTED_VALUE"""),"Enviei mensagem para a Renata, aguardando retorno") -> Enviei mensagem para a Renata, aguardando retorno | I63: =IFERROR(__xludf.DUMMYFUNCTION("""COMPUTED_VALUE"""),46134.45362503472) -> 46134.454 | J63: =IFERROR(__xludf.DUMMYFUNCTION("""COMPUTED_VALUE"""),46153.67651640046) -> 46153.677 | AA63: =IFERROR(__xludf.DUMMYFUNCTION("""COMPUTED_VALUE"""),9.0) -> 9 | AB63: =IFERROR(__xludf.DUMMYFUNCTION("""COMPUTED_VALUE"""),"CE") -> CE | AC63: =IFERROR(__xludf.DUMMYFUNCTION("""COMPUTED_VALUE"""),"Sim") -> Sim | AD63: =IFERROR(__xludf.DUMMYFUNCTION("""COMPUTED_VALUE"""),"Ifood") -> Ifood | AM63: =IFERROR(__xludf.DUMMYFUNCTION("""COMPUTED_VALUE"""),"FY27") -> FY27 | AO63: =IFERROR(__xludf.DUMMYFUNCTION("""COMPUTED_VALUE"""),62.0) -> 62 | AP63: =IFERROR(__xludf.DUMMYFUNCTION("""COMPUTED_VALUE"""),"BA") -> BA | AQ63: =IFERROR(__xludf.DUMMYFUNCTION("""COMPUTED_VALUE"""),"VIDOLIN EDUARDO") -> VIDOLIN EDUARDO | AR63: =IFERROR(__xludf.DUMMYFUNCTION("""COMPUTED_VALUE"""),"VALERIA VASCONCELOS") -> VALERIA VASCONCELOS | AS63: =IFERROR(__xludf.DUMMYFUNCTION("""COMPUTED_VALUE"""),"THIAGO ROMAGNOLE") -> THIAGO ROMAGNOLE | AT63: =IFERROR(__xludf.DUMMYFUNCTION("""COMPUTED_VALUE"""),"EDUARDO VAZ") -> EDUARDO VAZ | AU63: =IFERROR(__xludf.DUMMYFUNCTION("""COMPUTED_VALUE"""),0.0) -> 0 | AV63: =IFERROR(__xludf.DUMMYFUNCTION("""COMPUTED_VALUE"""),0.0) -> 0 | AW63: =IFERROR(__xludf.DUMMYFUNCTION("""COMPUTED_VALUE"""),0.0) -> 0 | AX63: =IFERROR(__xludf.DUMMYFUNCTION("""COMPUTED_VALUE"""),0.0) -> 0 | AZ63: =IFERROR(__xludf.DUMMYFUNCTION("""COMPUTED_VALUE"""),"Lanches") -> Lanches | BA63: =IFERROR(__xludf.DUMMYFUNCTION("""COMPUTED_VALUE"""),27.0) -> 27 | BB63: =IFERROR(__xludf.DUMMYFUNCTION("""COMPUTED_VALUE"""),"QSR - Salgados") -> QSR - Salgados | BC63: =IFERROR(__xludf.DUMMYFUNCTION("""COMPUTED_VALUE"""),"Sudeste") -> Sudeste | BD63: =IFERROR(__xludf.DUMMYFUNCTION("""COMPUTED_VALUE"""),"Dado não disponível publicamente - Necessário Discovery") -> Dado não disponível publicamente - Necessário Discovery | BE63: =IFERROR(__xludf.DUMMYFUNCTION("""COMPUTED_VALUE"""),70.0) -> 70 | BF63: =IFERROR(__xludf.DUMMYFUNCTION("""COMPUTED_VALUE"""),0.85) -> 0.85 | BG63: =IFERROR(__xludf.DUMMYFUNCTION("""COMPUTED_VALUE"""),"Alta aderência ao 3S: PDV atual não identificado. 3S oferece Kiosk nativo, Hub Delivery integrado e gestão centralizada multi-loja - diferenciais competitivos para expansão e redução de filas.") -> Alta aderência ao 3S: PDV atual não identificado. 3S oferece Kiosk nativo, Hub Delivery integrado e gestão centralizada multi-loja - diferenciais competitivos para expansão e redução de filas.
A64: =IFERROR(__xludf.DUMMYFUNCTION("""COMPUTED_VALUE"""),"COXINHA DO GAGO") -> COXINHA DO GAGO | B64: =IFERROR(__xludf.DUMMYFUNCTION("""COMPUTED_VALUE"""),"João Biagiotti") -> João Biagiotti | C64: =IFERROR(__xludf.DUMMYFUNCTION("""COMPUTED_VALUE"""),"Diego Santos") -> Diego Santos | D64: =IFERROR(__xludf.DUMMYFUNCTION("""COMPUTED_VALUE"""),"2. Primeiro Contato com a marca") -> 2. Primeiro Contato com a marca | E64: =IFERROR(__xludf.DUMMYFUNCTION("""COMPUTED_VALUE"""),"Parceiro - Conciliação agenda") -> Parceiro - Conciliação agenda | F64: =IFERROR(__xludf.DUMMYFUNCTION("""COMPUTED_VALUE"""),"P") -> P | G64: =IFERROR(__xludf.DUMMYFUNCTION("""COMPUTED_VALUE"""),46153.0) -> 46153 | H64: =IFERROR(__xludf.DUMMYFUNCTION("""COMPUTED_VALUE"""),"Estou conversando com o Gago, estamos agendando um papo em conjunto com a agenda de delivery ") -> Estou conversando com o Gago, estamos agendando um papo em conjunto com a agenda de delivery | I64: =IFERROR(__xludf.DUMMYFUNCTION("""COMPUTED_VALUE"""),46134.45472222222) -> 46134.455 | J64: =IFERROR(__xludf.DUMMYFUNCTION("""COMPUTED_VALUE"""),46153.67420826389) -> 46153.674 | AA64: =IFERROR(__xludf.DUMMYFUNCTION("""COMPUTED_VALUE"""),10.0) -> 10 | AB64: =IFERROR(__xludf.DUMMYFUNCTION("""COMPUTED_VALUE"""),"CE") -> CE | AC64: =IFERROR(__xludf.DUMMYFUNCTION("""COMPUTED_VALUE"""),"Sim") -> Sim | AD64: =IFERROR(__xludf.DUMMYFUNCTION("""COMPUTED_VALUE"""),"Ifood") -> Ifood | AM64: =IFERROR(__xludf.DUMMYFUNCTION("""COMPUTED_VALUE"""),"FY27") -> FY27 | AO64: =IFERROR(__xludf.DUMMYFUNCTION("""COMPUTED_VALUE"""),62.0) -> 62 | AP64: =IFERROR(__xludf.DUMMYFUNCTION("""COMPUTED_VALUE"""),"BA") -> BA | AQ64: =IFERROR(__xludf.DUMMYFUNCTION("""COMPUTED_VALUE"""),"MENEZES PAULA") -> MENEZES PAULA | AR64: =IFERROR(__xludf.DUMMYFUNCTION("""COMPUTED_VALUE"""),"LAIS CARDOSO") -> LAIS CARDOSO | AS64: =IFERROR(__xludf.DUMMYFUNCTION("""COMPUTED_VALUE"""),"THIAGO ROMAGNOLE") -> THIAGO ROMAGNOLE | AT64: =IFERROR(__xludf.DUMMYFUNCTION("""COMPUTED_VALUE"""),"EDUARDO VAZ") -> EDUARDO VAZ | AU64: =IFERROR(__xludf.DUMMYFUNCTION("""COMPUTED_VALUE"""),0.0) -> 0 | AV64: =IFERROR(__xludf.DUMMYFUNCTION("""COMPUTED_VALUE"""),0.0) -> 0 | AW64: =IFERROR(__xludf.DUMMYFUNCTION("""COMPUTED_VALUE"""),0.0) -> 0 | AX64: =IFERROR(__xludf.DUMMYFUNCTION("""COMPUTED_VALUE"""),0.0) -> 0 | AY64: =IFERROR(__xludf.DUMMYFUNCTION("""COMPUTED_VALUE"""),"Alpha Logo") -> Alpha Logo | AZ64: =IFERROR(__xludf.DUMMYFUNCTION("""COMPUTED_VALUE"""),"Lanches") -> Lanches | BA64: =IFERROR(__xludf.DUMMYFUNCTION("""COMPUTED_VALUE"""),19.0) -> 19 | BB64: =IFERROR(__xludf.DUMMYFUNCTION("""COMPUTED_VALUE"""),"QSR - Salgados") -> QSR - Salgados | BC64: =IFERROR(__xludf.DUMMYFUNCTION("""COMPUTED_VALUE"""),"Sul") -> Sul | BD64: =IFERROR(__xludf.DUMMYFUNCTION("""COMPUTED_VALUE"""),"Dado não disponível publicamente - Necessário Discovery") -> Dado não disponível publicamente - Necessário Discovery | BE64: =IFERROR(__xludf.DUMMYFUNCTION("""COMPUTED_VALUE"""),70.0) -> 70 | BF64: =IFERROR(__xludf.DUMMYFUNCTION("""COMPUTED_VALUE"""),0.85) -> 0.85 | BG64: =IFERROR(__xludf.DUMMYFUNCTION("""COMPUTED_VALUE"""),"Alta aderência ao 3S: PDV atual não identificado. 3S oferece Kiosk nativo, Hub Delivery integrado e gestão centralizada multi-loja - diferenciais competitivos para expansão e redução de filas.") -> Alta aderência ao 3S: PDV atual não identificado. 3S oferece Kiosk nativo, Hub Delivery integrado e gestão centralizada multi-loja - diferenciais competitivos para expansão e redução de filas. | BH64: Alpha Logo | BI64: 0.66666667
A65: =IFERROR(__xludf.DUMMYFUNCTION("""COMPUTED_VALUE"""),"CRUZEIROS") -> CRUZEIROS | B65: =IFERROR(__xludf.DUMMYFUNCTION("""COMPUTED_VALUE"""),"João Biagiotti") -> João Biagiotti | C65: =IFERROR(__xludf.DUMMYFUNCTION("""COMPUTED_VALUE"""),"Diego Santos") -> Diego Santos | D65: =IFERROR(__xludf.DUMMYFUNCTION("""COMPUTED_VALUE"""),"0. Não Iniciado") -> 0. Não Iniciado | F65: =IFERROR(__xludf.DUMMYFUNCTION("""COMPUTED_VALUE"""),"P") -> P | AA65: =IFERROR(__xludf.DUMMYFUNCTION("""COMPUTED_VALUE"""),12.0) -> 12 | AB65: =IFERROR(__xludf.DUMMYFUNCTION("""COMPUTED_VALUE"""),"CE") -> CE | AC65: =IFERROR(__xludf.DUMMYFUNCTION("""COMPUTED_VALUE"""),"Sim") -> Sim | AD65: =IFERROR(__xludf.DUMMYFUNCTION("""COMPUTED_VALUE"""),0.0) -> 0 | AM65: =IFERROR(__xludf.DUMMYFUNCTION("""COMPUTED_VALUE"""),"FY27") -> FY27 | AO65: =IFERROR(__xludf.DUMMYFUNCTION("""COMPUTED_VALUE"""),45553.0) -> 45553 | AP65: =IFERROR(__xludf.DUMMYFUNCTION("""COMPUTED_VALUE"""),"SP") -> SP | AQ65: =IFERROR(__xludf.DUMMYFUNCTION("""COMPUTED_VALUE"""),"RODRIGO ALBANESE") -> RODRIGO ALBANESE | AR65: =IFERROR(__xludf.DUMMYFUNCTION("""COMPUTED_VALUE"""),"PALOMA BRUNIALTI") -> PALOMA BRUNIALTI | AS65: =IFERROR(__xludf.DUMMYFUNCTION("""COMPUTED_VALUE"""),"NATHALIE MERTENS") -> NATHALIE MERTENS | AT65: =IFERROR(__xludf.DUMMYFUNCTION("""COMPUTED_VALUE"""),"MATHEUS LESSA") -> MATHEUS LESSA | AU65: =IFERROR(__xludf.DUMMYFUNCTION("""COMPUTED_VALUE"""),0.0) -> 0 | AV65: =IFERROR(__xludf.DUMMYFUNCTION("""COMPUTED_VALUE"""),0.0) -> 0 | AW65: =IFERROR(__xludf.DUMMYFUNCTION("""COMPUTED_VALUE"""),0.0) -> 0 | AX65: =IFERROR(__xludf.DUMMYFUNCTION("""COMPUTED_VALUE"""),0.0) -> 0 | AZ65: =IFERROR(__xludf.DUMMYFUNCTION("""COMPUTED_VALUE"""),"Brasileira") -> Brasileira | BA65: =IFERROR(__xludf.DUMMYFUNCTION("""COMPUTED_VALUE"""),61.0) -> 61 | BB65: =IFERROR(__xludf.DUMMYFUNCTION("""COMPUTED_VALUE"""),"Fast Casual - Multi-conceito") -> Fast Casual - Multi-conceito | BC65: =IFERROR(__xludf.DUMMYFUNCTION("""COMPUTED_VALUE"""),"Nordeste") -> Nordeste | BD65: =IFERROR(__xludf.DUMMYFUNCTION("""COMPUTED_VALUE"""),"Dado não disponível publicamente - Necessário Discovery") -> Dado não disponível publicamente - Necessário Discovery | BE65: =IFERROR(__xludf.DUMMYFUNCTION("""COMPUTED_VALUE"""),70.0) -> 70 | BF65: =IFERROR(__xludf.DUMMYFUNCTION("""COMPUTED_VALUE"""),0.75) -> 0.75 | BG65: =IFERROR(__xludf.DUMMYFUNCTION("""COMPUTED_VALUE"""),"Aderência forte ao 3S: PDV atual não identificado. 3S oferece PDV robusto, KDS integrado e mobilidade (3SGO) para gestão em tempo real - ideal para operações multi-canal.") -> Aderência forte ao 3S: PDV atual não identificado. 3S oferece PDV robusto, KDS integrado e mobilidade (3SGO) para gestão em tempo real - ideal para operações multi-canal.
A66: =IFERROR(__xludf.DUMMYFUNCTION("""COMPUTED_VALUE"""),"CULINARIA MINEIRA") -> CULINARIA MINEIRA | B66: =IFERROR(__xludf.DUMMYFUNCTION("""COMPUTED_VALUE"""),"Lídia Esteves") -> Lídia Esteves | C66: =IFERROR(__xludf.DUMMYFUNCTION("""COMPUTED_VALUE"""),"Gabriela Roma") -> Gabriela Roma | D66: =IFERROR(__xludf.DUMMYFUNCTION("""COMPUTED_VALUE"""),"0. Não Iniciado") -> 0. Não Iniciado | F66: =IFERROR(__xludf.DUMMYFUNCTION("""COMPUTED_VALUE"""),"P") -> P | AA66: =IFERROR(__xludf.DUMMYFUNCTION("""COMPUTED_VALUE"""),6.0) -> 6 | AB66: =IFERROR(__xludf.DUMMYFUNCTION("""COMPUTED_VALUE"""),"CE") -> CE | AC66: =IFERROR(__xludf.DUMMYFUNCTION("""COMPUTED_VALUE"""),"Sim") -> Sim | AD66: =IFERROR(__xludf.DUMMYFUNCTION("""COMPUTED_VALUE"""),"Ifood") -> Ifood | AM66: =IFERROR(__xludf.DUMMYFUNCTION("""COMPUTED_VALUE"""),"FY27") -> FY27 | AO66: =IFERROR(__xludf.DUMMYFUNCTION("""COMPUTED_VALUE"""),45553.0) -> 45553 | AP66: =IFERROR(__xludf.DUMMYFUNCTION("""COMPUTED_VALUE"""),"SP") -> SP | AQ66: =IFERROR(__xludf.DUMMYFUNCTION("""COMPUTED_VALUE"""),"ISADORA GARCIA") -> ISADORA GARCIA | AR66: =IFERROR(__xludf.DUMMYFUNCTION("""COMPUTED_VALUE"""),"LEANDRO SERPA") -> LEANDRO SERPA | AS66: =IFERROR(__xludf.DUMMYFUNCTION("""COMPUTED_VALUE"""),"NATHALIE MERTENS") -> NATHALIE MERTENS | AT66: =IFERROR(__xludf.DUMMYFUNCTION("""COMPUTED_VALUE"""),"MATHEUS LESSA") -> MATHEUS LESSA | AU66: =IFERROR(__xludf.DUMMYFUNCTION("""COMPUTED_VALUE"""),0.0) -> 0 | AV66: =IFERROR(__xludf.DUMMYFUNCTION("""COMPUTED_VALUE"""),0.0) -> 0 | AW66: =IFERROR(__xludf.DUMMYFUNCTION("""COMPUTED_VALUE"""),0.0) -> 0 | AX66: =IFERROR(__xludf.DUMMYFUNCTION("""COMPUTED_VALUE"""),0.0) -> 0 | AZ66: =IFERROR(__xludf.DUMMYFUNCTION("""COMPUTED_VALUE"""),"Brasileira") -> Brasileira | BA66: =IFERROR(__xludf.DUMMYFUNCTION("""COMPUTED_VALUE"""),"") | BB66: =IFERROR(__xludf.DUMMYFUNCTION("""COMPUTED_VALUE"""),"") | BC66: =IFERROR(__xludf.DUMMYFUNCTION("""COMPUTED_VALUE"""),"") | BD66: =IFERROR(__xludf.DUMMYFUNCTION("""COMPUTED_VALUE"""),"") | BE66: =IFERROR(__xludf.DUMMYFUNCTION("""COMPUTED_VALUE"""),"") | BF66: =IFERROR(__xludf.DUMMYFUNCTION("""COMPUTED_VALUE"""),"") | BG66: =IFERROR(__xludf.DUMMYFUNCTION("""COMPUTED_VALUE"""),"")
A67: =IFERROR(__xludf.DUMMYFUNCTION("""COMPUTED_VALUE"""),"D QUENTINHAS") -> D QUENTINHAS | B67: =IFERROR(__xludf.DUMMYFUNCTION("""COMPUTED_VALUE"""),"João Biagiotti") -> João Biagiotti | C67: =IFERROR(__xludf.DUMMYFUNCTION("""COMPUTED_VALUE"""),"Diego Santos") -> Diego Santos | D67: =IFERROR(__xludf.DUMMYFUNCTION("""COMPUTED_VALUE"""),"0. Não Iniciado") -> 0. Não Iniciado | F67: =IFERROR(__xludf.DUMMYFUNCTION("""COMPUTED_VALUE"""),"P") -> P | AA67: =IFERROR(__xludf.DUMMYFUNCTION("""COMPUTED_VALUE"""),10.0) -> 10 | AB67: =IFERROR(__xludf.DUMMYFUNCTION("""COMPUTED_VALUE"""),"CE") -> CE | AC67: =IFERROR(__xludf.DUMMYFUNCTION("""COMPUTED_VALUE"""),"Sim") -> Sim | AD67: =IFERROR(__xludf.DUMMYFUNCTION("""COMPUTED_VALUE"""),0.0) -> 0 | AM67: =IFERROR(__xludf.DUMMYFUNCTION("""COMPUTED_VALUE"""),"FY27") -> FY27 | AO67: =IFERROR(__xludf.DUMMYFUNCTION("""COMPUTED_VALUE"""),45553.0) -> 45553 | AP67: =IFERROR(__xludf.DUMMYFUNCTION("""COMPUTED_VALUE"""),0.0) -> 0 | AQ67: =IFERROR(__xludf.DUMMYFUNCTION("""COMPUTED_VALUE"""),0.0) -> 0 | AR67: =IFERROR(__xludf.DUMMYFUNCTION("""COMPUTED_VALUE"""),0.0) -> 0 | AS67: =IFERROR(__xludf.DUMMYFUNCTION("""COMPUTED_VALUE"""),0.0) -> 0 | AT67: =IFERROR(__xludf.DUMMYFUNCTION("""COMPUTED_VALUE"""),0.0) -> 0 | AU67: =IFERROR(__xludf.DUMMYFUNCTION("""COMPUTED_VALUE"""),0.0) -> 0 | AV67: =IFERROR(__xludf.DUMMYFUNCTION("""COMPUTED_VALUE"""),0.0) -> 0 | AW67: =IFERROR(__xludf.DUMMYFUNCTION("""COMPUTED_VALUE"""),0.0) -> 0 | AX67: =IFERROR(__xludf.DUMMYFUNCTION("""COMPUTED_VALUE"""),0.0) -> 0 | AZ67: =IFERROR(__xludf.DUMMYFUNCTION("""COMPUTED_VALUE"""),"Lanches") -> Lanches | BA67: =IFERROR(__xludf.DUMMYFUNCTION("""COMPUTED_VALUE"""),32.0) -> 32 | BB67: =IFERROR(__xludf.DUMMYFUNCTION("""COMPUTED_VALUE"""),"QSR - Comida Caseira") -> QSR - Comida Caseira | BC67: =IFERROR(__xludf.DUMMYFUNCTION("""COMPUTED_VALUE"""),"Rio de Janeiro/RJ") -> Rio de Janeiro/RJ | BD67: =IFERROR(__xludf.DUMMYFUNCTION("""COMPUTED_VALUE"""),"Dado não disponível publicamente - Necessário Discovery") -> Dado não disponível publicamente - Necessário Discovery | BE67: =IFERROR(__xludf.DUMMYFUNCTION("""COMPUTED_VALUE"""),70.0) -> 70 | BF67: =IFERROR(__xludf.DUMMYFUNCTION("""COMPUTED_VALUE"""),0.85) -> 0.85 | BG67: =IFERROR(__xludf.DUMMYFUNCTION("""COMPUTED_VALUE"""),"Alta aderência ao 3S: PDV atual não identificado. 3S oferece Kiosk nativo, Hub Delivery integrado e gestão centralizada multi-loja - diferenciais competitivos para expansão e redução de filas.") -> Alta aderência ao 3S: PDV atual não identificado. 3S oferece Kiosk nativo, Hub Delivery integrado e gestão centralizada multi-loja - diferenciais competitivos para expansão e redução de filas.
A68: =IFERROR(__xludf.DUMMYFUNCTION("""COMPUTED_VALUE"""),"DA PRI") -> DA PRI | B68: =IFERROR(__xludf.DUMMYFUNCTION("""COMPUTED_VALUE"""),"Lídia Esteves") -> Lídia Esteves | C68: =IFERROR(__xludf.DUMMYFUNCTION("""COMPUTED_VALUE"""),"Gabriela Roma") -> Gabriela Roma | D68: =IFERROR(__xludf.DUMMYFUNCTION("""COMPUTED_VALUE"""),"0. Não Iniciado") -> 0. Não Iniciado | F68: =IFERROR(__xludf.DUMMYFUNCTION("""COMPUTED_VALUE"""),"P") -> P | AA68: =IFERROR(__xludf.DUMMYFUNCTION("""COMPUTED_VALUE"""),8.0) -> 8 | AB68: =IFERROR(__xludf.DUMMYFUNCTION("""COMPUTED_VALUE"""),"CE") -> CE | AC68: =IFERROR(__xludf.DUMMYFUNCTION("""COMPUTED_VALUE"""),"Sim") -> Sim | AD68: =IFERROR(__xludf.DUMMYFUNCTION("""COMPUTED_VALUE"""),0.0) -> 0 | AM68: =IFERROR(__xludf.DUMMYFUNCTION("""COMPUTED_VALUE"""),"FY27") -> FY27 | AO68: =IFERROR(__xludf.DUMMYFUNCTION("""COMPUTED_VALUE"""),45553.0) -> 45553 | AP68: =IFERROR(__xludf.DUMMYFUNCTION("""COMPUTED_VALUE"""),"ES") -> ES | AQ68: =IFERROR(__xludf.DUMMYFUNCTION("""COMPUTED_VALUE"""),"LORENA PACHECO") -> LORENA PACHECO | AR68: =IFERROR(__xludf.DUMMYFUNCTION("""COMPUTED_VALUE"""),"MARLON PEREIRA") -> MARLON PEREIRA | AS68: =IFERROR(__xludf.DUMMYFUNCTION("""COMPUTED_VALUE"""),"FABIO DONATO") -> FABIO DONATO | AT68: =IFERROR(__xludf.DUMMYFUNCTION("""COMPUTED_VALUE"""),"GILSON JUNIOR") -> GILSON JUNIOR | AU68: =IFERROR(__xludf.DUMMYFUNCTION("""COMPUTED_VALUE"""),0.0) -> 0 | AV68: =IFERROR(__xludf.DUMMYFUNCTION("""COMPUTED_VALUE"""),0.0) -> 0 | AW68: =IFERROR(__xludf.DUMMYFUNCTION("""COMPUTED_VALUE"""),0.0) -> 0 | AX68: =IFERROR(__xludf.DUMMYFUNCTION("""COMPUTED_VALUE"""),0.0) -> 0 | AZ68: =IFERROR(__xludf.DUMMYFUNCTION("""COMPUTED_VALUE"""),"Doces & Bolos") -> Doces & Bolos | BA68: =IFERROR(__xludf.DUMMYFUNCTION("""COMPUTED_VALUE"""),62.0) -> 62 | BB68: =IFERROR(__xludf.DUMMYFUNCTION("""COMPUTED_VALUE"""),"Fast Casual - Multi-conceito") -> Fast Casual - Multi-conceito | BC68: =IFERROR(__xludf.DUMMYFUNCTION("""COMPUTED_VALUE"""),"Rio de Janeiro/RJ") -> Rio de Janeiro/RJ | BD68: =IFERROR(__xludf.DUMMYFUNCTION("""COMPUTED_VALUE"""),"Dado não disponível publicamente - Necessário Discovery") -> Dado não disponível publicamente - Necessário Discovery | BE68: =IFERROR(__xludf.DUMMYFUNCTION("""COMPUTED_VALUE"""),70.0) -> 70 | BF68: =IFERROR(__xludf.DUMMYFUNCTION("""COMPUTED_VALUE"""),0.75) -> 0.75 | BG68: =IFERROR(__xludf.DUMMYFUNCTION("""COMPUTED_VALUE"""),"Aderência forte ao 3S: PDV atual não identificado. 3S oferece PDV robusto, KDS integrado e mobilidade (3SGO) para gestão em tempo real - ideal para operações multi-canal.") -> Aderência forte ao 3S: PDV atual não identificado. 3S oferece PDV robusto, KDS integrado e mobilidade (3SGO) para gestão em tempo real - ideal para operações multi-canal. | BH68: Yooga | BI68: 1
A69: =IFERROR(__xludf.DUMMYFUNCTION("""COMPUTED_VALUE"""),"DALLE PIZZA") -> DALLE PIZZA | B69: =IFERROR(__xludf.DUMMYFUNCTION("""COMPUTED_VALUE"""),"Lídia Esteves") -> Lídia Esteves | C69: =IFERROR(__xludf.DUMMYFUNCTION("""COMPUTED_VALUE"""),"Gabriela Roma") -> Gabriela Roma | D69: =IFERROR(__xludf.DUMMYFUNCTION("""COMPUTED_VALUE"""),"2. Primeiro Contato com a marca") -> 2. Primeiro Contato com a marca | E69: =IFERROR(__xludf.DUMMYFUNCTION("""COMPUTED_VALUE"""),"Delivery - Aguardando retorno / Conciliação agenda") -> Delivery - Aguardando retorno / Conciliação agenda | F69: =IFERROR(__xludf.DUMMYFUNCTION("""COMPUTED_VALUE"""),"P") -> P | I69: =IFERROR(__xludf.DUMMYFUNCTION("""COMPUTED_VALUE"""),46121.67424068287) -> 46121.674 | J69: =IFERROR(__xludf.DUMMYFUNCTION("""COMPUTED_VALUE"""),46139.72439533565) -> 46139.724 | AA69: =IFERROR(__xludf.DUMMYFUNCTION("""COMPUTED_VALUE"""),10.0) -> 10 | AB69: =IFERROR(__xludf.DUMMYFUNCTION("""COMPUTED_VALUE"""),"CE") -> CE | AC69: =IFERROR(__xludf.DUMMYFUNCTION("""COMPUTED_VALUE"""),"Sim") -> Sim | AD69: =IFERROR(__xludf.DUMMYFUNCTION("""COMPUTED_VALUE"""),0.0) -> 0 | AM69: =IFERROR(__xludf.DUMMYFUNCTION("""COMPUTED_VALUE"""),"FY27") -> FY27 | AO69: =IFERROR(__xludf.DUMMYFUNCTION("""COMPUTED_VALUE"""),45553.0) -> 45553 | AP69: =IFERROR(__xludf.DUMMYFUNCTION("""COMPUTED_VALUE"""),"PR") -> PR | AQ69: =IFERROR(__xludf.DUMMYFUNCTION("""COMPUTED_VALUE"""),"PAULA VERDASCA") -> PAULA VERDASCA | AR69: =IFERROR(__xludf.DUMMYFUNCTION("""COMPUTED_VALUE"""),0.0) -> 0 | AS69: =IFERROR(__xludf.DUMMYFUNCTION("""COMPUTED_VALUE"""),0.0) -> 0 | AT69: =IFERROR(__xludf.DUMMYFUNCTION("""COMPUTED_VALUE"""),0.0) -> 0 | AU69: =IFERROR(__xludf.DUMMYFUNCTION("""COMPUTED_VALUE"""),0.0) -> 0 | AV69: =IFERROR(__xludf.DUMMYFUNCTION("""COMPUTED_VALUE"""),0.0) -> 0 | AW69: =IFERROR(__xludf.DUMMYFUNCTION("""COMPUTED_VALUE"""),0.0) -> 0 | AX69: =IFERROR(__xludf.DUMMYFUNCTION("""COMPUTED_VALUE"""),0.0) -> 0 | AZ69: =IFERROR(__xludf.DUMMYFUNCTION("""COMPUTED_VALUE"""),"Pizza") -> Pizza | BA69: =IFERROR(__xludf.DUMMYFUNCTION("""COMPUTED_VALUE"""),85.0) -> 85 | BB69: =IFERROR(__xludf.DUMMYFUNCTION("""COMPUTED_VALUE"""),"Fast Casual - Pizzaria") -> Fast Casual - Pizzaria | BC69: =IFERROR(__xludf.DUMMYFUNCTION("""COMPUTED_VALUE"""),"Sudeste") -> Sudeste | BD69: =IFERROR(__xludf.DUMMYFUNCTION("""COMPUTED_VALUE"""),"Dado não disponível publicamente - Necessário Discovery") -> Dado não disponível publicamente - Necessário Discovery | BE69: =IFERROR(__xludf.DUMMYFUNCTION("""COMPUTED_VALUE"""),70.0) -> 70 | BF69: =IFERROR(__xludf.DUMMYFUNCTION("""COMPUTED_VALUE"""),0.75) -> 0.75 | BG69: =IFERROR(__xludf.DUMMYFUNCTION("""COMPUTED_VALUE"""),"Aderência forte ao 3S: PDV atual não identificado. 3S oferece PDV robusto, KDS integrado e mobilidade (3SGO) para gestão em tempo real - ideal para operações multi-canal.") -> Aderência forte ao 3S: PDV atual não identificado. 3S oferece PDV robusto, KDS integrado e mobilidade (3SGO) para gestão em tempo real - ideal para operações multi-canal.
